Workbook

Sheet BRAYAN
A1: CONCEPTO | B1: VALOR | C1: ENERO | D1: FEBRERO | E1: MARZO | F1: ABRIL | G1: MAYO | H1: JUNIO | I1: JULIO | J1: AGOSTO | K1: SEPTIEMBRE | L1: OCTUBRE | M1: NOVIEMBRE | N1: DICIEMBRE | O1: ENERO | P1: FEBRERO | Q1: MARZO | R1: ABRIL | S1: MAYO | T1: JUNIO | U1: JULIO | V1: AGOSTO | W1: SEPTIEMBRE | X1: OCTUBRE | Y1: NOVIEMBRE | Z1: DICIEMBRE | AA1: ENERO | AB1: FEBRERO | AC1: MARZO | AD1: ABRIL | AE1: MAYO | AF1: JUNIO | AG1: JULIO | AH1: AGOSTO | AI1: SEPTIEMBRE | AJ1: OCTUBRE | AK1: NOVIEMBRE | AL1: DICIEMBRE | AM1: ENERO | AN1: FEBRERO | AO1: MARZO | AP1: ABRIL | AQ1: MAYO | AR1: JUNIO | AS1: JULIO | AT1: AGOSTO | AU1: SEPTIEMBRE | AV1: OCTUBRE | AW1: NOVIEMBRE | AX1: DICIEMBRE | AY1: ENERO | AZ1: FEBRERO | BA1: MARZO | BB1: ABRIL | BC1: MAYO | BD1: JUNIO | BE1: JULIO | BF1: AGOSTO | BG1: SEPTIEMBRE | BH1: OCTUBRE | BI1: NOVIEMBRE | BJ1: DICIEMBRE | BK1: ENERO | BL1: FEBRERO | BM1: MARZO | BN1: ABRIL | BO1: MAYO | BP1: JUNIO | BQ1: JULIO | BR1: AGOSTO | BS1: SEPTIEMBRE | BT1: OCTUBRE | BU1: NOVIEMBRE | BV1: DICIEMBRE | BW1: ENERO | BX1: FEBRERO | BY1: MARZO | BZ1: ABRIL | CA1: MAYO | CB1: JUNIO | CD1: DEUDA | CE1: % | CI1: GASTOS | CJ1: VALOR
A2: SEGURIDAD SOCIAL | B2: 1000000 | C2: 1113000 | D2: 1588000 | E2: 1732000 | F2: 1422000 | G2: 1000000 | H2: 1000000 | I2: 1500000 | J2: 1800000 | K2: 3100000 | L2: 2708500 | M2: 2800000 | N2: 2553300 | O2: 3033000 | P2: 3500000 | Q2: 2500000 | R2: 3740000 | S2: 2500000 | T2: 3050000 | U2: 4890000 | V2: 4000000 | W2: 3800000 | X2: 4000000 | Y2: 3750000 | Z2: 4500000 | AA2: 6000000 | AB2: 4700000 | AC2: 5000000 | AD2: 5000000 | AE2: 4000000 | AF2: 5500000 | AG2: 3800000 | AH2: 4500000 | AI2: 5000000 | AJ2: 4500000 | AK2: 7000000 | AL2: 10000000 | AM2: 6000000 | AN2: 6800000 | AO2: 7000000 | AP2: 8000000 | AQ2: 5500000 | AR2: 7000000 | AS2: 7000000 | AT2: 7000000 | AU2: 7000000 | AV2: 10000000 | AW2: 8000000 | AX2: 10000000 | AY2: 5000000 | AZ2: 7000000 | BA2: 6000000 | BB2: 6470000 | BC2: 5500000 | BD2: 4700000 | BE2: 8000000 | BF2: 6200000 | BG2: 6000000 | BH2: 7000000 | BI2: 5000000 | BJ2: 7000000 | BK2: 5000000 | BL2: 7000000 | BM2: 6000000 | BN2: 5700000 | BO2: 6500000 | BP2: 5000000 | BQ2: 7500000 | BR2: 6000000 | BS2: 9000000 | BT2: 4500000 | BU2: 4500000 | BV2: 6000000 | BW2: 5600000 | BX2: 4500000 | BY2: 7000000 | BZ2: 6000000 | CA2: 7000000 | CI2: Arriendo | CJ2: 700000
A3: FECOP | B3: 3500000 | BK3: 0 | BL3: 0 | BM3: 3700000 | BN3: 3996000 | BO3: 3848000 | BP3: 3878000 | BQ3: 3992000 | BR3: 4188000 | BS3: 4133000 | BT3: 4506000 | BU3: 4391000 | BV3: 4314000
A4: Megamudanzas CAMIONES | B4: 0 | C4: 0 | D4: 0 | E4: 0 | F4: 0 | G4: 0 | H4: 0 | I4: 0 | J4: 0 | K4: 0 | L4: 0 | M4: 2550000 | N4: 2500000 | O4: 2500000 | P4: 650000 | Q4: 1500000 | R4: 700000 | S4: 1150000 | T4: 2000000 | U4: 2250000 | V4: 2500000 | W4: 2500000 | X4: 2500000 | Y4: 2500000 | Z4: 2500000 | AA4: 2000000 | AB4: 2000000 | AC4: 2000000 | AD4: 2000000 | AE4: 2000000 | AF4: 2500000 | AG4: 2500000 | AH4: 2500000 | AI4: 2500000 | AJ4: 2200000 | AK4: 2500000 | AL4: 2500000 | AM4: 2500000 | AN4: 2000000 | AO4: 2000000 | AP4: 2000000 | AQ4: 2000000 | AR4: 2000000 | AS4: 2000000 | AT4: 2000000 | AU4: 2000000 | AV4: 2500000 | AW4: 2500000 | AX4: 2500000 | AY4: 2500000 | AZ4: 3000000 | BA4: 3000000 | BB4: 2500000 | BC4: 2000000 | BD4: 1100000 | BE4: 1400000 | BF4: 1300000 | BG4: 1500000 | BH4: 1500000 | BI4: 1500000 | BJ4: 1500000 | BK4: 1500000 | BL4: 2000000 | BM4: 1000000 | BN4: 2000000 | BO4: 2000000 | BP4: 2000000 | BQ4: 2000000 | BR4: 1750000 | BS4: 2000000 | BT4: 2000000 | BU4: 2000000 | CI4: Mercado | CJ4: 500000
A5: Mega-Transportes JUAMVI | B5: 0 | AV5: 0 | AW5: 0 | AX5: 0 | AY5: 0 | AZ5: 0 | BA5: 0 | BB5: 0 | BC5: 0 | BD5: 1400000 | BE5: 1500000 | BF5: 1600000 | BG5: 1700000 | BH5: 2000000 | BI5: 3000000 | BJ5: 2500000 | BK5: 1500000 | BL5: 0 | BM5: 3000000 | BN5: 2500000 | BO5: 2000000 | BP5: 0 | BQ5: 1500000 | BR5: 2000000 | BS5: 1300000 | BT5: 2000000 | BU5: 1400000
A6: Halcon | AN6: 685000 | AO6: 0 | AP6: 0 | AQ6: 0 | AR6: 0 | AS6: 0 | AT6: 0 | AU6: 0 | BB6: 2000000
A7: Cuenta Facil | BL7: 2470000 | BM7: 2470000 | BN7: 2470000 | BO7: 2470000 | BP7: 2470000 | BQ7: 2470000 | BR7: 2470000 | BS7: 0 | BT7: 0 | BU7: 0 | BV7: 28000000
A8: Llamadas | B8: 800000 | C8: 1000000 | D8: 1000000 | E8: 1000000 | F8: 1000000 | G8: 500000 | H8: 500000 | I8: 500000 | J8: 500000 | K8: 500000 | L8: 500000 | M8: 500000 | N8: 500000 | O8: 500000 | P8: 500000 | Q8: 500000 | R8: 500000 | S8: 500000 | T8: 500000 | U8: 500000 | V8: 500000 | W8: 500000 | X8: 500000 | Y8: 500000 | Z8: 500000 | AA8: 1000000 | AB8: 1000000 | AC8: 1000000 | AD8: 1000000 | AE8: 1000000 | AF8: 1000000 | AG8: 1000000 | AH8: 1000000 | AI8: 1000000 | AJ8: 1000000 | AK8: 1000000 | AL8: 1000000 | AM8: 1000000 | AN8: 1000000 | AO8: 1000000 | AP8: 1000000 | AQ8: 1000000 | AR8: 1000000 | AS8: 1000000 | AT8: 1000000 | AU8: 1000000 | AV8: 1000000 | AW8: 1000000 | AX8: 1000000 | AY8: 2000000 | AZ8: 2000000 | BA8: 2000000 | BB8: 2000000 | BC8: 2000000 | BD8: 2000000 | BE8: 2000000 | BF8: 2000000 | BG8: 2000000 | BH8: 2000000 | BI8: 2000000 | BJ8: 2000000 | BK8: 2000000 | BL8: 2000000 | BM8: 2000000 | BN8: 2000000 | BO8: 2000000 | BP8: 2000000 | BQ8: 2000000 | BR8: 2000000 | BS8: 2000000 | BT8: 2000000 | BU8: 2000000 | BV8: 2000000 | CI8: Diezmo | CJ8: 600000
A9: Internet | B9: 500000 | C9: -500000 | D9: 525000 | E9: 160000 | F9: 270000 | G9: -200000 | H9: -72000 | I9: 136000 | J9: 422000 | K9: 400000 | L9: 283000 | M9: -382000 | N9: 398000 | O9: -300000 | P9: 445000 | Q9: 320000 | R9: 333000 | S9: 692000 | T9: 700000 | U9: 600000 | V9: 196000 | W9: 180000 | X9: 652000 | Y9: 800000 | Z9: 350000 | AA9: 553000 | AB9: 280000 | AC9: 570000 | AD9: 226000 | AE9: 330000 | AF9: 502000 | AG9: 300000 | AH9: 406000 | AI9: 350000 | AJ9: 929000 | AK9: 580000 | AL9: 800000 | AM9: 0 | AN9: 62000 | AO9: 210000 | AP9: -487000 | AQ9: 0 | AR9: 0 | AS9: 0 | AT9: 0 | AU9: 0 | AV9: 0 | AW9: 0 | AY9: 798000 | AZ9: 788000 | BA9: 811000 | BB9: 811000 | BC9: 767000 | BD9: 691000 | BE9: 490000 | BF9: 478000 | BG9: 572000 | BH9: 389000 | BI9: 509000 | BJ9: 389000 | BK9: 0 | BL9: 0 | CI9: Gasolina | CJ9: 400000
A10: Mave integral -MARIANA | B10: 125000 | C10: 500000 | D10: 500000 | E10: 125000 | F10: 125000 | G10: 125000 | H10: 250000 | I10: 250000 | J10: 250000 | K10: 250000 | L10: 250000 | M10: 200000 | N10: 200000 | O10: 200000 | P10: 250000 | Q10: 250000 | R10: 250000 | S10: 250000 | T10: 330000 | U10: 330000 | V10: 330000 | W10: 330000 | X10: 330000 | Y10: 330000 | Z10: 330000 | AA10: 330000 | AB10: 330000 | AC10: 330000 | AD10: 330000 | AE10: 330000 | AF10: 330000 | AG10: 330000 | AH10: 330000 | AI10: 330000 | AJ10: 330000 | AK10: 330000 | AL10: 330000 | AM10: 330000 | AN10: 330000 | AO10: 330000 | AP10: 330000 | AQ10: 330000 | AR10: 330000 | AS10: 330000 | AT10: 330000 | AU10: 330000 | AV10: 330000 | AW10: 330000 | AX10: 330000 | AY10: 330000 | AZ10: 330000 | BA10: 330000 | BB10: 330000 | BC10: 330000 | BD10: 330000 | BE10: 330000 | BF10: 330000 | BG10: 330000 | BH10: 330000 | BI10: 330000 | BJ10: 330000 | BK10: 380000 | BL10: 380000 | BM10: 380000 | BN10: 380000 | BO10: 380000 | BP10: 380000 | BQ10: 380000 | BR10: 380000 | BS10: 380000 | BT10: 380000 | BU10: 380000 | BV10: 380000 | CI10: Parqueadero | CJ10: 200000
A11: Mave integral - ANDERSON | B11: 125000 | C11: 500000 | D11: 500000 | E11: 125000 | F11: 125000 | G11: 125000 | H11: 250000 | I11: 250000 | J11: 250000 | K11: 250000 | L11: 250000 | M11: 250000 | N11: 250000 | O11: 250000 | P11: 250000 | Q11: 250000 | R11: 250000 | S11: 250000 | T11: 570000 | U11: 330000 | V11: 330000 | W11: 330000 | X11: 280000 | Y11: 280000 | Z11: 280000 | AA11: 280000 | AB11: 280000 | AC11: 280000 | AD11: 280000 | AE11: 280000 | AF11: 280000 | AG11: 330000 | AH11: 330000 | AI11: 330000 | AJ11: 330000 | AK11: 330000 | AL11: 330000 | AM11: 330000 | AN11: 330000 | AO11: 330000 | AP11: 330000 | AQ11: 330000 | AR11: 330000 | AS11: 330000 | AT11: 330000 | AU11: 330000 | AV11: 330000 | AW11: 330000 | AX11: 330000 | AY11: 330000 | AZ11: 330000 | BA11: 330000 | BB11: 330000 | BC11: 330000 | BD11: 330000 | BE11: 330000 | BF11: 330000 | BG11: 330000 | BH11: 330000 | BI11: 330000 | BJ11: 330000 | BK11: 380000 | BL11: 380000 | BM11: 380000 | BN11: 380000 | CI11: Cadena | CJ11: 120000 | CQ11: pago el 5-marzo-20 | CR11: 860000
A12: MURO INTEGRAL | B12: 200000 | C12: 0 | D12: 0 | E12: 0 | F12: 0 | G12: 0 | H12: 0 | I12: 0 | J12: 0 | K12: 0 | L12: 0 | M12: 0 | N12: 300000 | O12: 200000 | P12: 200000 | Q12: 200000 | R12: 280000 | S12: 280000 | T12: 280000 | U12: 280000 | V12: 280000 | W12: 280000 | X12: 280000 | Y12: 280000 | Z12: 280000 | AA12: 280000 | AB12: 280000 | AC12: 280000 | AD12: 280000 | AE12: 280000 | AF12: 280000 | AG12: 280000 | AH12: 280000 | AI12: 280000 | AJ12: 280000 | AK12: 280000 | AL12: 280000 | AM12: 280000 | AN12: 280000 | AO12: 280000 | AP12: 280000 | AY12: 280000 | AZ12: 280000 | BA12: 280000 | BB12: 280000 | BC12: 280000 | BD12: 280000 | BE12: 280000 | BF12: 280000 | BG12: 280000 | BH12: 280000 | BI12: 280000 | BJ12: 280000 | BK12: 280000 | BL12: 280000 | BM12: 280000 | BN12: 280000 | BO12: 0 | BP12: 0 | BQ12: 830000 | CI12: Geral | CJ12: 500000
A13: FAGA - INTEGRAL | B13: 180000 | BH13: 0 | BI13: 0 | BJ13: 0 | BK13: 0 | BL13: 0 | BM13: 300000 | BN13: 180000 | BO13: 180000 | BP13: 180000 | BQ13: 180000 | BR13: 180000 | BS13: 180000 | BT13: 180000 | BU13: 180000
A14: INTERESES PRESTAMOS | AR14: 0 | AS14: 0 | AT14: 0 | AU14: 0 | AV14: 0 | AW14: 0 | AX14: 0 | AY14: 2419000 | AZ14: 3118706.2 | BA14: 3337892.3 | BB14: 2789696 | BC14: 2000000 | BD14: 2000000 | BE14: 2000000 | BF14: 2000000 | BG14: 2000000 | BH14: 2000000 | BI14: 2000000 | BJ14: 2789696 | BK14: 2200000 | BL14: 2200000 | BM14: 2200000 | BN14: 2200000 | BO14: 2200000 | BP14: 3200000 | BQ14: 3200000
A15: Congreso | B15: 500000 | C15: 500000 | D15: 500000 | E15: 500000 | F15: 500000 | G15: 500000 | H15: 500000 | I15: 500000 | J15: 500000 | K15: 500000 | L15: 500000 | M15: 500000 | N15: 500000 | O15: 500000 | P15: 500000 | Q15: 500000 | R15: 500000 | S15: 500000 | T15: 500000 | U15: 500000 | V15: 500000 | W15: 500000 | X15: 500000 | Y15: 500000 | Z15: 500000 | AA15: 500000 | AB15: 500000 | AC15: 500000 | AD15: 500000 | AE15: 500000 | AF15: 500000 | AG15: 500000 | AH15: 500000 | AI15: 500000 | AJ15: 500000 | AK15: 500000 | AL15: 500000 | AM15: 600000 | AN15: 600000 | AO15: 600000 | AP15: 600000 | AQ15: 600000 | AR15: 600000 | AS15: 600000 | AT15: 600000 | AU15: 600000 | AV15: 600000 | AW15: 600000 | AX15: 600000 | AY15: 600000 | AZ15: 750000 | BA15: 750000 | BB15: 750000 | BC15: 750000 | BD15: 750000 | BE15: 750000 | BF15: 750000 | BG15: 750000 | BH15: 750000 | BI15: 750000 | BJ15: 750000 | BK15: 750000 | BL15: 750000 | BM15: 750000 | BN15: 750000 | BO15: 750000 | BP15: 750000 | BQ15: 750000 | BR15: 750000 | BS15: 750000 | BT15: 750000 | BU15: 750000 | BV15: 750000 | CI15: transporte niños | CJ15: 150000 | CQ15: pago el 5-marzo-20 | CR15: 860000
A16: Concejo rolo | B16: 500000 | C16: 500000 | D16: 500000 | E16: 500000 | F16: 500000 | G16: 500000 | H16: 500000 | I16: 500000 | J16: 500000 | K16: 500000 | L16: 500000 | M16: 500000 | N16: 500000 | O16: 500000 | P16: 500000 | Q16: 500000 | R16: 500000 | S16: 500000 | T16: 500000 | U16: 500000 | V16: 500000 | W16: 500000 | X16: 500000 | Y16: 500000 | Z16: 500000 | AD16: 500000 | AE16: 500000 | AF16: 500000 | CI16: Comida fuera | CJ16: 500000
A17: Servidor Web | B17: 200000 | C17: 200000 | D17: 200000 | E17: 200000 | F17: 200000 | G17: 200000 | H17: 200000 | I17: 200000 | J17: 200000 | K17: 200000 | L17: 200000 | M17: 200000 | N17: 200000 | O17: 150000 | P17: 200000 | Q17: 200000 | R17: 200000 | S17: 200000 | T17: 200000 | U17: 200000 | V17: 200000 | W17: 200000 | X17: 200000 | Y17: 200000 | Z17: 200000 | AA17: 200000 | AB17: 200000 | AC17: 200000 | AD17: 200000 | AE17: 0 | AF17: 0 | AG17: 0 | AH17: 0 | AI17: 0 | AJ17: 0 | AK17: 0 | AL17: 0 | AM17: 0 | AN17: 0 | AO17: 0 | AP17: 0 | AQ17: 0 | AR17: 0 | AS17: 0 | AT17: 0 | AU17: 0 | AV17: 0 | AW17: 0 | AX17: 0
A18: Programa Org | B18: 300000 | C18: 300000 | D18: 300000 | E18: 300000 | F18: 300000 | G18: 0 | H18: 0 | I18: 0 | J18: 0 | K18: 0 | L18: 250000 | M18: 250000 | N18: 250000 | O18: 250000 | P18: 250000 | Q18: 250000 | R18: 250000 | S18: 250000 | T18: 250000 | U18: 250000 | V18: 250000 | W18: 250000 | X18: 250000 | Y18: 250000 | Z18: 250000 | AA18: 250000 | AB18: 250000 | AC18: 250000 | AD18: 250000 | AE18: 250000 | AF18: 250000 | AG18: 250000 | AH18: 250000 | AI18: 250000 | AJ18: 250000 | AK18: 250000 | AL18: 250000 | AM18: 250000 | AN18: 250000 | AO18: 250000 | AP18: 250000 | AQ18: 250000 | AR18: 250000 | AS18: 250000 | AT18: 250000 | AU18: 250000 | AV18: 250000 | AW18: 250000 | AX18: 250000 | AY18: 250000 | AZ18: 250000 | BA18: 250000 | BB18: 250000 | BC18: 250000 | BD18: 250000 | BE18: 250000 | BF18: 250000 | BG18: 250000 | BH18: 250000 | BI18: 250000 | BJ18: 250000 | BK18: 250000 | BL18: 250000 | BM18: 250000 | BN18: 250000 | BO18: 250000 | BP18: 250000 | BQ18: 250000 | BR18: 250000 | BS18: 250000 | BT18: 250000 | BU18: 250000 | BV18: 250000
A19: JOYERIA 18K | B19: 120000 | C19: 500000 | D19: 500000 | E19: 75000 | F19: 75000 | G19: 100000 | H19: 100000 | I19: 100000 | J19: 100000 | K19: 100000 | L19: 100000 | M19: 100000 | N19: 100000 | O19: 75000 | P19: 75000 | Q19: 75000 | R19: 75000 | S19: 75000 | T19: 75000 | U19: 75000 | V19: 100000 | W19: 75000 | X19: 75000 | Y19: 75000 | Z19: 75000 | AA19: 75000 | AB19: 75000 | AG19: 0 | AH19: 0 | AI19: 0 | AJ19: 0 | AK19: 0 | AL19: 0 | AM19: 0 | AN19: 0 | AO19: 0
A20: CONTRATO CONCEJO | B20: 980000 | C20: 980000 | D20: 980000 | E20: 980000 | F20: 980000 | G20: 1970000 | H20: 2200000 | I20: 0 | J20: 0 | K20: 0 | L20: 0 | M20: 2000000 | N20: 1900000 | O20: 1800000 | P20: 1800000 | Q20: 2000000 | R20: 2000000 | S20: 2000000 | T20: 2000000 | U20: 2000000 | V20: 2000000 | W20: 2000000 | X20: 2000000 | Y20: 2000000 | Z20: 500000 | AA20: 3280000 | AB20: 2982000 | AC20: 3280000 | AD20: 3280000 | AE20: 3280000 | AF20: 3362000 | AG20: 3100000 | AH20: 3837000 | AI20: 4320000 | AJ20: 4300000 | AK20: 3918000 | AL20: 3918000 | AM20: 4300000 | AN20: 4200000 | AO20: 3967000 | AP20: 3967000 | AQ20: 3800000 | AR20: 4300000 | AS20: 3000000 | AT20: 3970000 | AU20: 3970000 | AV20: 3970000 | AW20: 4300000 | AX20: 3000000 | AY20: 2500000 | AZ20: 4300000 | BA20: 3203000 | BB20: 4000000 | BC20: 3760000 | BD20: 3760000 | BE20: 3760000 | BF20: 3946000 | BG20: 4119000 | BH20: 4500000 | BI20: 4200000 | BJ20: 3946000 | BK20: 4500000 | BL20: 4500000 | BM20: 4500000 | BN20: 4500000 | BO20: 4500000 | BP20: 4500000 | BQ20: 4500000 | BR20: 4500000 | BS20: 4500000 | BT20: 4500000 | BU20: 4500000 | BV20: 4500000
A21: Intereses Lucy 2 | B21: =CD21*CE21 -> 110250 | C21: 0 | D21: 35000 | E21: 35000 | F21: 35000 | G21: 35000 | H21: 35000 | I21: 256000 | J21: 291000 | K21: 300000 | L21: 300000 | M21: 300000 | N21: 300000 | O21: 300000 | P21: 300000 | Q21: 300000 | R21: 300000 | S21: 300000 | T21: 300000 | U21: 300000 | V21: 300000 | W21: 300000 | X21: 250000 | Y21: 250000 | Z21: 250000 | AA21: 250000 | AB21: 210000 | AC21: 200000 | AD21: 50000 | AE21: 250000 | AF21: 0 | AG21: 250000 | AH21: 250000 | AI21: 200000 | AJ21: 200000 | AK21: 90000 | AL21: 200000 | AM21: 0 | AN21: 200000 | AO21: 200000 | AP21: 200000 | AQ21: 200000 | AR21: 100000 | AS21: 200000 | AT21: 200000 | AU21: 0 | AV21: 200000 | AW21: 200000 | AX21: 0 | CD21: 3150000 | CE21: 0.035 | CF21: 30 | CJ21: =SUM(CJ2:CJ20) -> 3670000
A22: HECTOR MEDINA AVIOMAR | B22: =CD22*CE22 -> 280000 | C22: 0 | D22: 0 | E22: 0 | F22: 0 | G22: 0 | H22: 0 | I22: 0 | J22: 0 | K22: 0 | L22: 35000 | M22: 105000 | N22: 105000 | O22: 105000 | P22: 280000 | Q22: 0 | R22: 1000000 | S22: 1000000 | T22: 1488000 | U22: 0 | V22: 500000 | W22: 0 | X22: 1000000 | Y22: 2000000 | Z22: 1000000 | AA22: 0 | AB22: 100000 | AC22: 600000 | AD22: 0 | AE22: 900000 | AF22: 0 | AG22: 1000000 | AH22: 0 | AI22: 0 | AJ22: 1000000 | AK22: 2000000 | AL22: 0 | AM22: 0 | AN22: 1000000 | AO22: 250000 | AT22: 1000000 | CD22: 8000000 | CE22: 0.035 | CF22: 2
A23: TOÑO- MIGUEL ANTONIO | I23: 0 | J23: 0 | K23: 0 | L23: 0 | M23: 0 | N23: 0 | O23: 0 | P23: 0 | Q23: 0 | R23: 120000 | S23: 120000 | T23: 100000 | U23: 50000 | V23: 0 | W23: 300000 | X23: 0 | Y23: 200000 | Z23: 100000 | AA23: 200000 | AB23: 150000 | AC23: 200000 | AD23: 0 | AE23: 0 | AF23: 100000 | AG23: 0 | AH23: 100000 | AI23: 100000 | AJ23: 100000 | AK23: 100000 | AL23: 100000 | AM23: 100000 | AN23: 100000 | AO23: 0 | AP23: 100000 | AQ23: 100000 | AR23: 100000 | AS23: 100000 | AT23: 100000 | AU23: 100000 | AV23: 100000 | AW23: 100000 | AX23: 100000 | CD23: 2000000 | CE23: 0.035 | CF23: 1
A24: Veronica Peña - Arroyave | B24: =CD24*CE24 -> 45000 | C24: 0 | D24: 0 | E24: 53000 | F24: 53000 | G24: 53000 | H24: 53000 | I24: 53000 | J24: 53000 | K24: 53000 | L24: 53000 | M24: 553000 | N24: 45000 | O24: 45000 | P24: 45000 | Q24: 45000 | R24: 45000 | S24: 45000 | T24: 45000 | U24: 45000 | V24: 45000 | W24: 45000 | X24: 45000 | Y24: 45000 | Z24: 45000 | AA24: 45000 | AB24: 45000 | AC24: 45000 | AD24: 45000 | AE24: 45000 | AF24: 45000 | AG24: 45000 | AH24: 45000 | AI24: 45000 | AJ24: 45000 | AK24: 45000 | AL24: 45000 | AM24: 45000 | AN24: 45000 | AO24: 45000 | AP24: 45000 | AQ24: 45000 | AR24: 45000 | AS24: 45000 | AT24: 45000 | AU24: 45000 | AV24: 45000 | AW24: 45000 | AX24: 45000 | CD24: 3000000 | CE24: 0.015 | CF24: 5
A25: Prestamos Halcon | AO25: 1000000 | AP25: 1000000 | AQ25: 1000000 | AR25: 500000 | AS25: 500000 | AT25: 500000 | CD25: 14700000 | CE25: 0.035 | CF25: 5
A26: Jessica ramirez - diana | U26: 0 | V26: 0 | W26: 0 | X26: 0 | Y26: 0 | Z26: 0 | AA26: 0 | AB26: 0 | AC26: 0 | AD26: 1200000 | AE26: 1140000 | AF26: 1100000 | AG26: 1100000 | AH26: 500000 | AI26: 498000 | AJ26: 0 | AK26: 0 | AL26: 0 | AM26: 0 | AN26: 0 | AO26: 0
A27: Fabionelson Ocoro | Z27: 0 | AA27: 50000 | AB27: 50000 | AC27: 1120000 | AD27: 0 | AP27: 500000 | AR27: 200000 | CD27: 1500000
A28: Intereses Humberto Pineda | B28: =CD28*CE28 -> 70000 | C28: 0 | D28: 0 | E28: 0 | F28: 0 | G28: 0 | H28: 0 | I28: 0 | J28: 0 | K28: 70000 | L28: 70000 | M28: 0 | N28: 140000 | O28: 70000 | P28: 70000 | Q28: 0 | R28: 70000 | S28: 70000 | T28: 70000 | AD28: 210000 | AI28: 1000000 | AL28: 1500000 | AM28: 0 | CD28: 2000000 | CE28: 0.035
A29: JHON JAIRO MUÑOZ | C29: 0 | D29: 0 | E29: 0 | F29: 0 | G29: 0 | H29: 0 | I29: 0 | J29: 0 | K29: 0 | L29: 0 | M29: 0 | N29: 500000 | CD29: 1830000 | CE29: 0.035
A30: Intereses Einer Mejia | B30: =CD30*CE30 -> 45500 | C30: 0 | D30: 0 | E30: 0 | F30: 0 | G30: 0 | H30: 0 | I30: 0 | J30: 0 | K30: 0 | L30: 0 | M30: 12000 | N30: 200000 | O30: 100000 | P30: 100000 | Q30: 0 | R30: 25000 | S30: 0 | T30: 117000 | CD30: 1300000 | CE30: 0.035 | CF30: 10
A31: Intereses Edgar Garcia | B31: =CD31*CE31 -> 73500 | C31: 0 | D31: 100000 | E31: 0 | F31: 45000 | K31: 100000 | L31: 400000 | CD31: 2100000 | CE31: 0.035 | CF31: 30
A32: intereses estefania bareiro | B32: =CD32*CE32 -> 42000 | C32: 0 | D32: 60000 | E32: 120000 | F32: 120000 | G32: 120000 | H32: 120000 | I32: 120000 | J32: 120000 | K32: 600000 | T32: 250000 | Z32: 300000 | AH32: 300000 | AI32: 300000 | CD32: 1200000 | CE32: 0.035 | CF32: 28
A33: intereses estefania bareiro | B33: =CD33*CE33 -> 30450 | C33: 0 | D33: 0 | E33: 0 | F33: 0 | G33: 0 | H33: 0 | I33: 0 | J33: 0 | K33: 400000 | CD33: 870000 | CE33: 0.035 | CF33: 5
A34: Intereses Viviana Gil | B34: =CD34*CE34 -> 19600 | C34: 0 | D34: 53000 | E34: 0 | F34: 0 | G34: 0 | H34: 0 | I34: 0 | J34: 0 | K34: 0 | L34: 0 | M34: 0 | N34: 0 | O34: 0 | P34: 0 | Q34: 0 | R34: 0 | S34: 0 | T34: 0 | U34: 0 | V34: 0 | W34: 0 | X34: 0 | Y34: 0 | Z34: 0 | AA34: 0 | AB34: 0 | AC34: 0 | AD34: 0 | AE34: 0 | AF34: 0 | AG34: 0 | AH34: 0 | AI34: 0 | AJ34: 0 | AK34: 0 | AL34: 0 | CD34: 560000 | CE34: 0.035 | CF34: 5
A35: Intereses Martin Chavez | B35: =CD35*CE35 -> 35000 | C35: 35000 | D35: 0 | E35: 0 | F35: 0 | G35: 0 | H35: 0 | I35: 0 | J35: 0 | K35: 0 | L35: 0 | M35: 0 | N35: 0 | O35: 0 | P35: 0 | Q35: 0 | R35: 0 | S35: 0 | T35: 0 | U35: 0 | V35: 0 | W35: 0 | X35: 0 | Y35: 0 | Z35: 0 | AA35: 0 | AB35: 0 | AC35: 0 | AD35: 0 | AE35: 0 | AF35: 0 | AG35: 0 | AH35: 0 | AI35: 400000 | AJ35: 0 | AK35: 400000 | AL35: 300000 | CD35: 1000000 | CE35: 0.035 | CF35: 10
A36: Diana Molina | B36: =CD36*CE36 -> 0 | C36: 0 | D36: 0 | E36: 0 | F36: 0 | G36: 0 | H36: 0 | I36: 0 | J36: 0 | K36: 0 | L36: 0 | M36: 0 | N36: 0 | O36: 0 | P36: 0 | Q36: 0 | R36: 0 | S36: 0 | T36: 0 | U36: 0 | V36: 0 | W36: 0 | X36: 0 | Y36: 0 | Z36: 0 | AA36: 0 | AB36: 0 | AC36: 0 | AD36: 0 | AE36: 0 | AF36: 0 | AG36: 0 | AH36: 0 | AI36: 0 | AJ36: 0 | AK36: 0 | AL36: 0 | CD36: 1700000 | CE36: 0 | CF36: 5
A37: manzano | B37: =CD37*CE37 -> 0 | C37: 0 | D37: 0 | E37: 0 | F37: 0 | G37: 0 | H37: 0 | I37: 0 | J37: 0 | K37: 0 | L37: 0 | M37: 0 | N37: 0 | O37: 0 | P37: 0 | Q37: 0 | R37: 0 | S37: 0 | T37: 0 | U37: 0 | V37: 0 | W37: 0 | X37: 0 | Y37: 0 | Z37: 0 | AA37: 0 | AB37: 0 | AC37: 0 | AD37: 0 | AE37: 0 | AF37: 0 | AG37: 0 | AH37: 0 | AI37: 0 | AJ37: 0 | AK37: 0 | AL37: 0 | CD37: 500000
A38: intereses johana barona 1 | B38: =CD38*CE38 -> 4900 | C38: 0 | D38: 21000 | E38: 21000 | F38: 21000 | G38: 0 | H38: 0 | I38: 0 | J38: 0 | K38: 600000 | X38: 0 | Y38: 0 | Z38: 0 | AA38: 0 | AB38: 0 | AC38: 0 | AD38: 0 | AE38: 0 | AF38: 0 | AG38: 0 | AH38: 0 | AI38: 0 | AJ38: 0 | AK38: 0 | AL38: 0 | AM38: 0 | AN38: 0 | AO38: 0 | AP38: 0 | AQ38: 0 | AR38: 0 | AS38: 0 | AT38: 0 | AU38: 0 | AV38: 0 | AW38: 0 | AX38: 0 | AY38: 0 | CD38: 140000 | CE38: 0.035 | CF38: 25
A39: intereses johana barona 2 | B39: =CD39*CE39 -> 70000 | C39: 0 | D39: 0 | E39: 0 | F39: 0 | G39: 0 | H39: 0 | I39: 0 | J39: 0 | K39: 0 | L39: 0 | M39: 0 | N39: 0 | O39: 0 | P39: 0 | Q39: 0 | R39: 0 | S39: 0 | T39: 0 | U39: 0 | V39: 0 | W39: 0 | X39: 0 | Y39: 0 | Z39: 0 | AA39: 0 | AB39: 2000000 | AC39: 0 | AD39: 0 | AE39: 0 | AF39: 0 | AG39: 0 | AH39: 0 | AI39: 0 | AJ39: 0 | AK39: 0 | AL39: 0 | AM39: 0 | AN39: 0 | AO39: 0 | AP39: 0 | AQ39: 0 | AR39: 0 | AS39: 0 | AT39: 0 | AU39: 0 | AV39: 0 | AW39: 0 | AX39: 0 | AY39: 0 | CD39: 2000000 | CE39: 0.035 | CF39: 5
A40: efecty | B40: 250000 | C40: 265000 | D40: 520000 | E40: 863000 | F40: 1831000 | G40: 1842000 | H40: 1514000 | I40: 1637000 | J40: 1414000 | K40: 1640000 | L40: 1504000 | M40: 1633320 | N40: 1303456 | O40: 1207000 | P40: 1197000 | Q40: 1474000 | R40: 1218716 | S40: 1265758 | T40: 299000 | U40: 0 | V40: 0 | W40: 0 | X40: 0 | Y40: 0 | Z40: 0 | AA40: 0 | AB40: 0 | AC40: 0 | AD40: 0 | AE40: 0 | AF40: 0 | AG40: 0 | AH40: 0 | AI40: 0 | AJ40: 0 | AK40: 0 | AL40: 0 | AM40: 0 | AN40: 0 | AO40: 0 | AP40: 0 | AQ40: 0 | AR40: 0 | AS40: 0 | AT40: 0 | AU40: 0 | AV40: 0 | AW40: 0 | AX40: 0 | AY40: 0 | CD40: 0
A41: BJSVISSION carlos herm | B41: 200000 | C41: 0 | D41: 0 | E41: 0 | F41: 0 | G41: 0 | H41: 0 | I41: 0 | J41: 0 | K41: 0 | L41: 0 | M41: 0 | N41: 0 | O41: 0 | P41: 200000 | Q41: x | R41: x | S41: x | T41: x | U41: x | V41: x | W41: x | X41: x | Y41: x | Z41: x | AA41: x | AB41: x | AC41: x | AD41: x | AE41: x | AF41: x | AG41: x | AH41: x | AI41: x | AJ41: x | AK41: x | AL41: x | AM41: x | AN41: x | AO41: x | AP41: x | AQ41: x | AR41: x | AS41: x | AT41: x | AU41: x | AV41: x | AW41: x | AX41: x | AY41: x | CD41: 0
A42: Fabionelson Ocoro | B42: =CD42*CE42 -> 20300 | C42: 0 | D42: 0 | E42: 0 | F42: 0 | G42: 100000 | H42: 130000 | I42: 100000 | J42: 100000 | K42: 100000 | L42: 100000 | M42: 100000 | N42: 100000 | O42: 100000 | P42: 100000 | Q42: 100000 | R42: 100000 | S42: 100000 | T42: 60000 | U42: 0 | V42: 0 | W42: 0 | X42: 0 | Y42: 0 | Z42: 0 | AA42: 0 | AB42: 0 | AC42: 0 | AD42: 0 | AE42: 0 | AF42: 0 | AG42: 0 | AH42: 0 | AI42: 0 | AJ42: 0 | AK42: 0 | AL42: 0 | AM42: 0 | AN42: 0 | AO42: 0 | AP42: 0 | AQ42: 0 | AR42: 0 | AS42: 0 | AT42: 0 | AU42: 0 | AV42: 0 | AW42: 0 | AX42: 0 | AY42: 0 | CD42: 580000 | CE42: 0.035 | CF42: 30
A43: tia de diana - LORENA | B43: =CD43*CE43 -> 0 | C43: 0 | D43: 0 | E43: 0 | F43: 0 | G43: 0 | H43: 175000 | I43: 1325000 | J43: 500000 | K43: 500000 | L43: 500000 | M43: 500000 | N43: 500000 | O43: 500000 | P43: 500000 | Q43: 1000000 | R43: 0 | S43: 0 | T43: 0 | U43: 0 | V43: 0 | W43: 0 | X43: 0 | Y43: 0 | Z43: 0 | AA43: 0 | AB43: 0 | AC43: 0 | AD43: 0 | AE43: 0 | AF43: 0 | AG43: 0 | AH43: 0 | AI43: 0 | AJ43: 0 | AK43: 0 | AL43: 0 | AM43: 0 | AN43: 0 | AO43: 0 | AP43: 0 | AQ43: 0 | AR43: 0 | AS43: 0 | AT43: 0 | AU43: 0 | AV43: 0 | AW43: 0 | AX43: 0 | AY43: 0 | CD43: 0 | CE43: 0.035
A44: Intereses Arroyave | B44: =CD44*CE44 -> 0 | C44: 990000 | D44: 990000 | E44: 976000 | F44: 976000 | G44: 1028386.8 | H44: 1028386.8 | I44: 1028386.8 | J44: 1028386.8 | K44: 1028386.8 | L44: 35100000 | M44: 0 | N44: 0 | O44: 0 | P44: 0 | Q44: 0 | R44: 0 | S44: 0 | T44: 0 | U44: 0 | V44: 0 | W44: 0 | X44: 0 | Y44: 0 | Z44: 0 | AA44: 0 | AB44: 0 | AC44: 0 | AD44: 0 | AE44: 0 | AF44: 0 | AG44: 0 | AH44: 0 | AI44: 0 | AJ44: 0 | AK44: 0 | AL44: 0 | AM44: 0 | AN44: 0 | AO44: 0 | AP44: 0 | AQ44: 0 | AR44: 0 | AS44: 0 | AT44: 0 | AU44: 0 | AV44: 0 | AW44: 0 | AX44: 0 | AY44: 0 | CD44: 0 | CE44: 0.015 | CF44: 25
A45: maria torres | B45: =CD45*CE45 -> 0 | C45: 0 | D45: 0 | E45: 0 | F45: 0 | G45: 60000 | H45: 0 | I45: 0 | J45: 0 | K45: 60000 | L45: 0 | M45: 0 | N45: 0 | O45: 0 | P45: 0 | Q45: 0 | R45: 0 | S45: 0 | T45: 0 | U45: 0 | V45: 0 | W45: 0 | X45: 0 | Y45: 0 | Z45: 0 | AA45: 0 | AB45: 0 | AC45: 0 | AD45: 0 | AE45: 0 | AF45: 0 | AG45: 0 | AH45: 0 | AI45: 0 | AJ45: 0 | AK45: 0 | AL45: 0 | AM45: 0 | AN45: 0 | AO45: 0 | AP45: 0 | AQ45: 0 | AR45: 0 | AS45: 0 | AT45: 0 | AU45: 0 | AV45: 0 | AW45: 0 | AX45: 0 | AY45: 0 | CD45: 0
A46: leidy casierra | B46: =CD46*CE46 -> 0 | C46: 0 | D46: 0 | E46: 0 | F46: 0 | G46: 0 | H46: 0 | I46: 0 | J46: 116000 | K46: 116000 | L46: 66000 | M46: 116000 | N46: 142000 | O46: 0 | P46: 0 | Q46: 0 | R46: 0 | S46: 0 | T46: 0 | U46: 0 | V46: 0 | W46: 0 | X46: 0 | Y46: 0 | Z46: 0 | AA46: 0 | AB46: 0 | AC46: 0 | AD46: 0 | AE46: 0 | AF46: 0 | AG46: 0 | AH46: 0 | AI46: 0 | AJ46: 0 | AK46: 0 | AL46: 0 | AM46: 0 | AN46: 0 | AO46: 0 | AP46: 0 | AQ46: 0 | AR46: 0 | AS46: 0 | AT46: 0 | AU46: 0 | AV46: 0 | AW46: 0 | AX46: 0 | AY46: 0 | CD46: 0 | CE46: 0.035
A47: leidy casierra | B47: =CD47*CE47 -> 0 | C47: 0 | D47: 0 | E47: 0 | F47: 0 | G47: 0 | H47: 0 | I47: 0 | J47: 0 | K47: 0 | L47: 0 | M47: 0 | N47: 0 | O47: 100000 | P47: 50000 | Q47: 100000 | R47: 89000 | S47: 0 | T47: 0 | U47: 0 | V47: 0 | W47: 0 | X47: 0 | Y47: 0 | Z47: 0 | AA47: 0 | AB47: 0 | AC47: 0 | AD47: 0 | AE47: 0 | AF47: 0 | AG47: 0 | AH47: 0 | AI47: 0 | AJ47: 0 | AK47: 0 | AL47: 0 | AM47: 0 | AN47: 0 | AO47: 0 | AP47: 0 | AQ47: 0 | AR47: 0 | AS47: 0 | AT47: 0 | AU47: 0 | AV47: 0 | AW47: 0 | AX47: 0 | AY47: 0 | CD47: 0 | CE47: 0.035
A48: Intereses Lucy 1 | B48: =CD48*CE48 -> 0 | C48: 51500 | D48: 43500 | E48: 35000 | F48: 250000 | G48: 250000 | H48: 250000 | I48: 0 | J48: 0 | K48: 0 | L48: 0 | M48: 0 | N48: 0 | O48: 0 | P48: 0 | Q48: 0 | R48: 0 | S48: 0 | T48: 0 | U48: 0 | V48: 0 | W48: 0 | X48: 0 | Y48: 0 | Z48: 0 | AA48: 0 | AB48: 0 | AC48: 0 | AD48: 0 | AE48: 0 | AF48: 0 | AG48: 0 | AH48: 0 | AI48: 0 | AJ48: 0 | AK48: 0 | AL48: 0 | AM48: 0 | AN48: 0 | AO48: 0 | AP48: 0 | AQ48: 0 | AR48: 0 | AS48: 0 | AT48: 0 | AU48: 0 | AV48: 0 | AW48: 0 | AX48: 0 | AY48: 0 | CD48: 0 | CE48: 0.035 | CF48: 30
A49: intereses leidy casierra | B49: =CD49*CE49 -> 0 | C49: 0 | D49: 116000 | E49: 116000 | F49: 66000 | G49: 113000 | H49: 100000 | I49: 50000 | J49: 0 | K49: 0 | L49: 0 | M49: 0 | N49: 0 | O49: 0 | P49: 0 | Q49: 0 | R49: 0 | S49: 0 | T49: 0 | U49: 0 | V49: 0 | W49: 0 | X49: 0 | Y49: 0 | Z49: 0 | AA49: 0 | AB49: 0 | AC49: 0 | AD49: 0 | AE49: 0 | AF49: 0 | AG49: 0 | AH49: 0 | AI49: 0 | AJ49: 0 | AK49: 0 | AL49: 0 | AM49: 0 | AN49: 0 | AO49: 0 | AP49: 0 | AQ49: 0 | AR49: 0 | AS49: 0 | AT49: 0 | AU49: 0 | AV49: 0 | AW49: 0 | AX49: 0 | AY49: 0 | CD49: 0 | CE49: 0.032 | CF49: 30
A50: OTROS ENTRADAS | C50: 290000 | D50: 240000 | E50: 58000 | F50: 1580000 | G50: 2050000 | H50: 4125000 | I50: 3531000 | J50: =SUMIFS(GASTOS!E:E,GASTOS!B:B,2020,GASTOS!C:C,8) -> 997000 | K50: =SUMIFS(GASTOS!E:E,GASTOS!B:B,2020,GASTOS!C:C,9) -> 1680000 | L50: =SUMIFS(GASTOS!E:E,GASTOS!B:B,2020,GASTOS!C:C,10) -> 8447020 | M50: =SUMIFS(GASTOS!E:E,GASTOS!B:B,2020,GASTOS!C:C,11) -> 3220000 | N50: =SUMIFS(GASTOS!E:E,GASTOS!B:B,2020,GASTOS!C:C,12) -> 8772900 | O50: =SUMIFS(GASTOS!E:E,GASTOS!B:B,2021,GASTOS!C:C,1) -> 7789000 | P50: =SUMIFS(GASTOS!E:E,GASTOS!B:B,2021,GASTOS!C:C,2) -> 2983000 | Q50: =SUMIFS(GASTOS!E:E,GASTOS!B:B,2021,GASTOS!C:C,3) -> 1120000 | R50: =SUMIFS(GASTOS!E:E,GASTOS!B:B,2021,GASTOS!C:C,4) -> 2353200 | S50: =SUMIFS(GASTOS!E:E,GASTOS!B:B,2021,GASTOS!C:C,5) -> 641000 | T50: =SUMIFS(GASTOS!E:E,GASTOS!B:B,2021,GASTOS!C:C,6) -> 955000 | U50: =SUMIFS(GASTOS!E:E,GASTOS!B:B,2021,GASTOS!C:C,7) -> 2771100 | V50: =SUMIFS(GASTOS!E:E,GASTOS!B:B,2021,GASTOS!C:C,8) -> 11311000 | W50: =SUMIFS(GASTOS!E:E,GASTOS!B:B,2021,GASTOS!C:C,9) -> 11585300 | X50: =SUMIFS(GASTOS!E:E,GASTOS!B:B,2021,GASTOS!C:C,10) -> 13620000 | Y50: =SUMIFS(GASTOS!E:E,GASTOS!B:B,2021,GASTOS!C:C,11) -> 9598900 | Z50: =SUMIFS(GASTOS!E:E,GASTOS!B:B,2021,GASTOS!C:C,12) -> 18601500 | AA50: =SUMIFS(GASTOS!E:E,GASTOS!B:B,2022,GASTOS!C:C,1) -> 2200000 | AB50: =SUMIFS(GASTOS!E:E,GASTOS!B:B,2022,GASTOS!C:C,2) -> 4660000 | AC50: =SUMIFS(GASTOS!E:E,GASTOS!B:B,2022,GASTOS!C:C,3) -> 11780000 | AD50: =SUMIFS(GASTOS!E:E,GASTOS!B:B,2022,GASTOS!C:C,4) -> 5330000 | AE50: =SUMIFS(GASTOS!E:E,GASTOS!B:B,2022,GASTOS!C:C,5) -> 12711700 | AF50: =SUMIFS(GASTOS!E:E,GASTOS!B:B,2022,GASTOS!C:C,6) -> 1380500 | AG50: =SUMIFS(GASTOS!E:E,GASTOS!B:B,2022,GASTOS!C:C,7) -> 2100000 | AH50: =SUMIFS(GASTOS!E:E,GASTOS!B:B,2022,GASTOS!C:C,8) -> 6545000 | AI50: =SUMIFS(GASTOS!E:E,GASTOS!B:B,2022,GASTOS!C:C,9) -> 6048058 | AJ50: =SUMIFS(GASTOS!E:E,GASTOS!B:B,2022,GASTOS!C:C,10) -> 5451000 | AK50: =SUMIFS(GASTOS!E:E,GASTOS!B:B,2022,GASTOS!C:C,11) -> 48509684 | AL50: =SUMIFS(GASTOS!E:E,GASTOS!B:B,2022,GASTOS!C:C,12) -> 33940000 | AM50: =SUMIFS(GASTOS!E:E,GASTOS!B:B,2023,GASTOS!C:C,1) -> 2000000 | AN50: =SUMIFS(GASTOS!E:E,GASTOS!B:B,2023,GASTOS!C:C,2) -> 12000000 | AO50: =SUMIFS(GASTOS!E:E,GASTOS!B:B,2023,GASTOS!C:C,3) -> 3977000 | AP50: =SUMIFS(GASTOS!E:E,GASTOS!B:B,2023,GASTOS!C:C,4) -> 13156000 | AQ50: =SUMIFS(GASTOS!E:E,GASTOS!B:B,2023,GASTOS!C:C,5) -> 6110000 | AR50: =SUMIFS(GASTOS!E:E,GASTOS!B:B,2023,GASTOS!C:C,6) -> 2000000 | AS50: =SUMIFS(GASTOS!E:E,GASTOS!B:B,2023,GASTOS!C:C,7) -> 4625000 | AT50: =SUMIFS(GASTOS!E:E,GASTOS!B:B,2023,GASTOS!C:C,8) -> 17180000 | AU50: =SUMIFS(GASTOS!E:E,GASTOS!B:B,2023,GASTOS!C:C,9) -> 5000000 | AV50: =SUMIFS(GASTOS!E:E,GASTOS!B:B,2023,GASTOS!C:C,10) -> 35926000 | AW50: =SUMIFS(GASTOS!E:E,GASTOS!B:B,2023,GASTOS!C:C,11) -> 5800000 | AX50: =SUMIFS(GASTOS!E:E,GASTOS!B:B,2023,GASTOS!C:C,12) -> 16900000 | AY50: =SUMIFS(GASTOS!E:E,GASTOS!B:B,2024,GASTOS!C:C,1) -> 0 | AZ50: =SUMIFS(GASTOS!E:E,GASTOS!B:B,2024,GASTOS!C:C,2) -> 400000 | BA50: =SUMIFS(GASTOS!E:E,GASTOS!B:B,2024,GASTOS!C:C,3) -> 0 | BB50: =SUMIFS(GASTOS!E:E,GASTOS!B:B,2024,GASTOS!C:C,4) -> 0 | BC50: =SUMIFS(GASTOS!E:E,GASTOS!B:B,2024,GASTOS!C:C,5) -> 0 | BD50: =SUMIFS(GASTOS!E:E,GASTOS!B:B,2024,GASTOS!C:C,6) -> 3995000 | BE50: =SUMIFS(GASTOS!E:E,GASTOS!B:B,2024,GASTOS!C:C,7) -> 500000 | BF50: =SUMIFS(GASTOS!E:E,GASTOS!B:B,2024,GASTOS!C:C,8) -> 0 | BG50: =SUMIFS(GASTOS!E:E,GASTOS!B:B,2024,GASTOS!C:C,9) -> 5830000 | BH50: =SUMIFS(GASTOS!E:E,GASTOS!B:B,2024,GASTOS!C:C,10) -> 0 | BI50: =SUMIFS(GASTOS!E:E,GASTOS!B:B,2024,GASTOS!C:C,11) -> 300000 | BJ50: =SUMIFS(GASTOS!E:E,GASTOS!B:B,2024,GASTOS!C:C,12) -> 22785000 | BK50: =SUMIFS(GASTOS!E:E,GASTOS!B:B,2025,GASTOS!C:C,1) -> 0 | BL50: =SUMIFS(GASTOS!E:E,GASTOS!B:B,2025,GASTOS!C:C,2) -> 0 | BM50: =SUMIFS(GASTOS!E:E,GASTOS!B:B,2025,GASTOS!C:C,3) -> 11500000 | BN50: =SUMIFS(GASTOS!E:E,GASTOS!B:B,2025,GASTOS!C:C,4) -> 0 | BO50: =SUMIFS(GASTOS!E:E,GASTOS!B:B,2025,GASTOS!C:C,5) -> 0 | BP50: =SUMIFS(GASTOS!E:E,GASTOS!B:B,2025,GASTOS!C:C,6) -> 0 | BQ50: =SUMIFS(GASTOS!E:E,GASTOS!B:B,2025,GASTOS!C:C,7) -> 2100000 | BR50: =SUMIFS(GASTOS!E:E,GASTOS!B:B,2025,GASTOS!C:C,8) -> 2000000 | BS50: =SUMIFS(GASTOS!E:E,GASTOS!B:B,2025,GASTOS!C:C,9) -> 0 | BT50: =SUMIFS(GASTOS!E:E,GASTOS!B:B,2025,GASTOS!C:C,10) -> 380000 | BU50: =SUMIFS(GASTOS!E:E,GASTOS!B:B,2025,GASTOS!C:C,11) -> 0 | BV50: =SUMIFS(GASTOS!E:E,GASTOS!B:B,2025,GASTOS!C:C,12) -> 27600000
A52: TOTAL ENTRADAS | B52: =SUM(B2:B51) -> 10326500 | C52: 7224500 | D52: 9271500 | E52: 7974000 | F52: 10474000 | G52: 10471387 | H52: 12958387 | I52: 12036387 | J52: =SUM(J2:J51) -> 9141386.8 | K52: =SUM(K2:K51) -> 13047387 | L52: =SUM(L2:L51) -> 52116520 | M52: =SUM(M2:M51) -> 16007320 | N52: =SUM(N2:N51) -> 22259656 | O52: =SUM(O2:O51) -> 19974000 | P52: =SUM(P2:P51) -> 14945000 | Q52: =SUM(Q2:Q51) -> 13184000 | ... CD52: =SUM(CD2:CD51) -> 48130000
A53: Prestamos | B53: PRESTAMOS | C53: 53000 | D53: 610000 | E53: 650000 | F53: 1200000 | G53: 100000 | H53: 750000 | I53: 0 | J53: =SUMIFS(GASTOS!G:G,GASTOS!B:B,2020,GASTOS!C:C,8) -> 0 | K53: =SUMIFS(GASTOS!G:G,GASTOS!B:B,2020,GASTOS!C:C,9) -> 0 | L53: =SUMIFS(GASTOS!G:G,GASTOS!B:B,2020,GASTOS!C:C,10) -> 0 | M53: =SUMIFS(GASTOS!G:G,GASTOS!B:B,2020,GASTOS!C:C,11) -> 0 | N53: =SUMIFS(GASTOS!G:G,GASTOS!B:B,2020,GASTOS!C:C,12) -> 0 | O53: =SUMIFS(GASTOS!G:G,GASTOS!B:B,2021,GASTOS!C:C,1) -> 0 | P53: =SUMIFS(GASTOS!G:G,GASTOS!B:B,2021,GASTOS!C:C,2) -> 0 | Q53: =SUMIFS(GASTOS!G:G,GASTOS!B:B,2021,GASTOS!C:C,3) -> 0 | R53: =SUMIFS(GASTOS!G:G,GASTOS!B:B,2021,GASTOS!C:C,4) -> 0 | S53: =SUMIFS(GASTOS!G:G,GASTOS!B:B,2021,GASTOS!C:C,5) -> 0 | T53: =SUMIFS(GASTOS!G:G,GASTOS!B:B,2021,GASTOS!C:C,6) -> 0 | U53: =SUMIFS(GASTOS!G:G,GASTOS!B:B,2021,GASTOS!C:C,7) -> 0 | V53: =SUMIFS(GASTOS!G:G,GASTOS!B:B,2021,GASTOS!C:C,8) -> 0 | W53: =SUMIFS(GASTOS!G:G,GASTOS!B:B,2021,GASTOS!C:C,9) -> 5000000 | X53: =SUMIFS(GASTOS!G:G,GASTOS!B:B,2021,GASTOS!C:C,10) -> 2000000 | Y53: =SUMIFS(GASTOS!G:G,GASTOS!B:B,2021,GASTOS!C:C,11) -> 0 | Z53: =SUMIFS(GASTOS!G:G,GASTOS!B:B,2021,GASTOS!C:C,12) -> 0 | AA53: =SUMIFS(GASTOS!G:G,GASTOS!B:B,2022,GASTOS!C:C,1) -> 0 | AB53: =SUMIFS(GASTOS!G:G,GASTOS!B:B,2022,GASTOS!C:C,2) -> 2460000 | AC53: =SUMIFS(GASTOS!G:G,GASTOS!B:B,2022,GASTOS!C:C,3) -> 0 | AD53: =SUMIFS(GASTOS!G:G,GASTOS!B:B,2022,GASTOS!C:C,4) -> 3000000 | AE53: =SUMIFS(GASTOS!G:G,GASTOS!B:B,2022,GASTOS!C:C,5) -> 0 | AF53: =SUMIFS(GASTOS!G:G,GASTOS!B:B,2022,GASTOS!C:C,6) -> 0 | AG53: =SUMIFS(GASTOS!G:G,GASTOS!B:B,2022,GASTOS!C:C,7) -> 100000 | AH53: =SUMIFS(GASTOS!G:G,GASTOS!B:B,2022,GASTOS!C:C,8) -> 0 | AI53: =SUMIFS(GASTOS!G:G,GASTOS!B:B,2022,GASTOS!C:C,9) -> 0 | AJ53: =SUMIFS(GASTOS!G:G,GASTOS!B:B,2022,GASTOS!C:C,10) -> 0 | AK53: =SUMIFS(GASTOS!G:G,GASTOS!B:B,2022,GASTOS!C:C,11) -> 80000 | AL53: =SUMIFS(GASTOS!G:G,GASTOS!B:B,2022,GASTOS!C:C,12) -> 0 | AM53: =SUMIFS(GASTOS!G:G,GASTOS!B:B,2023,GASTOS!C:C,1) -> 0 | AN53: =SUMIFS(GASTOS!G:G,GASTOS!B:B,2023,GASTOS!C:C,2) -> 0 | AO53: =SUMIFS(GASTOS!G:G,GASTOS!B:B,2023,GASTOS!C:C,3) -> 0 | AP53: =SUMIFS(GASTOS!G:G,GASTOS!B:B,2023,GASTOS!C:C,4) -> 0 | AQ53: =SUMIFS(GASTOS!G:G,GASTOS!B:B,2023,GASTOS!C:C,5) -> 0 | AR53: =SUMIFS(GASTOS!G:G,GASTOS!B:B,2023,GASTOS!C:C,6) -> 0 | AS53: =SUMIFS(GASTOS!G:G,GASTOS!B:B,2023,GASTOS!C:C,7) -> 0 | AT53: =SUMIFS(GASTOS!G:G,GASTOS!B:B,2023,GASTOS!C:C,8) -> 0 | AU53: =SUMIFS(GASTOS!G:G,GASTOS!B:B,2023,GASTOS!C:C,9) -> 0 | AV53: =SUMIFS(GASTOS!G:G,GASTOS!B:B,2023,GASTOS!C:C,10) -> 198000 | AW53: =SUMIFS(GASTOS!G:G,GASTOS!B:B,2023,GASTOS!C:C,11) -> 0 | AX53: =SUMIFS(GASTOS!G:G,GASTOS!B:B,2023,GASTOS!C:C,12) -> 0 | AY53: =SUMIFS(GASTOS!G:G,GASTOS!B:B,2024,GASTOS!C:C,1) -> 0 | AZ53: =SUMIFS(GASTOS!G:G,GASTOS!B:B,2024,GASTOS!C:C,2) -> 0 | BA53: =SUMIFS(GASTOS!G:G,GASTOS!B:B,2024,GASTOS!C:C,3) -> 0 | BB53: =SUMIFS(GASTOS!G:G,GASTOS!B:B,2024,GASTOS!C:C,4) -> 0 | BC53: =SUMIFS(GASTOS!G:G,GASTOS!B:B,2024,GASTOS!C:C,5) -> 0 | BD53: =SUMIFS(GASTOS!G:G,GASTOS!B:B,2024,GASTOS!C:C,6) -> 0 | BE53: =SUMIFS(GASTOS!G:G,GASTOS!B:B,2024,GASTOS!C:C,7) -> 0 | BF53: =SUMIFS(GASTOS!G:G,GASTOS!B:B,2024,GASTOS!C:C,8) -> 0 | BG53: =SUMIFS(GASTOS!G:G,GASTOS!B:B,2024,GASTOS!C:C,9) -> 850000 | BH53: =SUMIFS(GASTOS!G:G,GASTOS!B:B,2024,GASTOS!C:C,10) -> 500000 | BI53: =SUMIFS(GASTOS!G:G,GASTOS!B:B,2024,GASTOS!C:C,11) -> 0 | BJ53: =SUMIFS(GASTOS!G:G,GASTOS!B:B,2024,GASTOS!C:C,12) -> 0 | BK53: =SUMIFS(GASTOS!G:G,GASTOS!B:B,2025,GASTOS!C:C,1) -> 0 | BL53: =SUMIFS(GASTOS!G:G,GASTOS!B:B,2025,GASTOS!C:C,2) -> 0 | BM53: =SUMIFS(GASTOS!G:G,GASTOS!B:B,2025,GASTOS!C:C,3) -> 0 | BN53: =SUMIFS(GASTOS!G:G,GASTOS!B:B,2025,GASTOS!C:C,4) -> 0 | BO53: =SUMIFS(GASTOS!G:G,GASTOS!B:B,2025,GASTOS!C:C,5) -> 0 | BP53: =SUMIFS(GASTOS!G:G,GASTOS!B:B,2025,GASTOS!C:C,6) -> 3000000 | BQ53: =SUMIFS(GASTOS!G:G,GASTOS!B:B,2025,GASTOS!C:C,7) -> 1840000 | BR53: =SUMIFS(GASTOS!G:G,GASTOS!B:B,2025,GASTOS!C:C,8) -> 4000000 | BS53: =SUMIFS(GASTOS!G:G,GASTOS!B:B,2025,GASTOS!C:C,9) -> 1500000 | BT53: =SUMIFS(GASTOS!G:G,GASTOS!B:B,2025,GASTOS!C:C,10) -> 0 | BU53: =SUMIFS(GASTOS!G:G,GASTOS!B:B,2025,GASTOS!C:C,11) -> 9750000 | BV53: =SUMIFS(GASTOS!G:G,GASTOS!B:B,2025,GASTOS!C:C,12) -> 0 | BW53: =SUMIFS(GASTOS!G:G,GASTOS!B:B,2026,GASTOS!C:C,1) -> 2420000 | BX53: =SUMIFS(GASTOS!G:G,GASTOS!B:B,2026,GASTOS!C:C,2) -> 1350000 | BY53: =SUMIFS(GASTOS!G:G,GASTOS!B:B,2026,GASTOS!C:C,3) -> 0 | BZ53: =SUMIFS(GASTOS!G:G,GASTOS!B:B,2026,GASTOS!C:C,4) -> 2500000 | CA53: =SUMIFS(GASTOS!G:G,GASTOS!B:B,2026,GASTOS!C:C,5) -> 3500000 | CB53: =SUMIFS(GASTOS!G:G,GASTOS!B:B,2026,GASTOS!C:C,6) -> 0
A54: Inversion | B54: INVERSION | C54: 0 | D54: 0 | E54: 0 | F54: 0 | G54: 0 | H54: 0 | I54: 698000 | J54: =SUMIFS(GASTOS!H:H,GASTOS!B:B,2020,GASTOS!C:C,8) -> 1239500 | K54: =SUMIFS(GASTOS!H:H,GASTOS!B:B,2020,GASTOS!C:C,9) -> 3884000 | L54: =SUMIFS(GASTOS!H:H,GASTOS!B:B,2020,GASTOS!C:C,10) -> 1215000 | M54: =SUMIFS(GASTOS!H:H,GASTOS!B:B,2020,GASTOS!C:C,11) -> 1051000 | N54: =SUMIFS(GASTOS!H:H,GASTOS!B:B,2020,GASTOS!C:C,12) -> 2097000 | O54: =SUMIFS(GASTOS!H:H,GASTOS!B:B,2021,GASTOS!C:C,1) -> 272000 | P54: =SUMIFS(GASTOS!H:H,GASTOS!B:B,2021,GASTOS!C:C,2) -> 1000000 | Q54: =SUMIFS(GASTOS!H:H,GASTOS!B:B,2021,GASTOS!C:C,3) -> 105000 | R54: =SUMIFS(GASTOS!H:H,GASTOS!B:B,2021,GASTOS!C:C,4) -> 604000 | S54: =SUMIFS(GASTOS!H:H,GASTOS!B:B,2021,GASTOS!C:C,5) -> 0 | T54: =SUMIFS(GASTOS!H:H,GASTOS!B:B,2021,GASTOS!C:C,6) -> 3011000 | U54: =SUMIFS(GASTOS!H:H,GASTOS!B:B,2021,GASTOS!C:C,7) -> 3717000 | V54: =SUMIFS(GASTOS!H:H,GASTOS!B:B,2021,GASTOS!C:C,8) -> 2693000 | W54: =SUMIFS(GASTOS!H:H,GASTOS!B:B,2021,GASTOS!C:C,9) -> 2724000 | X54: =SUMIFS(GASTOS!H:H,GASTOS!B:B,2021,GASTOS!C:C,10) -> 6747400 | Y54: =SUMIFS(GASTOS!H:H,GASTOS!B:B,2021,GASTOS!C:C,11) -> 6164000 | Z54: =SUMIFS(GASTOS!H:H,GASTOS!B:B,2021,GASTOS!C:C,12) -> 1121000 | AA54: =SUMIFS(GASTOS!H:H,GASTOS!B:B,2022,GASTOS!C:C,1) -> 3764100 | AB54: =SUMIFS(GASTOS!H:H,GASTOS!B:B,2022,GASTOS!C:C,2) -> 4103000 | AC54: =SUMIFS(GASTOS!H:H,GASTOS!B:B,2022,GASTOS!C:C,3) -> 3143000 | AD54: =SUMIFS(GASTOS!H:H,GASTOS!B:B,2022,GASTOS!C:C,4) -> 0 | AE54: =SUMIFS(GASTOS!H:H,GASTOS!B:B,2022,GASTOS!C:C,5) -> 1776500 | AF54: =SUMIFS(GASTOS!H:H,GASTOS!B:B,2022,GASTOS!C:C,6) -> 5771000 | AG54: =SUMIFS(GASTOS!H:H,GASTOS!B:B,2022,GASTOS!C:C,7) -> 1686500 | AH54: =SUMIFS(GASTOS!H:H,GASTOS!B:B,2022,GASTOS!C:C,8) -> 2309000 | AI54: =SUMIFS(GASTOS!H:H,GASTOS!B:B,2022,GASTOS!C:C,9) -> 2186000 | AJ54: =SUMIFS(GASTOS!H:H,GASTOS!B:B,2022,GASTOS!C:C,10) -> 5202000 | AK54: =SUMIFS(GASTOS!H:H,GASTOS!B:B,2022,GASTOS!C:C,11) -> 0 | AL54: =SUMIFS(GASTOS!H:H,GASTOS!B:B,2022,GASTOS!C:C,12) -> #REF! | AM54: =SUMIFS(GASTOS!H:H,GASTOS!B:B,2023,GASTOS!C:C,1) -> 0 | AN54: =SUMIFS(GASTOS!H:H,GASTOS!B:B,2023,GASTOS!C:C,2) -> 0 | AO54: =SUMIFS(GASTOS!H:H,GASTOS!B:B,2023,GASTOS!C:C,3) -> 0 | AP54: =SUMIFS(GASTOS!H:H,GASTOS!B:B,2023,GASTOS!C:C,4) -> 0 | AQ54: =SUMIFS(GASTOS!H:H,GASTOS!B:B,2023,GASTOS!C:C,5) -> 2500000 | AR54: =SUMIFS(GASTOS!H:H,GASTOS!B:B,2023,GASTOS!C:C,6) -> 0 | AS54: =SUMIFS(GASTOS!H:H,GASTOS!B:B,2023,GASTOS!C:C,7) -> 0 | AT54: =SUMIFS(GASTOS!H:H,GASTOS!B:B,2023,GASTOS!C:C,8) -> 0 | AU54: =SUMIFS(GASTOS!H:H,GASTOS!B:B,2023,GASTOS!C:C,9) -> 0 | AV54: =SUMIFS(GASTOS!H:H,GASTOS!B:B,2023,GASTOS!C:C,10) -> 0 | AW54: =SUMIFS(GASTOS!H:H,GASTOS!B:B,2023,GASTOS!C:C,11) -> 0 | AX54: =SUMIFS(GASTOS!H:H,GASTOS!B:B,2023,GASTOS!C:C,12) -> 0 | AY54: =SUMIFS(GASTOS!H:H,GASTOS!B:B,2024,GASTOS!C:C,1) -> 0 | AZ54: =SUMIFS(GASTOS!H:H,GASTOS!B:B,2024,GASTOS!C:C,2) -> 180000 | BA54: =SUMIFS(GASTOS!H:H,GASTOS!B:B,2024,GASTOS!C:C,3) -> 181000 | BB54: =SUMIFS(GASTOS!H:H,GASTOS!B:B,2024,GASTOS!C:C,4) -> 0 | BC54: =SUMIFS(GASTOS!H:H,GASTOS!B:B,2024,GASTOS!C:C,5) -> 0 | BD54: =SUMIFS(GASTOS!H:H,GASTOS!B:B,2024,GASTOS!C:C,6) -> 0 | BE54: =SUMIFS(GASTOS!H:H,GASTOS!B:B,2024,GASTOS!C:C,7) -> 0 | BF54: =SUMIFS(GASTOS!H:H,GASTOS!B:B,2024,GASTOS!C:C,8) -> 0 | BG54: =SUMIFS(GASTOS!H:H,GASTOS!B:B,2024,GASTOS!C:C,9) -> 0 | BH54: =SUMIFS(GASTOS!H:H,GASTOS!B:B,2024,GASTOS!C:C,10) -> 0 | BI54: =SUMIFS(GASTOS!H:H,GASTOS!B:B,2024,GASTOS!C:C,11) -> 0 | BJ54: =SUMIFS(GASTOS!H:H,GASTOS!B:B,2024,GASTOS!C:C,12) -> 0 | BK54: =SUMIFS(GASTOS!H:H,GASTOS!B:B,2025,GASTOS!C:C,1) -> 0 | BL54: =SUMIFS(GASTOS!H:H,GASTOS!B:B,2025,GASTOS!C:C,2) -> 0 | BM54: =SUMIFS(GASTOS!H:H,GASTOS!B:B,2025,GASTOS!C:C,3) -> 0 | BN54: =SUMIFS(GASTOS!H:H,GASTOS!B:B,2025,GASTOS!C:C,4) -> 0 | BO54: =SUMIFS(GASTOS!H:H,GASTOS!B:B,2025,GASTOS!C:C,5) -> 0 | BP54: =SUMIFS(GASTOS!H:H,GASTOS!B:B,2025,GASTOS!C:C,6) -> 0 | BQ54: =SUMIFS(GASTOS!H:H,GASTOS!B:B,2025,GASTOS!C:C,7) -> 0 | BR54: =SUMIFS(GASTOS!H:H,GASTOS!B:B,2025,GASTOS!C:C,8) -> 0 | BS54: =SUMIFS(GASTOS!H:H,GASTOS!B:B,2025,GASTOS!C:C,9) -> 0 | BT54: =SUMIFS(GASTOS!H:H,GASTOS!B:B,2025,GASTOS!C:C,10) -> 0 | BU54: =SUMIFS(GASTOS!H:H,GASTOS!B:B,2025,GASTOS!C:C,11) -> 0 | BV54: =SUMIFS(GASTOS!H:H,GASTOS!B:B,2025,GASTOS!C:C,12) -> 0 | BW54: =SUMIFS(GASTOS!H:H,GASTOS!B:B,2026,GASTOS!C:C,1) -> 0 | BX54: =SUMIFS(GASTOS!H:H,GASTOS!B:B,2026,GASTOS!C:C,2) -> 0 | BY54: =SUMIFS(GASTOS!H:H,GASTOS!B:B,2026,GASTOS!C:C,3) -> 0 | BZ54: =SUMIFS(GASTOS!H:H,GASTOS!B:B,2026,GASTOS!C:C,4) -> 0 | CA54: =SUMIFS(GASTOS!H:H,GASTOS!B:B,2026,GASTOS!C:C,5) -> 0 | CB54: =SUMIFS(GASTOS!H:H,GASTOS!B:B,2026,GASTOS!C:C,6) -> 0
A55: GASTOS | B55: GASTOS | C55: 3106200 | D55: 3179000 | E55: 2514400 | F55: 2124600 | G55: 3396500 | H55: 5295000 | I55: 4263000 | J55: =SUMIFS(GASTOS!F:F,GASTOS!B:B,2020,GASTOS!C:C,8) -> 2939400 | K55: =SUMIFS(GASTOS!F:F,GASTOS!B:B,2020,GASTOS!C:C,9) -> 6665000 | L55: =SUMIFS(GASTOS!F:F,GASTOS!B:B,2020,GASTOS!C:C,10) -> 3662500 | M55: =SUMIFS(GASTOS!F:F,GASTOS!B:B,2020,GASTOS!C:C,11) -> 7259000 | N55: =SUMIFS(GASTOS!F:F,GASTOS!B:B,2020,GASTOS!C:C,12) -> 9064500 | O55: =SUMIFS(GASTOS!F:F,GASTOS!B:B,2021,GASTOS!C:C,1) -> 4049000 | P55: =SUMIFS(GASTOS!F:F,GASTOS!B:B,2021,GASTOS!C:C,2) -> 7827000 | Q55: =SUMIFS(GASTOS!F:F,GASTOS!B:B,2021,GASTOS!C:C,3) -> 7027000 | R55: =SUMIFS(GASTOS!F:F,GASTOS!B:B,2021,GASTOS!C:C,4) -> 5056500 | S55: =SUMIFS(GASTOS!F:F,GASTOS!B:B,2021,GASTOS!C:C,5) -> 5904800 | T55: =SUMIFS(GASTOS!F:F,GASTOS!B:B,2021,GASTOS!C:C,6) -> 5757000 | U55: =SUMIFS(GASTOS!F:F,GASTOS!B:B,2021,GASTOS!C:C,7) -> 6184000 | V55: =SUMIFS(GASTOS!F:F,GASTOS!B:B,2021,GASTOS!C:C,8) -> 6987800 | W55: =SUMIFS(GASTOS!F:F,GASTOS!B:B,2021,GASTOS!C:C,9) -> 5813800 | X55: =SUMIFS(GASTOS!F:F,GASTOS!B:B,2021,GASTOS!C:C,10) -> 8120700 | Y55: =SUMIFS(GASTOS!F:F,GASTOS!B:B,2021,GASTOS!C:C,11) -> 13525200 | Z55: =SUMIFS(GASTOS!F:F,GASTOS!B:B,2021,GASTOS!C:C,12) -> 9170000 | AA55: =SUMIFS(GASTOS!F:F,GASTOS!B:B,2022,GASTOS!C:C,1) -> 6097500 | AB55: =SUMIFS(GASTOS!F:F,GASTOS!B:B,2022,GASTOS!C:C,2) -> 3737000 | AC55: =SUMIFS(GASTOS!F:F,GASTOS!B:B,2022,GASTOS!C:C,3) -> 6764500 | AD55: =SUMIFS(GASTOS!F:F,GASTOS!B:B,2022,GASTOS!C:C,4) -> 9033500 | AE55: =SUMIFS(GASTOS!F:F,GASTOS!B:B,2022,GASTOS!C:C,5) -> 5809000 | AF55: =SUMIFS(GASTOS!F:F,GASTOS!B:B,2022,GASTOS!C:C,6) -> 6200000 | AG55: =SUMIFS(GASTOS!F:F,GASTOS!B:B,2022,GASTOS!C:C,7) -> 5107000 | AH55: =SUMIFS(GASTOS!F:F,GASTOS!B:B,2022,GASTOS!C:C,8) -> 8890000 | AI55: =SUMIFS(GASTOS!F:F,GASTOS!B:B,2022,GASTOS!C:C,9) -> 6969000 | AJ55: =SUMIFS(GASTOS!F:F,GASTOS!B:B,2022,GASTOS!C:C,10) -> 20632048 | AK55: =SUMIFS(GASTOS!F:F,GASTOS!B:B,2022,GASTOS!C:C,11) -> 24927000 | AL55: =SUMIFS(GASTOS!F:F,GASTOS!B:B,2022,GASTOS!C:C,12) -> 13848000 | AM55: =SUMIFS(GASTOS!F:F,GASTOS!B:B,2023,GASTOS!C:C,1) -> 10604000 | AN55: =SUMIFS(GASTOS!F:F,GASTOS!B:B,2023,GASTOS!C:C,2) -> 12042000 | AO55: =SUMIFS(GASTOS!F:F,GASTOS!B:B,2023,GASTOS!C:C,3) -> 24557000 | AP55: =SUMIFS(GASTOS!F:F,GASTOS!B:B,2023,GASTOS!C:C,4) -> 7676000 | AQ55: =SUMIFS(GASTOS!F:F,GASTOS!B:B,2023,GASTOS!C:C,5) -> 12027000 | AR55: =SUMIFS(GASTOS!F:F,GASTOS!B:B,2023,GASTOS!C:C,6) -> 8840000 | AS55: =SUMIFS(GASTOS!F:F,GASTOS!B:B,2023,GASTOS!C:C,7) -> 7794000 | AT55: =SUMIFS(GASTOS!F:F,GASTOS!B:B,2023,GASTOS!C:C,8) -> 20028000 | AU55: =SUMIFS(GASTOS!F:F,GASTOS!B:B,2023,GASTOS!C:C,9) -> 10052000 | AV55: =SUMIFS(GASTOS!F:F,GASTOS!B:B,2023,GASTOS!C:C,10) -> 8613600 | AW55: =SUMIFS(GASTOS!F:F,GASTOS!B:B,2023,GASTOS!C:C,11) -> 20202000 | AX55: =SUMIFS(GASTOS!F:F,GASTOS!B:B,2023,GASTOS!C:C,12) -> 43364499 | AY55: =SUMIFS(GASTOS!F:F,GASTOS!B:B,2024,GASTOS!C:C,1) -> 8972200 | AZ55: =SUMIFS(GASTOS!F:F,GASTOS!B:B,2024,GASTOS!C:C,2) -> 7463000 | BA55: =SUMIFS(GASTOS!F:F,GASTOS!B:B,2024,GASTOS!C:C,3) -> 7506500 | BB55: =SUMIFS(GASTOS!F:F,GASTOS!B:B,2024,GASTOS!C:C,4) -> 5818000 | BC55: =SUMIFS(GASTOS!F:F,GASTOS!B:B,2024,GASTOS!C:C,5) -> 8291000 | BD55: =SUMIFS(GASTOS!F:F,GASTOS!B:B,2024,GASTOS!C:C,6) -> 7303000 | BE55: =SUMIFS(GASTOS!F:F,GASTOS!B:B,2024,GASTOS!C:C,7) -> 6724000 | BF55: =SUMIFS(GASTOS!F:F,GASTOS!B:B,2024,GASTOS!C:C,8) -> 5656600 | BG55: =SUMIFS(GASTOS!F:F,GASTOS!B:B,2024,GASTOS!C:C,9) -> 5245000 | BH55: =SUMIFS(GASTOS!F:F,GASTOS!B:B,2024,GASTOS!C:C,10) -> 8373000 | BI55: =SUMIFS(GASTOS!F:F,GASTOS!B:B,2024,GASTOS!C:C,11) -> 5806000 | BJ55: =SUMIFS(GASTOS!F:F,GASTOS!B:B,2024,GASTOS!C:C,12) -> 16936000 | BK55: =SUMIFS(GASTOS!F:F,GASTOS!B:B,2025,GASTOS!C:C,1) -> 7554000 | BL55: =SUMIFS(GASTOS!F:F,GASTOS!B:B,2025,GASTOS!C:C,2) -> 9139000 | BM55: =SUMIFS(GASTOS!F:F,GASTOS!B:B,2025,GASTOS!C:C,3) -> 11255000 | BN55: =SUMIFS(GASTOS!F:F,GASTOS!B:B,2025,GASTOS!C:C,4) -> 7184000 | BO55: =SUMIFS(GASTOS!F:F,GASTOS!B:B,2025,GASTOS!C:C,5) -> 19993000 | BP55: =SUMIFS(GASTOS!F:F,GASTOS!B:B,2025,GASTOS!C:C,6) -> 11375000 | BQ55: =SUMIFS(GASTOS!F:F,GASTOS!B:B,2025,GASTOS!C:C,7) -> 14527000 | BR55: =SUMIFS(GASTOS!F:F,GASTOS!B:B,2025,GASTOS!C:C,8) -> 7675000 | BS55: =SUMIFS(GASTOS!F:F,GASTOS!B:B,2025,GASTOS!C:C,9) -> 7187000 | BT55: =SUMIFS(GASTOS!F:F,GASTOS!B:B,2025,GASTOS!C:C,10) -> 14239000 | BU55: =SUMIFS(GASTOS!F:F,GASTOS!B:B,2025,GASTOS!C:C,11) -> 17490000 | BV55: =SUMIFS(GASTOS!F:F,GASTOS!B:B,2025,GASTOS!C:C,12) -> 0 | BW55: =SUMIFS(GASTOS!F:F,GASTOS!B:B,2026,GASTOS!C:C,1) -> 8658000 | BX55: =SUMIFS(GASTOS!F:F,GASTOS!B:B,2026,GASTOS!C:C,2) -> 11227000 | BY55: =SUMIFS(GASTOS!F:F,GASTOS!B:B,2026,GASTOS!C:C,3) -> 9145000 | BZ55: =SUMIFS(GASTOS!F:F,GASTOS!B:B,2026,GASTOS!C:C,4) -> 9807000 | CA55: =SUMIFS(GASTOS!F:F,GASTOS!B:B,2026,GASTOS!C:C,5) -> 18543000 | CB55: =SUMIFS(GASTOS!F:F,GASTOS!B:B,2026,GASTOS!C:C,6) -> 6630300
C57: 4065300 | D57: 5482500 | E57: 4809600 | F57: 7149400 | G57: 6974886.8 | H57: 6913386.8 | I57: 7075386.8 | J57: =J52-(J55+J53+J54) -> 4962486.8 | K57: =K52-(K55+K53+K54) -> 2498386.8 | L57: =L52-(L55+L53+L54) -> 47239020 | M57: =M52-(M55+M53+M54) -> 7697320 | N57: =N52-(N55+N53+N54) -> 11098156 | O57: =O52-(O55+O53+O54) -> 15653000 | P57: =P52-(P55+P53+P54) -> 6118000 | Q57: =Q52-(Q55+Q53+Q54) -> 6052000 | ... CC57: =CC52-(CC55+CC53+CC54) -> 0 | CD57: =SUM(C57:CC57) -> #REF!
CD60: =C57+D57+E57+F57+G57+H57+I57+J57+K57+L57+M57+N57+O57+P57+Q57+R57+S57+T57+U57+V57+W57+X57+Y57+Z57+AA57+AB57+AC57+AD57+AE57+AF57+AG57+AH57+AI57+AJ57+AK57+AL57+AM57+AN57+AO57+AP57+AQ57+AR57+AS57+AT57+AU57+AV57+AW57+AX57+AY57+AZ57+BA57+BB57+BC57+BD57+BE57+BF57+BG57+BH57+BI57+BJ57+BK57+BL57+BM57+BN57+BO57+BP57+BQ57+BR57+BS57+BT57+BU57+BV57+BW57+BX57+BY57+BZ57+CA57+CB57+CC57 -> #REF!
AI67: Plataforma.1564 | AJ67: 4FE75-2SEVH-GUNPW-TVYRM-7TQ8Z

Sheet GASTOS
A1: No. | D1: FECHA | E1: ENTRADAS | F1: SALIDA | G1: PRESTAMOS | H1: INVERSION | I1: TIPO | J1: DESCRIPCION
A2: 1 | B2: =YEAR(D2) -> 2020 | C2: =MONTH(D2) -> 1 | D2: 43849 | F2: 100000 | I2: GASOLINA | J2: tanqueo
A3: 2 | B3: =YEAR(D3) -> 2020 | C3: =MONTH(D3) -> 1 | D3: 43852 | F3: 800000 | I3: OTROS | J3: Compra de portatil Dell
A4: 3 | B4: =YEAR(D4) -> 2020 | C4: =MONTH(D4) -> 1 | D4: 43852 | F4: 150000 | I4: OTROS | J4: giro c
A5: 4 | B5: =YEAR(D5) -> 2020 | C5: =MONTH(D5) -> 1 | D5: 43852 | F5: 4000 | I5: COMIDA | J5: desayuno
A6: 5 | B6: =YEAR(D6) -> 2020 | C6: =MONTH(D6) -> 1 | D6: 43852 | F6: 12000 | I6: OTROS | J6: peluquiada
A7: 6 | B7: =YEAR(D7) -> 2020 | C7: =MONTH(D7) -> 1 | D7: 43853 | F7: 2500 | I7: COMIDA | J7: desayuno
A8: 7 | B8: =YEAR(D8) -> 2020 | C8: =MONTH(D8) -> 1 | D8: 43853 | F8: 10000 | I8: COMIDA | J8: almuerzo
A9: 8 | B9: =YEAR(D9) -> 2020 | C9: =MONTH(D9) -> 1 | D9: 43853 | F9: 53000 | G9: 0 | I9: PRESTAMO | J9: giro a viviana gil - prestamos
A10: 9 | B10: =YEAR(D10) -> 2020 | C10: =MONTH(D10) -> 1 | D10: 43853 | F10: 100000 | I10: TRABAJOS | J10: mandar hacer libros iglesia
A11: 10 | B11: =YEAR(D11) -> 2020 | C11: =MONTH(D11) -> 1 | D11: 43853 | F11: 5200 | I11: PARQUEADERO | J11: parqueadero éxito
A12: 11 | B12: =YEAR(D12) -> 2020 | C12: =MONTH(D12) -> 1 | D12: 43853 | F12: 2500 | I12: COMIDA | J12: presa de pollo cena
A13: 12 | B13: =YEAR(D13) -> 2020 | C13: =MONTH(D13) -> 1 | D13: 43854 | F13: 3000 | I13: COMIDA | J13: desayuno
A14: 13 | B14: =YEAR(D14) -> 2020 | C14: =MONTH(D14) -> 1 | D14: 43854 | F14: 50000 | I14: SALIDAS | J14: cumpleaños de Abraham Cortes
A15: 14 | B15: =YEAR(D15) -> 2020 | C15: =MONTH(D15) -> 1 | D15: 43854 | F15: 5000 | I15: COMIDA | J15: almuerzo
A16: 15 | B16: =YEAR(D16) -> 2020 | C16: =MONTH(D16) -> 1 | D16: 43856 | F16: 70000 | I16: SALIDAS | J16: salida cajita feliz
A17: 16 | B17: =YEAR(D17) -> 2020 | C17: =MONTH(D17) -> 1 | D17: 43856 | F17: 10000 | I17: COMIDA | J17: cena
A18: 17 | B18: =YEAR(D18) -> 2020 | C18: =MONTH(D18) -> 1 | D18: 43856 | F18: 14000 | I18: OTROS | J18: boonyurg y regeneris
A19: 18 | B19: =YEAR(D19) -> 2020 | C19: =MONTH(D19) -> 1 | D19: 43857 | F19: 5000 | I19: COMIDA | J19: desayuno
A20: 19 | B20: =YEAR(D20) -> 2020 | C20: =MONTH(D20) -> 1 | D20: 43857 | F20: 10000 | I20: COMIDA | J20: almuerzo
A21: 20 | B21: =YEAR(D21) -> 2020 | C21: =MONTH(D21) -> 1 | D21: 43857 | F21: 2000 | I21: COMIDA | J21: pan cena
... A26: 25 | B26: =YEAR(D26) -> 2020 | C26: =MONTH(D26) -> 1 | D26: 43860 | F26: 10000 | I26: COMIDA | J26: desayuno
A27: 26 | B27: =YEAR(D27) -> 2020 | C27: =MONTH(D27) -> 1 | D27: 43860 | E27: 225000 | I27: ENTRADA | J27: ENVIO DE SMS
A28: 27 | B28: =YEAR(D28) -> 2020 | C28: =MONTH(D28) -> 1 | D28: 43860 | E28: 65000 | I28: ENTRADA | J28: IMPRESIÓN DE TIQUETES
A29: 28 | B29: =YEAR(D29) -> 2020 | C29: =MONTH(D29) -> 1 | D29: 43860 | F29: 10000 | I29: OTROS | J29: camara y comercio center cit
A30: 29 | B30: =YEAR(D30) -> 2020 | C30: =MONTH(D30) -> 1 | D30: 43860 | F30: 4000 | I30: OTROS | J30: copias
A31: 30 | B31: =YEAR(D31) -> 2020 | C31: =MONTH(D31) -> 1 | D31: 43861 | F31: 100000 | I31: TRABAJOS | J31: recarga sms
A32: 31 | B32: =YEAR(D32) -> 2020 | C32: =MONTH(D32) -> 1 | D32: 43861 | F32: 30000 | I32: SALIDAS | J32: Compra de perritos altoque
A33: 32 | B33: =YEAR(D33) -> 2020 | C33: =MONTH(D33) -> 1 | D33: 43861 | F33: 10000 | I33: COMIDA | J33: almuerzo oficina | K33: =SUM(F2:F33) -> 1759200
A34: 33 | B34: =YEAR(D34) -> 2020 | C34: =MONTH(D34) -> 2 | D34: 43862 | F34: 120000 | I34: OTROS | J34: compra zapatos niños
A35: 34 | B35: =YEAR(D35) -> 2020 | C35: =MONTH(D35) -> 2 | D35: 43862 | F35: 20000 | I35: SALIDAS | J35: compra de helado
A36: 35 | B36: =YEAR(D36) -> 2020 | C36: =MONTH(D36) -> 2 | D36: 43862 | F36: 100000 | I36: GASOLINA | J36: gasolina
A37: 36 | B37: =YEAR(D37) -> 2020 | C37: =MONTH(D37) -> 2 | D37: 43863 | F37: 20000 | I37: SALIDAS | J37: helados
A38: 37 | B38: =YEAR(D38) -> 2020 | C38: =MONTH(D38) -> 2 | D38: 43863 | F38: 50000 | I38: SALIDAS | J38: detalle cumple martha cabal
A39: 38 | B39: =YEAR(D39) -> 2020 | C39: =MONTH(D39) -> 2 | D39: 43864 | F39: 10000 | I39: COMIDA | J39: almuerzo comida
A40: 39 | B40: =YEAR(D40) -> 2020 | C40: =MONTH(D40) -> 2 | D40: 43865 | F40: 90000 | I40: COMIDA | J40: compra de mercado D1
A41: 40 | B41: =YEAR(D41) -> 2020 | C41: =MONTH(D41) -> 2 | D41: 43865 | F41: 40000 | I41: COMIDA | J41: almuerzo con madre - casuela
A42: 41 | B42: =YEAR(D42) -> 2020 | C42: =MONTH(D42) -> 2 | D42: 43870 | F42: 50000 | I42: SALIDAS | J42: salida con diana a comer sushi
A43: 42 | B43: =YEAR(D43) -> 2020 | C43: =MONTH(D43) -> 2 | D43: 43871 | F43: 150000 | J43: gastos
A44: 43 | B44: =YEAR(D44) -> 2020 | C44: =MONTH(D44) -> 2 | D44: 43873 | F44: 20000 | I44: OTROS | J44: yui comida
A45: 44 | B45: =YEAR(D45) -> 2020 | C45: =MONTH(D45) -> 2 | D45: 43872 | F45: 80000 | I45: GASOLINA | J45: gasolina
A46: 45 | B46: =YEAR(D46) -> 2020 | C46: =MONTH(D46) -> 2 | D46: 43873 | F46: 30000 | I46: COMIDA | J46: almuerzos y parqueaderos trabajo
A47: 46 | B47: =YEAR(D47) -> 2020 | C47: =MONTH(D47) -> 2 | D47: 43862 | E47: 240000 | I47: ENTRADA | J47: entrada compra de antiespia
A48: 47 | B48: =YEAR(D48) -> 2020 | C48: =MONTH(D48) -> 2 | D48: 43880 | F48: 80000 | I48: OTROS | J48: KIT CARRETERA
A49: 48 | B49: =YEAR(D49) -> 2020 | C49: =MONTH(D49) -> 2 | D49: 43880 | F49: 100000 | I49: GASOLINA | J49: gasolina
A50: 49 | B50: =YEAR(D50) -> 2020 | C50: =MONTH(D50) -> 2 | D50: 43878 | F50: 50000 | I50: GASOLINA | J50: gasolina
A51: 50 | B51: =YEAR(D51) -> 2020 | C51: =MONTH(D51) -> 2 | D51: 43876 | F51: 50000 | I51: SALIDAS | J51: salida con diana a comer MAICITOS
A52: 51 | B52: =YEAR(D52) -> 2020 | C52: =MONTH(D52) -> 2 | D52: 43876 | F52: 50000 | I52: SALIDAS | J52: TORNEO FUTBOL
A53: 52 | B53: =YEAR(D53) -> 2020 | C53: =MONTH(D53) -> 2 | D53: 43880 | F53: 300000 | G53: 0 | I53: PRESTAMO | J53: PRESTAMO A MANZANO PARA CONTRATO LIBRO
A54: 53 | B54: =YEAR(D54) -> 2020 | C54: =MONTH(D54) -> 2 | D54: 43880 | F54: 35000 | I54: COMIDA | J54: Almuerzo con mi padre
A55: 54 | B55: =YEAR(D55) -> 2020 | C55: =MONTH(D55) -> 2 | D55: 43880 | F55: 72000 | I55: OTROS | J55: varilla
A56: 55 | B56: =YEAR(D56) -> 2020 | C56: =MONTH(D56) -> 2 | D56: 43880 | F56: 50000 | G56: 0 | I56: PRESTAMO | J56: PRESTAR A EDGAR
A57: 56 | B57: =YEAR(D57) -> 2020 | C57: =MONTH(D57) -> 2 | D57: 43884 | F57: 100000 | I57: COMIDA | J57: MERCADO D1
A58: 57 | B58: =YEAR(D58) -> 2020 | C58: =MONTH(D58) -> 2 | D58: 43885 | F58: 42000 | I58: OTROS | J58: PAGO DE FACTURA DIANA MOLINA
A59: 58 | B59: =YEAR(D59) -> 2020 | C59: =MONTH(D59) -> 2 | D59: 43884 | F59: 10000 | I59: SALIDAS | J59: FUTBOL
A60: 59 | B60: =YEAR(D60) -> 2020 | C60: =MONTH(D60) -> 2 | D60: 43866 | F60: 175000 | I60: FACTURAS | J60: pago tarjeta credito bbva
A61: 60 | B61: =YEAR(D61) -> 2020 | C61: =MONTH(D61) -> 2 | D61: 43887 | F61: 135000 | I61: FACTURAS | J61: pago tarjeta credito banco occidente
A62: 61 | B62: =YEAR(D62) -> 2020 | C62: =MONTH(D62) -> 2 | D62: 43889 | F62: 50000 | I62: GASOLINA | J62: gasolina
A63: 62 | B63: =YEAR(D63) -> 2020 | C63: =MONTH(D63) -> 2 | D63: 43890 | F63: 50000 | I63: SALIDAS | J63: salida ver partido con diana
A64: 63 | B64: =YEAR(D64) -> 2020 | C64: =MONTH(D64) -> 2 | D64: 43890 | F64: 60000 | G64: 0 | I64: PRESTAMO | J64: prestamo maria torres
A65: 64 | B65: =YEAR(D65) -> 2020 | C65: =MONTH(D65) -> 2 | D65: 43890 | F65: 200000 | G65: 0 | I65: PRESTAMO | J65: PRESTAMO A MANZANO PARA CONTRATO LIBRO
A66: 65 | B66: =YEAR(D66) -> 2020 | C66: =MONTH(D66) -> 3 | D66: 43892 | F66: 100000 | I66: GASOLINA | J66: gasolina
A67: 66 | B67: =YEAR(D67) -> 2020 | C67: =MONTH(D67) -> 3 | D67: 43891 | F67: 10000 | I67: OTROS | J67: ofrenda
A68: 67 | B68: =YEAR(D68) -> 2020 | C68: =MONTH(D68) -> 3 | D68: 43892 | F68: 10000 | I68: SALIDAS | J68: pizza
A69: 68 | B69: =YEAR(D69) -> 2020 | C69: =MONTH(D69) -> 3 | D69: 43893 | F69: 54000 | I69: SALIDAS | J69: cumpleaños de estefania
A70: 69 | B70: =YEAR(D70) -> 2020 | C70: =MONTH(D70) -> 3 | D70: 43893 | F70: 20000 | I70: PARQUEADERO | J70: parqueaderos y otros
A71: 70 | B71: =YEAR(D71) -> 2020 | C71: =MONTH(D71) -> 3 | D71: 43895 | F71: 16000 | I71: PARQUEADERO | J71: parqueadero
A72: 71 | B72: =YEAR(D72) -> 2020 | C72: =MONTH(D72) -> 3 | D72: 43895 | F72: 10000 | I72: COMIDA | J72: almuerzo
A73: 72 | B73: =YEAR(D73) -> 2020 | C73: =MONTH(D73) -> 3 | D73: 43895 | F73: 50000 | G73: 0 | I73: PRESTAMO | J73: prestamo transporte k
A74: 73 | B74: =YEAR(D74) -> 2020 | C74: =MONTH(D74) -> 3 | D74: 43895 | F74: 100000 | I74: COMIDA | J74: MERCADO D1
A75: 74 | B75: =YEAR(D75) -> 2020 | C75: =MONTH(D75) -> 3 | D75: 43895 | F75: 10000 | I75: COMIDA | J75: panal huevos
A76: 75 | B76: =YEAR(D76) -> 2020 | C76: =MONTH(D76) -> 3 | D76: 43898 | F76: 25000 | I76: SALIDAS | J76: helados
A77: 76 | B77: =YEAR(D77) -> 2020 | C77: =MONTH(D77) -> 3 | D77: 43902 | F77: 46000 | I77: OTROS | J77: arreglo puerta sala
A78: 77 | B78: =YEAR(D78) -> 2020 | C78: =MONTH(D78) -> 3 | D78: 43902 | F78: 30000 | I78: COMIDA | J78: almuerzo alameda
A79: 78 | B79: =YEAR(D79) -> 2020 | C79: =MONTH(D79) -> 3 | D79: 43902 | F79: 12000 | I79: OTROS | J79: taxi amparo
A80: 79 | B80: =YEAR(D80) -> 2020 | C80: =MONTH(D80) -> 3 | D80: 43902 | F80: 5200 | I80: PARQUEADERO | J80: parqueadero
A81: 80 | B81: =YEAR(D81) -> 2020 | C81: =MONTH(D81) -> 3 | D81: 43902 | F81: 100000 | I81: GASOLINA | J81: gasolina
A82: 81 | B82: =YEAR(D82) -> 2020 | C82: =MONTH(D82) -> 3 | D82: 43903 | F82: 40000 | I82: OTROS | J82: saldo pago a don chucho
A83: 82 | B83: =YEAR(D83) -> 2020 | C83: =MONTH(D83) -> 3 | D83: 43903 | F83: 109000 | I83: FACTURAS | J83: factura internet casa
A84: 83 | B84: =YEAR(D84) -> 2020 | C84: =MONTH(D84) -> 3 | D84: 43903 | F84: 100000 | G84: 0 | I84: PRESTAMO | J84: prestamo a manzano
A85: 84 | B85: =YEAR(D85) -> 2020 | C85: =MONTH(D85) -> 3 | D85: 43903 | F85: 20000 | I85: OTROS | J85: peluquiada brayan y santiago
A86: 85 | B86: =YEAR(D86) -> 2020 | C86: =MONTH(D86) -> 3 | D86: 43903 | F86: 500000 | G86: 0 | I86: PRESTAMO | J86: prestamo amparo
A87: 86 | B87: =YEAR(D87) -> 2020 | C87: =MONTH(D87) -> 3 | D87: 43903 | F87: 55000 | I87: SALIDAS | J87: salida a comer maicitos
A88: 87 | B88: =YEAR(D88) -> 2020 | C88: =MONTH(D88) -> 3 | D88: 43904 | F88: 16000 | I88: SALIDAS | J88: alcazecer - perro - agua
A89: 88 | B89: =YEAR(D89) -> 2020 | C89: =MONTH(D89) -> 3 | D89: 43904 | F89: 10000 | I89: PARQUEADERO | J89: parqueadero éxito
A90: 89 | B90: =YEAR(D90) -> 2020 | C90: =MONTH(D90) -> 3 | D90: 43904 | F90: 2500 | I90: OTROS | J90: gasosa limon
A91: 90 | B91: =YEAR(D91) -> 2020 | C91: =MONTH(D91) -> 3 | D91: 43905 | E91: 58000 | I91: ABONO | J91: pago leidy
A92: 91 | B92: =YEAR(D92) -> 2020 | C92: =MONTH(D92) -> 3 | D92: 43905 | F92: 200000 | I92: FACTURAS | J92: quincena yuli
A93: 92 | B93: =YEAR(D93) -> 2020 | C93: =MONTH(D93) -> 3 | D93: 43905 | F93: 8000 | I93: SALIDAS | J93: helados
A94: 93 | B94: =YEAR(D94) -> 2020 | C94: =MONTH(D94) -> 3 | D94: 43905 | F94: 7000 | I94: COMIDA | J94: gaseosa y pan
A95: 94 | B95: =YEAR(D95) -> 2020 | C95: =MONTH(D95) -> 3 | D95: 43906 | F95: 5000 | I95: COMIDA | J95: desayuno niños
A96: 95 | B96: =YEAR(D96) -> 2020 | C96: =MONTH(D96) -> 3 | D96: 43906 | F96: 7000 | I96: COMIDA | J96: desayuno brayan y amparo
A97: 96 | B97: =YEAR(D97) -> 2020 | C97: =MONTH(D97) -> 3 | D97: 43906 | F97: 240000 | I97: FACTURAS | J97: cadenas brayan
A98: 97 | B98: =YEAR(D98) -> 2020 | C98: =MONTH(D98) -> 3 | D98: 43906 | F98: 93000 | I98: COMIDA | J98: MERCADO D1
A99: 98 | B99: =YEAR(D99) -> 2020 | C99: =MONTH(D99) -> 3 | D99: 43907 | F99: 11000 | I99: COMIDA | J99: pollo asado
A100: 99 | B100: =YEAR(D100) -> 2020 | C100: =MONTH(D100) -> 3 | D100: 43907 | F100: 13000 | I100: COMIDA | J100: huevo - maduro - limones
A101: 100 | B101: =YEAR(D101) -> 2020 | C101: =MONTH(D101) -> 3 | D101: 43907 | F101: 4000 | I101: COMIDA | J101: refrigerio
A102: 101 | B102: =YEAR(D102) -> 2020 | C102: =MONTH(D102) -> 3 | D102: 43907 | F102: 147000 | I102: OTROS | J102: compras papeleria y cosas niños
A103: 102 | B103: =YEAR(D103) -> 2020 | C103: =MONTH(D103) -> 3 | D103: 43907 | F103: 15000 | I103: TRABAJOS | J103: recarga arroyave
... A126: 125 | B126: =YEAR(D126) -> 2020 | C126: =MONTH(D126) -> 3 | D126: 43920 | F126: 6000 | I126: OTROS | J126: recarga yilmar
...

Sheet PROYECTOS
A1: No | B1: Fecha | C1: Entrada | D1: Salida | E1: Proyecto | F1: Obervacion
A2: 1 | B2: 45721 | C2: 3470000 | E2: CuentaFacil | F2: pago cuota febrero de Martin
A3: 2 | B3: 45721 | C3: 2470000 | E3: CuentaFacil | F3: pago cuota febrero de Rosero
A4: 3 | B4: 45722 | C4: - | D4: 120000 | E4: CuentaFacil | F4: pago a gisell cuentas FEBRERO
A5: 4 | B5: 45722 | C5: - | D5: 2470000 | E5: CuentaFacil | F5: para Jhon Rosero
A6: 5 | B6: 45722 | C6: - | D6: 2470000 | E6: CuentaFacil | F6: para Brayan Garcia
A7: 6 | B7: 45724 | D7: 100000 | E7: Zencorp | F7: Reunion telk
A8: 7 | B8: 45726 | D8: 3000000 | E8: CuentaFacil | F8: Compra portatil jhon Rosero
A9: 8 | B9: 45728 | C9: 7500000 | D9: - | E9: Zencorp | F9: Abono de aliados proyecto 2025
A10: 9 | B10: 45728 | C10: - | D10: 7500000 | E10: Zencorp | F10: Jhon Rosero
A11: 10 | B11: 45735 | C11: - | D11: 450000 | E11: CuentaFacil | F11: Planilla Febebrero Rosero
A12: 11 | B12: 45737 | C12: - | D12: 82000 | E12: Zencorp | F12: ChatGpt Marzo
A13: 12 | B13: 45738 | D13: 368000 | E13: Avapp | F13: Hosting Hostgator Avapp
A14: 13 | B14: 45747 | C14: 3470000 | D14: - | E14: CuentaFacil | F14: pago cuota Marzo de Martin
A15: 14 | B15: 45747 | C15: 2470000 | D15: - | E15: CuentaFacil | F15: pago cuota Marzo de Rosero
A16: 15 | B16: 45747 | C16: - | D16: 2470000 | E16: CuentaFacil | F16: para Jhon Rosero
A17: 16 | B17: 45747 | C17: - | D17: 2470000 | E17: CuentaFacil | F17: para Brayan Garcia
A18: 17 | B18: 45747 | C18: 15500000 | D18: - | E18: Zencorp | F18: Abono de aliados proyecto 2025
A19: 18 | B19: 45747 | C19: - | D19: 4000000 | E19: Zencorp | F19: Jhon Rosero
A20: 19 | B20: 45747 | C20: - | D20: 11500000 | E20: Zencorp | F20: Brayan Garcia
A21: 20 | B21: 45748 | C21: - | D21: 146000 | E21: CuentaFacil | F21: Dominio Cuentafacil.co 2 años | M21: =26/4 -> 6.5
A22: 21 | B22: 45755 | C22: 1500000 | D22: - | E22: Avapp | F22: gustavo pacto valle
A23: 22 | B23: 45777 | C23: - | D23: 450000 | E23: CuentaFacil | F23: Planilla Marzo Rosero
A24: 23 | B24: 45777 | C24: 3500000 | D24: - | E24: CuentaFacil | F24: pago cuota Abril de Martin
A25: 24 | B25: 45777 | C25: 2470000 | D25: - | E25: CuentaFacil | F25: pago cuota Abril de Rosero
A26: 25 | B26: 45777 | C26: - | D26: 2470000 | E26: CuentaFacil | F26: para Jhon Rosero
A27: 26 | B27: 45777 | C27: - | D27: 2470000 | E27: CuentaFacil | F27: para Brayan Garcia
A28: 27 | B28: 45789 | D28: 120000 | E28: CuentaFacil | F28: giselle cuentas CUENTA MARZO
A29: 28 | B29: 45798 | C29: - | D29: 450000 | E29: CuentaFacil | F29: Planilla Abril Rosero
A30: 29 | B30: 45807 | C30: 3500000 | D30: - | E30: CuentaFacil | F30: pago cuota Mayo de Martin
A31: 30 | B31: 45807 | C31: 2470000 | D31: - | E31: CuentaFacil | F31: pago cuota Mayo de Rosero
A32: 31 | B32: 45807 | C32: - | D32: 2470000 | E32: CuentaFacil | F32: para Jhon Rosero
A33: 32 | B33: 45807 | C33: - | D33: 2470000 | E33: CuentaFacil | F33: para Brayan Garcia
A34: 33 | B34: 45789 | C34: - | D34: 120000 | E34: CuentaFacil | F34: giselle cuentas CEUNTA ABRIL
A35: 34 | B35: 45832 | C35: - | D35: 450000 | E35: CuentaFacil | F35: Planilla Mayo Rosero
A36: 35 | B36: 45838 | C36: 3500000 | D36: - | E36: CuentaFacil | F36: pago cuota Junio de Martin
A37: 36 | B37: 45838 | C37: 2470000 | D37: - | E37: CuentaFacil | F37: pago cuota Junio de Rosero
A38: 37 | B38: 45838 | C38: - | D38: 2470000 | E38: CuentaFacil | F38: para Jhon Rosero
A39: 38 | B39: 45838 | C39: - | D39: 2470000 | E39: CuentaFacil | F39: para Brayan Garcia
A40: 39 | B40: 45820 | C40: - | D40: 120000 | E40: CuentaFacil | F40: giselle cuentas CEUNTA MAYO
A41: 40 | B41: 45813 | C41: - | D41: 180000 | E41: Solidify | F41: Reunion Solidify
A42: 41 | B42: 45814 | C42: - | D42: 240000 | E42: Zencorp | F42: 240 luis lopez zencorp
A43: 42 | B43: 45829 | C43: - | D43: 210000 | E43: Zencorp | F43: 210 pago a luis lopez
A44: 43 | B44: 45832 | C44: - | D44: 57000 | E44: Avapp | F44: 57 dominio carlosapp.co
A45: 44 | B45: 45840 | C45: - | D45: 81000 | E45: Avapp | F45: chat gpt
A46: 45 | B46: 45856 | C46: - | D46: 450000 | E46: CuentaFacil | F46: Planilla Junio Rosero
A47: 46 | B47: 45820 | C47: - | D47: 120000 | E47: CuentaFacil | F47: giselle cuentas CUENTA JUNIO
A48: 47 | B48: 45868 | C48: 3500000 | D48: - | E48: CuentaFacil | F48: pago cuota Julio de Martin
A49: 48 | B49: 45868 | C49: 2470000 | D49: - | E49: CuentaFacil | F49: pago cuota Julio de Rosero
A50: 49 | B50: 45868 | C50: - | D50: 2470000 | E50: CuentaFacil | F50: para Jhon Rosero
A51: 50 | B51: 45868 | C51: - | D51: 2470000 | E51: CuentaFacil | F51: para Brayan Garcia
A52: 51 | B52: 45868 | C52: - | D52: 120000 | E52: CuentaFacil | F52: giselle cuentas CUENTA
A53: 52 | B53: 45888 | C53: - | D53: 120000 | E53: CuentaFacil | F53: giselle cuentas CUENTA
A54: 45 | B54: 45887 | C54: - | D54: 450000 | E54: CuentaFacil | F54: Planilla julio Rosero
A55: 53 | B55: 45899 | C55: 3500000 | D55: - | E55: CuentaFacil | F55: pago cuota agosto de Martin
A56: 54 | B56: 45899 | C56: 2470000 | D56: - | E56: CuentaFacil | F56: pago cuota agosto de Rosero
A57: 55 | B57: 45899 | C57: - | D57: 2470000 | E57: CuentaFacil | F57: para Jhon Rosero
A58: 56 | B58: 45899 | C58: - | D58: 2470000 | E58: CuentaFacil | F58: para Brayan Garcia
A59: 57 | B59: 45899 | C59: - | D59: 120000 | E59: CuentaFacil | F59: giselle cuentas CUENTA
A60: 58 | B60: 45899 | C60: - | D60: 120000 | E60: CuentaFacil | F60: giselle cuentas CUENTA
A61: 59 | B61: 45933 | D61: 1200000 | E61: Solidify | F61: devolucion dinero
A62: 60 | B62: 45924 | D62: 267000 | E62: Avapp | F62: 267 cambio avapp
A63: 61 | B63: 45891 | D63: 189000 | E63: CuentaFacil | F63: 189 salida cuenta fácil Gisell
A64: 62 | B64: 46381 | C64: 6000000 | D64: - | E64: CuentaFacil | F64: Pago cuota angela ortiz nov y dic
A65: 63 | B65: 46381 | C65: 4500000 | D65: - | E65: CuentaFacil | F65: Pago cuota martin chavez nov y dic
A66: 64 | B66: 46382 | C66: 4000000 | D66: - | E66: CuentaFacil | F66: Pago cuota yazmin dic
A67: 65 | B67: 46386 | C67: 7290000 | D67: - | E67: CuentaFacil | F67: pago cuota avapp
A68: 66 | B68: 46386 | C68: 8145000 | D68: - | E68: CuentaFacil | F68: pago cuota avapp
A69: 67 | B69: 46386 | C69: - | D69: 600000 | E69: CuentaFacil | F69: yerly cuentas
A70: 68 | B70: 46386 | D70: 140000 | E70: CuentaFacil | F70: salida cuenta fácil Gisell
A71: 69
A72: 70
A73: 71 | B73: 46068 | C73: 40000000 | F73: CONTRATO CUENTA FACIL 2026 | H73: 90000000
A74: 72 | B74: 46068 | D74: 10000000 | F74: impuesto contrato cuenta facil 2026
A75: 73 | B75: 46025 | D75: 450000 | F75: 450 zerossl | H75: acuerdo | I75: 0.3 | J75: =H73*I75 -> 27000000
A76: 74 | B76: 46030 | D76: 62000 | F76: 62 dominio geovoto | H76: Empresa | I76: 0.15 | J76: =H73*I76 -> 13500000
A77: 75 | B77: 46038 | D77: 600000 | F77: 600 yerli avapp | H77: Iva | I77: 0.19 | J77: =H73*I77 -> 17100000
A78: 76 | B78: 46090 | D78: 490000 | F78: 490 Google avapp | H78: contabilidad | I78: 0.01 | J78: =H73*I78 -> 900000
A79: 77 | B79: 46121 | D79: 490000 | F79: 490 Google avapp | H79: Brayan | I79: 0.15 | J79: =H73*I79 -> 13500000
A80: 78 | B80: 46153 | D80: 490000 | F80: 490 Google avapp | H80: Martin | I80: 0.05 | J80: =H73*I80 -> 4500000
A81: 79 | B81: 46135 | D81: 60000 | F81: 60 servidor contabo | H81: Jhon | I81: 0.15 | J81: =H73*I81 -> 13500000
A82: 80 | B82: 46132 | D82: 400000 | F82: 400 Raywall
A83: 81 | B83: 46059 | D83: 215000 | F83: 215 póliza avapp | I83: =SUM(I75:I82) -> 1 | J83: =SUM(J75:J82) -> 90000000
A84: 82 | B84: 46051 | D84: 600000 | F84: 600 recapchat capsolver
A85: 83 | B85: 46068 | D85: 300000 | F85: seguridad social amparo cuota 1
A86: 84 | B86: 46190 | D86: 300000 | F86: seguridad social amparo cuota 2
A87: 85
A88: 86
A89: 87
A90: 88
A91: 89
A92: 90
A93: 91
A94: 92
A95: 93
A96: 94 | C96: =SUM(C2:C95) -> 136165000 | D96: =SUM(D2:D95) -> 82677000
D98: =C96-D96 -> 53488000 | E98: Guardar

Sheet APP
B1: CARLOSAPP | C1: CMJRADICAL | D1: PACTO | E1: SIEMBRA20 | K1: TOTAL MENSUAL
A2: ENERO | B2: x | D2: x | K2: =SUM(B2:J2) -> 0
A3: FEBRERO | B3: x | D3: - | K3: =SUM(B3:J3) -> 0
A4: MARZO | B4: 1500000 | D4: - | K4: =SUM(B4:J4) -> 1500000
A5: ABRIL | B5: 1000000 | D5: - | K5: =SUM(B5:J5) -> 1000000
A6: MAYO | B6: 1000000 | D6: - | K6: =SUM(B6:J6) -> 1000000
A7: JUNIO | B7: 1000000 | D7: - | K7: =SUM(B7:J7) -> 1000000
A8: JULIO | B8: 1000000 | D8: - | E8: 1000000 | K8: =SUM(B8:J8) -> 2000000
A9: AGOSTO | B9: 1000000 | C9: 1000000 | D9: 1000000 | E9: 0 | K9: =SUM(B9:J9) -> 3000000
A10: SEPTIEMBRE | B10: 1000000 | C10: 500000 | D10: 1000000 | E10: 0 | K10: =SUM(B10:J10) -> 2500000
A11: OCTUBRE | B11: 1000000 | C11: 500000 | D11: 500000 | E11: 0 | K11: =SUM(B11:J11) -> 2000000
A12: NOVIEMBRE | B12: 1000000 | C12: 0 | D12: - | E12: - | K12: =SUM(B12:J12) -> 1000000
A13: DICIEMBRE | B13: 1000000 | C13: 500000 | D13: - | E13: - | K13: =SUM(B13:J13) -> 1500000
B14: =SUM(B2:B13) -> 10500000 | C14: =SUM(C2:C13) -> 2500000 | D14: =SUM(D2:D13) -> 2500000 | E14: =SUM(E2:E13) -> 1000000 | F14: =SUM(F2:F13) -> 0 | G14: =SUM(G2:G13) -> 0 | J14: =SUM(J2:J13) -> 0 | K14: =SUM(B14:J14) -> 16500000
B18: 1523 | C18: Jovenes_lideres
B19: 2026 | C19: Jovenes_carlosapp
B20: 2250 | C20: jovenes_CMJ
B21: 17398 | C21: Ingreso Fya Carlos Hernan | J21: =54000-B21 -> 36602
A22: Envios | B22: =SUM(B18:B21) -> 23197 | C22: =B22*100 -> 2319700
B24: 7000 | C24: censo cmj
B25: 24000 | C25: censo carlosapp
A26: total | B26: =SUM(B24:B25) -> 31000 | C26: =B26*85 -> 2635000 | F26: =40000*80 -> 3200000
B29: TOTAL | C29: =B14+C22+C26+C14 -> 17954700
B34: CARLOSAPP | C34: CMJRADICAL | D34: PACTO | E34: SIEMBRA20 | F34: VARELA | G34: SOMOS C | H34: BTURA | I34: L-103 | K34: TOTAL MENSUAL
A35: ENERO | B35: 1000000 | C35: 500000 | D35: - | E35: - | F35: - | G35: - | H35: - | I35: - | K35: =SUM(B35:J35) -> 1500000
A36: FEBRERO | B36: 1000000 | C36: - | D36: - | E36: - | F36: - | G36: - | H36: - | I36: - | K36: =SUM(B36:J36) -> 1000000 | L36: 3200000
A37: MARZO | B37: 1000000 | C37: - | D37: - | E37: - | F37: - | G37: - | H37: - | I37: - | K37: =SUM(B37:J37) -> 1000000 | L37: =25000*100 -> 2500000
A38: ABRIL | B38: - | D38: - | E38: - | F38: - | G38: - | H38: - | I38: - | K38: =SUM(B38:J38) -> 0
A39: MAYO | B39: - | D39: - | E39: - | F39: - | G39: - | H39: - | I39: - | K39: =SUM(B39:J39) -> 0 | L39: =20000*80 -> 1600000
A40: JUNIO | B40: - | D40: - | E40: - | F40: - | G40: - | H40: - | I40: - | K40: =SUM(B40:J40) -> 0 | L40: =20000*100 -> 2000000
A41: JULIO | B41: - | D41: - | E41: - | F41: - | G41: - | H41: - | I41: - | K41: =SUM(B41:J41) -> 0 | M41: =30000000/60000 -> 500
A42: AGOSTO | B42: - | D42: - | E42: - | F42: - | G42: - | H42: - | I42: - | K42: =SUM(B42:J42) -> 0
A43: SEPTIEMBRE | B43: - | D43: - | E43: - | F43: - | G43: - | H43: - | I43: - | K43: =SUM(B43:J43) -> 0 | L43: =50000*100 -> 5000000
A44: OCTUBRE | B44: - | D44: - | E44: - | F44: - | G44: - | H44: - | I44: - | K44: =SUM(B44:J44) -> 0
A45: NOVIEMBRE | B45: - | D45: - | E45: - | F45: - | G45: - | H45: - | I45: - | K45: =SUM(B45:J45) -> 0
A46: DICIEMBRE | B46: - | D46: - | E46: - | F46: - | G46: - | H46: - | I46: - | K46: =SUM(B46:J46) -> 0
B47: =SUM(B35:B46) -> 3000000 | C47: =SUM(C35:C46) -> 500000 | D47: =SUM(D35:D46) -> 0 | E47: =SUM(E35:E46) -> 0 | F47: =SUM(F35:F46) -> 0 | G47: =SUM(G35:G46) -> 0 | J47: =SUM(J35:J46) -> 0 | K47: =SUM(B47:J47) -> 3500000 | M47: =K47+C29 -> 21454700
A50: 36602 X 100 | B50: =36602*100 -> 3660200 | C50: Ingreso Fya Carlos Hernan
A51: 77507 X 100 | B51: =77507*100 -> 7750700 | C51: Ingreso Fya Carlos Hernan
A52: 138027 X 80 | B52: =138027*80 -> 11042160 | C52: censo carlosapp | M52: =300 -> 300
A53: 40000 X 100 | B53: =40000*100 -> 4000000 | C53: Dia electoral - puesto | M53: 40000
A54: total | B54: =SUM(B50:B53) -> 26453060 | C54: =B54*85 -> 2248510100 | M54: =M53/M52 -> 133.33333
B56: TOTAL | C56: =B47+C47+B54 -> 29953060
A59: TOTAL CORTE A DICIEMBRE | C59: =C29 -> 17954700
A60: TOTAL CORTE A MARZO | C60: =C56 -> 29953060
A61: TOTAL CAMPAÑA | C61: =C59+C60 -> 47907760
B64: CRUCE | C64: 24000000
B65: SALDO | C65: =C61-C64 -> 23907760
B67: abono junio | C67: =4000000 -> 4000000
B68: abono julio | C68: 0
B69: abono agosto | C69: 0
C70: 0
B72: SALDO | C72: =C65-(C67+C68+C69+C70) -> 19907760

Sheet INFORME GASTOS
A1: AÑO | B1: 2024
B2: 1 | C2: 2 | D2: 3 | E2: 4 | F2: 5 | G2: 6 | H2: 7 | I2: 8 | J2: 9 | K2: 10 | L2: 11 | M2: 12
A3: TIPO GASTO | B3: ENERO | C3: FEBRERO | D3: MARZO | E3: ABRIL | F3: MAYO | G3: JUNIO | H3: JULIO | I3: AGOSTO | J3: SEPTIEMBRE | K3: OCTUBRE | L3: NOVIEMBRE | M3: DICIEMBRE
A4: almuerzo | B4: =SUMIFS(GASTOS!$F:$F,GASTOS!$I:$I,'INFORME GASTOS'!$A4,GASTOS!$B:$B,$B$1,GASTOS!$C:$C,B$2) -> 469000 | C4: =SUMIFS(GASTOS!$F:$F,GASTOS!$I:$I,'INFORME GASTOS'!$A4,GASTOS!$B:$B,$B$1,GASTOS!$C:$C,C$2) -> 792000 | D4: =SUMIFS(GASTOS!$F:$F,GASTOS!$I:$I,'INFORME GASTOS'!$A4,GASTOS!$B:$B,$B$1,GASTOS!$C:$C,D$2) -> 614000 | E4: =SUMIFS(GASTOS!$F:$F,GASTOS!$I:$I,'INFORME GASTOS'!$A4,GASTOS!$B:$B,$B$1,GASTOS!$C:$C,E$2) -> 435000 | F4: =SUMIFS(GASTOS!$F:$F,GASTOS!$I:$I,'INFORME GASTOS'!$A4,GASTOS!$B:$B,$B$1,GASTOS!$C:$C,F$2) -> 580000 | G4: =SUMIFS(GASTOS!$F:$F,GASTOS!$I:$I,'INFORME GASTOS'!$A4,GASTOS!$B:$B,$B$1,GASTOS!$C:$C,G$2) -> 498000 | H4: =SUMIFS(GASTOS!$F:$F,GASTOS!$I:$I,'INFORME GASTOS'!$A4,GASTOS!$B:$B,$B$1,GASTOS!$C:$C,H$2) -> 125000 | I4: =SUMIFS(GASTOS!$F:$F,GASTOS!$I:$I,'INFORME GASTOS'!$A4,GASTOS!$B:$B,$B$1,GASTOS!$C:$C,I$2) -> 346000 | ... M4: =SUMIFS(GASTOS!$F:$F,GASTOS!$I:$I,'INFORME GASTOS'!$A4,GASTOS!$B:$B,$B$1,GASTOS!$C:$C,M$2) -> 425000
A5: MERCADO | B5: =SUMIFS(GASTOS!$F:$F,GASTOS!$I:$I,'INFORME GASTOS'!$A5,GASTOS!$B:$B,$B$1,GASTOS!$C:$C,B$2) -> 605000 | C5: =SUMIFS(GASTOS!$F:$F,GASTOS!$I:$I,'INFORME GASTOS'!$A5,GASTOS!$B:$B,$B$1,GASTOS!$C:$C,C$2) -> 580500 | D5: =SUMIFS(GASTOS!$F:$F,GASTOS!$I:$I,'INFORME GASTOS'!$A5,GASTOS!$B:$B,$B$1,GASTOS!$C:$C,D$2) -> 519000 | E5: =SUMIFS(GASTOS!$F:$F,GASTOS!$I:$I,'INFORME GASTOS'!$A5,GASTOS!$B:$B,$B$1,GASTOS!$C:$C,E$2) -> 190000 | F5: =SUMIFS(GASTOS!$F:$F,GASTOS!$I:$I,'INFORME GASTOS'!$A5,GASTOS!$B:$B,$B$1,GASTOS!$C:$C,F$2) -> 526000 | G5: =SUMIFS(GASTOS!$F:$F,GASTOS!$I:$I,'INFORME GASTOS'!$A5,GASTOS!$B:$B,$B$1,GASTOS!$C:$C,G$2) -> 469000 | H5: =SUMIFS(GASTOS!$F:$F,GASTOS!$I:$I,'INFORME GASTOS'!$A5,GASTOS!$B:$B,$B$1,GASTOS!$C:$C,H$2) -> 606000 | I5: =SUMIFS(GASTOS!$F:$F,GASTOS!$I:$I,'INFORME GASTOS'!$A5,GASTOS!$B:$B,$B$1,GASTOS!$C:$C,I$2) -> 550000 | ... M5: =SUMIFS(GASTOS!$F:$F,GASTOS!$I:$I,'INFORME GASTOS'!$A5,GASTOS!$B:$B,$B$1,GASTOS!$C:$C,M$2) -> 320000
A6: OTROS | B6: =SUMIFS(GASTOS!$F:$F,GASTOS!$I:$I,'INFORME GASTOS'!$A6,GASTOS!$B:$B,$B$1,GASTOS!$C:$C,B$2) -> 1662000 | C6: =SUMIFS(GASTOS!$F:$F,GASTOS!$I:$I,'INFORME GASTOS'!$A6,GASTOS!$B:$B,$B$1,GASTOS!$C:$C,C$2) -> 780000 | D6: =SUMIFS(GASTOS!$F:$F,GASTOS!$I:$I,'INFORME GASTOS'!$A6,GASTOS!$B:$B,$B$1,GASTOS!$C:$C,D$2) -> 1566000 | E6: =SUMIFS(GASTOS!$F:$F,GASTOS!$I:$I,'INFORME GASTOS'!$A6,GASTOS!$B:$B,$B$1,GASTOS!$C:$C,E$2) -> 929000 | F6: =SUMIFS(GASTOS!$F:$F,GASTOS!$I:$I,'INFORME GASTOS'!$A6,GASTOS!$B:$B,$B$1,GASTOS!$C:$C,F$2) -> 2589000 | G6: =SUMIFS(GASTOS!$F:$F,GASTOS!$I:$I,'INFORME GASTOS'!$A6,GASTOS!$B:$B,$B$1,GASTOS!$C:$C,G$2) -> 2800000 | H6: =SUMIFS(GASTOS!$F:$F,GASTOS!$I:$I,'INFORME GASTOS'!$A6,GASTOS!$B:$B,$B$1,GASTOS!$C:$C,H$2) -> 1192000 | I6: =SUMIFS(GASTOS!$F:$F,GASTOS!$I:$I,'INFORME GASTOS'!$A6,GASTOS!$B:$B,$B$1,GASTOS!$C:$C,I$2) -> 837000 | ... M6: =SUMIFS(GASTOS!$F:$F,GASTOS!$I:$I,'INFORME GASTOS'!$A6,GASTOS!$B:$B,$B$1,GASTOS!$C:$C,M$2) -> 3515000
A7: NIÑOS | B7: =SUMIFS(GASTOS!$F:$F,GASTOS!$I:$I,'INFORME GASTOS'!$A7,GASTOS!$B:$B,$B$1,GASTOS!$C:$C,B$2) -> 757000 | C7: =SUMIFS(GASTOS!$F:$F,GASTOS!$I:$I,'INFORME GASTOS'!$A7,GASTOS!$B:$B,$B$1,GASTOS!$C:$C,C$2) -> 823000 | D7: =SUMIFS(GASTOS!$F:$F,GASTOS!$I:$I,'INFORME GASTOS'!$A7,GASTOS!$B:$B,$B$1,GASTOS!$C:$C,D$2) -> 1248000 | E7: =SUMIFS(GASTOS!$F:$F,GASTOS!$I:$I,'INFORME GASTOS'!$A7,GASTOS!$B:$B,$B$1,GASTOS!$C:$C,E$2) -> 821000 | F7: =SUMIFS(GASTOS!$F:$F,GASTOS!$I:$I,'INFORME GASTOS'!$A7,GASTOS!$B:$B,$B$1,GASTOS!$C:$C,F$2) -> 750000 | G7: =SUMIFS(GASTOS!$F:$F,GASTOS!$I:$I,'INFORME GASTOS'!$A7,GASTOS!$B:$B,$B$1,GASTOS!$C:$C,G$2) -> 563000 | H7: =SUMIFS(GASTOS!$F:$F,GASTOS!$I:$I,'INFORME GASTOS'!$A7,GASTOS!$B:$B,$B$1,GASTOS!$C:$C,H$2) -> 662000 | I7: =SUMIFS(GASTOS!$F:$F,GASTOS!$I:$I,'INFORME GASTOS'!$A7,GASTOS!$B:$B,$B$1,GASTOS!$C:$C,I$2) -> 800000 | ... M7: =SUMIFS(GASTOS!$F:$F,GASTOS!$I:$I,'INFORME GASTOS'!$A7,GASTOS!$B:$B,$B$1,GASTOS!$C:$C,M$2) -> 2772000
A8: salidas | B8: =SUMIFS(GASTOS!$F:$F,GASTOS!$I:$I,'INFORME GASTOS'!$A8,GASTOS!$B:$B,$B$1,GASTOS!$C:$C,B$2) -> 949000 | C8: =SUMIFS(GASTOS!$F:$F,GASTOS!$I:$I,'INFORME GASTOS'!$A8,GASTOS!$B:$B,$B$1,GASTOS!$C:$C,C$2) -> 1324000 | D8: =SUMIFS(GASTOS!$F:$F,GASTOS!$I:$I,'INFORME GASTOS'!$A8,GASTOS!$B:$B,$B$1,GASTOS!$C:$C,D$2) -> 729000 | E8: =SUMIFS(GASTOS!$F:$F,GASTOS!$I:$I,'INFORME GASTOS'!$A8,GASTOS!$B:$B,$B$1,GASTOS!$C:$C,E$2) -> 1266000 | F8: =SUMIFS(GASTOS!$F:$F,GASTOS!$I:$I,'INFORME GASTOS'!$A8,GASTOS!$B:$B,$B$1,GASTOS!$C:$C,F$2) -> 996000 | G8: =SUMIFS(GASTOS!$F:$F,GASTOS!$I:$I,'INFORME GASTOS'!$A8,GASTOS!$B:$B,$B$1,GASTOS!$C:$C,G$2) -> 1210000 | H8: =SUMIFS(GASTOS!$F:$F,GASTOS!$I:$I,'INFORME GASTOS'!$A8,GASTOS!$B:$B,$B$1,GASTOS!$C:$C,H$2) -> 1220000 | I8: =SUMIFS(GASTOS!$F:$F,GASTOS!$I:$I,'INFORME GASTOS'!$A8,GASTOS!$B:$B,$B$1,GASTOS!$C:$C,I$2) -> 450000 | ... M8: =SUMIFS(GASTOS!$F:$F,GASTOS!$I:$I,'INFORME GASTOS'!$A8,GASTOS!$B:$B,$B$1,GASTOS!$C:$C,M$2) -> 60000
A9: parqueadero | B9: =SUMIFS(GASTOS!$F:$F,GASTOS!$I:$I,'INFORME GASTOS'!$A9,GASTOS!$B:$B,$B$1,GASTOS!$C:$C,B$2) -> 423000 | C9: =SUMIFS(GASTOS!$F:$F,GASTOS!$I:$I,'INFORME GASTOS'!$A9,GASTOS!$B:$B,$B$1,GASTOS!$C:$C,C$2) -> 234000 | D9: =SUMIFS(GASTOS!$F:$F,GASTOS!$I:$I,'INFORME GASTOS'!$A9,GASTOS!$B:$B,$B$1,GASTOS!$C:$C,D$2) -> 310000 | E9: =SUMIFS(GASTOS!$F:$F,GASTOS!$I:$I,'INFORME GASTOS'!$A9,GASTOS!$B:$B,$B$1,GASTOS!$C:$C,E$2) -> 274000 | F9: =SUMIFS(GASTOS!$F:$F,GASTOS!$I:$I,'INFORME GASTOS'!$A9,GASTOS!$B:$B,$B$1,GASTOS!$C:$C,F$2) -> 225000 | G9: =SUMIFS(GASTOS!$F:$F,GASTOS!$I:$I,'INFORME GASTOS'!$A9,GASTOS!$B:$B,$B$1,GASTOS!$C:$C,G$2) -> 142000 | H9: =SUMIFS(GASTOS!$F:$F,GASTOS!$I:$I,'INFORME GASTOS'!$A9,GASTOS!$B:$B,$B$1,GASTOS!$C:$C,H$2) -> 67000 | I9: =SUMIFS(GASTOS!$F:$F,GASTOS!$I:$I,'INFORME GASTOS'!$A9,GASTOS!$B:$B,$B$1,GASTOS!$C:$C,I$2) -> 74000 | ... M9: =SUMIFS(GASTOS!$F:$F,GASTOS!$I:$I,'INFORME GASTOS'!$A9,GASTOS!$B:$B,$B$1,GASTOS!$C:$C,M$2) -> 157000
A10: empresa | B10: =SUMIFS(GASTOS!$F:$F,GASTOS!$I:$I,'INFORME GASTOS'!$A10,GASTOS!$B:$B,$B$1,GASTOS!$C:$C,B$2) -> 652000 | C10: =SUMIFS(GASTOS!$F:$F,GASTOS!$I:$I,'INFORME GASTOS'!$A10,GASTOS!$B:$B,$B$1,GASTOS!$C:$C,C$2) -> 599000 | D10: =SUMIFS(GASTOS!$F:$F,GASTOS!$I:$I,'INFORME GASTOS'!$A10,GASTOS!$B:$B,$B$1,GASTOS!$C:$C,D$2) -> 456000 | E10: =SUMIFS(GASTOS!$F:$F,GASTOS!$I:$I,'INFORME GASTOS'!$A10,GASTOS!$B:$B,$B$1,GASTOS!$C:$C,E$2) -> 285000 | F10: =SUMIFS(GASTOS!$F:$F,GASTOS!$I:$I,'INFORME GASTOS'!$A10,GASTOS!$B:$B,$B$1,GASTOS!$C:$C,F$2) -> 968000 | G10: =SUMIFS(GASTOS!$F:$F,GASTOS!$I:$I,'INFORME GASTOS'!$A10,GASTOS!$B:$B,$B$1,GASTOS!$C:$C,G$2) -> 817000 | H10: =SUMIFS(GASTOS!$F:$F,GASTOS!$I:$I,'INFORME GASTOS'!$A10,GASTOS!$B:$B,$B$1,GASTOS!$C:$C,H$2) -> 341000 | I10: =SUMIFS(GASTOS!$F:$F,GASTOS!$I:$I,'INFORME GASTOS'!$A10,GASTOS!$B:$B,$B$1,GASTOS!$C:$C,I$2) -> 0 | ... M10: =SUMIFS(GASTOS!$F:$F,GASTOS!$I:$I,'INFORME GASTOS'!$A10,GASTOS!$B:$B,$B$1,GASTOS!$C:$C,M$2) -> 326000
A11: gasolina | B11: =SUMIFS(GASTOS!$F:$F,GASTOS!$I:$I,'INFORME GASTOS'!$A11,GASTOS!$B:$B,$B$1,GASTOS!$C:$C,B$2) -> 276000 | C11: =SUMIFS(GASTOS!$F:$F,GASTOS!$I:$I,'INFORME GASTOS'!$A11,GASTOS!$B:$B,$B$1,GASTOS!$C:$C,C$2) -> 637000 | D11: =SUMIFS(GASTOS!$F:$F,GASTOS!$I:$I,'INFORME GASTOS'!$A11,GASTOS!$B:$B,$B$1,GASTOS!$C:$C,D$2) -> 340000 | E11: =SUMIFS(GASTOS!$F:$F,GASTOS!$I:$I,'INFORME GASTOS'!$A11,GASTOS!$B:$B,$B$1,GASTOS!$C:$C,E$2) -> 530000 | F11: =SUMIFS(GASTOS!$F:$F,GASTOS!$I:$I,'INFORME GASTOS'!$A11,GASTOS!$B:$B,$B$1,GASTOS!$C:$C,F$2) -> 365000 | G11: =SUMIFS(GASTOS!$F:$F,GASTOS!$I:$I,'INFORME GASTOS'!$A11,GASTOS!$B:$B,$B$1,GASTOS!$C:$C,G$2) -> 417000 | H11: =SUMIFS(GASTOS!$F:$F,GASTOS!$I:$I,'INFORME GASTOS'!$A11,GASTOS!$B:$B,$B$1,GASTOS!$C:$C,H$2) -> 387000 | I11: =SUMIFS(GASTOS!$F:$F,GASTOS!$I:$I,'INFORME GASTOS'!$A11,GASTOS!$B:$B,$B$1,GASTOS!$C:$C,I$2) -> 590000 | ... M11: =SUMIFS(GASTOS!$F:$F,GASTOS!$I:$I,'INFORME GASTOS'!$A11,GASTOS!$B:$B,$B$1,GASTOS!$C:$C,M$2) -> 620000
A12: isabella | B12: =SUMIFS(GASTOS!$F:$F,GASTOS!$I:$I,'INFORME GASTOS'!$A12,GASTOS!$B:$B,$B$1,GASTOS!$C:$C,B$2) -> 1918000 | C12: =SUMIFS(GASTOS!$F:$F,GASTOS!$I:$I,'INFORME GASTOS'!$A12,GASTOS!$B:$B,$B$1,GASTOS!$C:$C,C$2) -> 0 | D12: =SUMIFS(GASTOS!$F:$F,GASTOS!$I:$I,'INFORME GASTOS'!$A12,GASTOS!$B:$B,$B$1,GASTOS!$C:$C,D$2) -> 328000 | E12: =SUMIFS(GASTOS!$F:$F,GASTOS!$I:$I,'INFORME GASTOS'!$A12,GASTOS!$B:$B,$B$1,GASTOS!$C:$C,E$2) -> 150000 | F12: =SUMIFS(GASTOS!$F:$F,GASTOS!$I:$I,'INFORME GASTOS'!$A12,GASTOS!$B:$B,$B$1,GASTOS!$C:$C,F$2) -> 32000 | G12: =SUMIFS(GASTOS!$F:$F,GASTOS!$I:$I,'INFORME GASTOS'!$A12,GASTOS!$B:$B,$B$1,GASTOS!$C:$C,G$2) -> 24000 | H12: =SUMIFS(GASTOS!$F:$F,GASTOS!$I:$I,'INFORME GASTOS'!$A12,GASTOS!$B:$B,$B$1,GASTOS!$C:$C,H$2) -> 120000 | I12: =SUMIFS(GASTOS!$F:$F,GASTOS!$I:$I,'INFORME GASTOS'!$A12,GASTOS!$B:$B,$B$1,GASTOS!$C:$C,I$2) -> 331000 | ... M12: =SUMIFS(GASTOS!$F:$F,GASTOS!$I:$I,'INFORME GASTOS'!$A12,GASTOS!$B:$B,$B$1,GASTOS!$C:$C,M$2) -> 89000
A13: IGLESIA | B13: =SUMIFS(GASTOS!$F:$F,GASTOS!$I:$I,'INFORME GASTOS'!$A13,GASTOS!$B:$B,$B$1,GASTOS!$C:$C,B$2) -> 600000 | C13: =SUMIFS(GASTOS!$F:$F,GASTOS!$I:$I,'INFORME GASTOS'!$A13,GASTOS!$B:$B,$B$1,GASTOS!$C:$C,C$2) -> 1000000 | D13: =SUMIFS(GASTOS!$F:$F,GASTOS!$I:$I,'INFORME GASTOS'!$A13,GASTOS!$B:$B,$B$1,GASTOS!$C:$C,D$2) -> 700000 | E13: =SUMIFS(GASTOS!$F:$F,GASTOS!$I:$I,'INFORME GASTOS'!$A13,GASTOS!$B:$B,$B$1,GASTOS!$C:$C,E$2) -> 0 | F13: =SUMIFS(GASTOS!$F:$F,GASTOS!$I:$I,'INFORME GASTOS'!$A13,GASTOS!$B:$B,$B$1,GASTOS!$C:$C,F$2) -> 700000 | G13: =SUMIFS(GASTOS!$F:$F,GASTOS!$I:$I,'INFORME GASTOS'!$A13,GASTOS!$B:$B,$B$1,GASTOS!$C:$C,G$2) -> 0 | H13: =SUMIFS(GASTOS!$F:$F,GASTOS!$I:$I,'INFORME GASTOS'!$A13,GASTOS!$B:$B,$B$1,GASTOS!$C:$C,H$2) -> 700000 | I13: =SUMIFS(GASTOS!$F:$F,GASTOS!$I:$I,'INFORME GASTOS'!$A13,GASTOS!$B:$B,$B$1,GASTOS!$C:$C,I$2) -> 700000 | ... M13: =SUMIFS(GASTOS!$F:$F,GASTOS!$I:$I,'INFORME GASTOS'!$A13,GASTOS!$B:$B,$B$1,GASTOS!$C:$C,M$2) -> 1000000
A14: cadena | B14: =SUMIFS(GASTOS!$F:$F,GASTOS!$I:$I,'INFORME GASTOS'!$A14,GASTOS!$B:$B,$B$1,GASTOS!$C:$C,B$2) -> 250000 | C14: =SUMIFS(GASTOS!$F:$F,GASTOS!$I:$I,'INFORME GASTOS'!$A14,GASTOS!$B:$B,$B$1,GASTOS!$C:$C,C$2) -> 250000 | D14: =SUMIFS(GASTOS!$F:$F,GASTOS!$I:$I,'INFORME GASTOS'!$A14,GASTOS!$B:$B,$B$1,GASTOS!$C:$C,D$2) -> 250000 | E14: =SUMIFS(GASTOS!$F:$F,GASTOS!$I:$I,'INFORME GASTOS'!$A14,GASTOS!$B:$B,$B$1,GASTOS!$C:$C,E$2) -> 250000 | F14: =SUMIFS(GASTOS!$F:$F,GASTOS!$I:$I,'INFORME GASTOS'!$A14,GASTOS!$B:$B,$B$1,GASTOS!$C:$C,F$2) -> 250000 | G14: =SUMIFS(GASTOS!$F:$F,GASTOS!$I:$I,'INFORME GASTOS'!$A14,GASTOS!$B:$B,$B$1,GASTOS!$C:$C,G$2) -> 250000 | H14: =SUMIFS(GASTOS!$F:$F,GASTOS!$I:$I,'INFORME GASTOS'!$A14,GASTOS!$B:$B,$B$1,GASTOS!$C:$C,H$2) -> 250000 | I14: =SUMIFS(GASTOS!$F:$F,GASTOS!$I:$I,'INFORME GASTOS'!$A14,GASTOS!$B:$B,$B$1,GASTOS!$C:$C,I$2) -> 250000 | ... M14: =SUMIFS(GASTOS!$F:$F,GASTOS!$I:$I,'INFORME GASTOS'!$A14,GASTOS!$B:$B,$B$1,GASTOS!$C:$C,M$2) -> 0
A15: ASEO | B15: =SUMIFS(GASTOS!$F:$F,GASTOS!$I:$I,'INFORME GASTOS'!$A15,GASTOS!$B:$B,$B$1,GASTOS!$C:$C,B$2) -> 50000 | C15: =SUMIFS(GASTOS!$F:$F,GASTOS!$I:$I,'INFORME GASTOS'!$A15,GASTOS!$B:$B,$B$1,GASTOS!$C:$C,C$2) -> 40000 | D15: =SUMIFS(GASTOS!$F:$F,GASTOS!$I:$I,'INFORME GASTOS'!$A15,GASTOS!$B:$B,$B$1,GASTOS!$C:$C,D$2) -> 247500 | E15: =SUMIFS(GASTOS!$F:$F,GASTOS!$I:$I,'INFORME GASTOS'!$A15,GASTOS!$B:$B,$B$1,GASTOS!$C:$C,E$2) -> 220000 | F15: =SUMIFS(GASTOS!$F:$F,GASTOS!$I:$I,'INFORME GASTOS'!$A15,GASTOS!$B:$B,$B$1,GASTOS!$C:$C,F$2) -> 80000 | G15: =SUMIFS(GASTOS!$F:$F,GASTOS!$I:$I,'INFORME GASTOS'!$A15,GASTOS!$B:$B,$B$1,GASTOS!$C:$C,G$2) -> 60000 | H15: =SUMIFS(GASTOS!$F:$F,GASTOS!$I:$I,'INFORME GASTOS'!$A15,GASTOS!$B:$B,$B$1,GASTOS!$C:$C,H$2) -> 50000 | I15: =SUMIFS(GASTOS!$F:$F,GASTOS!$I:$I,'INFORME GASTOS'!$A15,GASTOS!$B:$B,$B$1,GASTOS!$C:$C,I$2) -> 0 | ... M15: =SUMIFS(GASTOS!$F:$F,GASTOS!$I:$I,'INFORME GASTOS'!$A15,GASTOS!$B:$B,$B$1,GASTOS!$C:$C,M$2) -> 0
... A21: ENTRADA | B21: =SUMIFS(GASTOS!$F:$F,GASTOS!$I:$I,'INFORME GASTOS'!$A21,GASTOS!$B:$B,$B$1,GASTOS!$C:$C,B$2) -> 0 | C21: =SUMIFS(GASTOS!$F:$F,GASTOS!$I:$I,'INFORME GASTOS'!$A21,GASTOS!$B:$B,$B$1,GASTOS!$C:$C,C$2) -> 0 | D21: =SUMIFS(GASTOS!$F:$F,GASTOS!$I:$I,'INFORME GASTOS'!$A21,GASTOS!$B:$B,$B$1,GASTOS!$C:$C,D$2) -> 0 | E21: =SUMIFS(GASTOS!$F:$F,GASTOS!$I:$I,'INFORME GASTOS'!$A21,GASTOS!$B:$B,$B$1,GASTOS!$C:$C,E$2) -> 0 | F21: =SUMIFS(GASTOS!$F:$F,GASTOS!$I:$I,'INFORME GASTOS'!$A21,GASTOS!$B:$B,$B$1,GASTOS!$C:$C,F$2) -> 0 | G21: =SUMIFS(GASTOS!$F:$F,GASTOS!$I:$I,'INFORME GASTOS'!$A21,GASTOS!$B:$B,$B$1,GASTOS!$C:$C,G$2) -> 0 | H21: =SUMIFS(GASTOS!$F:$F,GASTOS!$I:$I,'INFORME GASTOS'!$A21,GASTOS!$B:$B,$B$1,GASTOS!$C:$C,H$2) -> 0 | I21: =SUMIFS(GASTOS!$F:$F,GASTOS!$I:$I,'INFORME GASTOS'!$A21,GASTOS!$B:$B,$B$1,GASTOS!$C:$C,I$2) -> 0 | ... M21: =SUMIFS(GASTOS!$F:$F,GASTOS!$I:$I,'INFORME GASTOS'!$A21,GASTOS!$B:$B,$B$1,GASTOS!$C:$C,M$2) -> 0
B22: =SUM(B5:B21) -> 8503200 | C22: =SUM(C5:C21) -> 6671000 | D22: =SUM(D5:D21) -> 6892500 | E22: =SUM(E5:E21) -> 5383000 | F22: =SUM(F5:F21) -> 7711000 | G22: =SUM(G5:G21) -> 6805000 | H22: =SUM(H5:H21) -> 6599000 | I22: =SUM(I5:I21) -> 5310600 | ... M22: =SUM(M5:M21) -> 10011000
A25: AÑO | B25: 2026
B26: 1 | C26: 2 | D26: 3 | E26: 4 | F26: 5 | G26: 6 | H26: 7 | I26: 8 | J26: 9 | K26: 10 | L26: 11 | M26: 12
A27: TIPO GASTO | B27: ENERO | C27: FEBRERO | D27: MARZO | E27: ABRIL | F27: MAYO | G27: JUNIO | H27: JULIO | I27: AGOSTO | J27: SEPTIEMBRE | K27: OCTUBRE | L27: NOVIEMBRE | M27: DICIEMBRE
A28: almuerzo | B28: =SUMIFS(GASTOS!$F:$F,GASTOS!$I:$I,'INFORME GASTOS'!$A28,GASTOS!$B:$B,$B$25,GASTOS!$C:$C,B$2) -> 638000 | C28: =SUMIFS(GASTOS!$F:$F,GASTOS!$I:$I,'INFORME GASTOS'!$A28,GASTOS!$B:$B,$B$25,GASTOS!$C:$C,C$2) -> 584000 | D28: =SUMIFS(GASTOS!$F:$F,GASTOS!$I:$I,'INFORME GASTOS'!$A28,GASTOS!$B:$B,$B$25,GASTOS!$C:$C,D$2) -> 309000 | E28: =SUMIFS(GASTOS!$F:$F,GASTOS!$I:$I,'INFORME GASTOS'!$A28,GASTOS!$B:$B,$B$25,GASTOS!$C:$C,E$2) -> 210000 | F28: =SUMIFS(GASTOS!$F:$F,GASTOS!$I:$I,'INFORME GASTOS'!$A28,GASTOS!$B:$B,$B$25,GASTOS!$C:$C,F$2) -> 1249000 | G28: =SUMIFS(GASTOS!$F:$F,GASTOS!$I:$I,'INFORME GASTOS'!$A28,GASTOS!$B:$B,$B$25,GASTOS!$C:$C,G$2) -> 116000 | H28: =SUMIFS(GASTOS!$F:$F,GASTOS!$I:$I,'INFORME GASTOS'!$A28,GASTOS!$B:$B,$B$25,GASTOS!$C:$C,H$2) -> 0 | I28: =SUMIFS(GASTOS!$F:$F,GASTOS!$I:$I,'INFORME GASTOS'!$A28,GASTOS!$B:$B,$B$25,GASTOS!$C:$C,I$2) -> 0 | ... M28: =SUMIFS(GASTOS!$F:$F,GASTOS!$I:$I,'INFORME GASTOS'!$A28,GASTOS!$B:$B,$B$25,GASTOS!$C:$C,M$2) -> 725000
A29: MERCADO | B29: =SUMIFS(GASTOS!$F:$F,GASTOS!$I:$I,'INFORME GASTOS'!$A29,GASTOS!$B:$B,$B$25,GASTOS!$C:$C,B$2) -> 1430000 | C29: =SUMIFS(GASTOS!$F:$F,GASTOS!$I:$I,'INFORME GASTOS'!$A29,GASTOS!$B:$B,$B$25,GASTOS!$C:$C,C$2) -> 0 | D29: =SUMIFS(GASTOS!$F:$F,GASTOS!$I:$I,'INFORME GASTOS'!$A29,GASTOS!$B:$B,$B$25,GASTOS!$C:$C,D$2) -> 972000 | E29: =SUMIFS(GASTOS!$F:$F,GASTOS!$I:$I,'INFORME GASTOS'!$A29,GASTOS!$B:$B,$B$25,GASTOS!$C:$C,E$2) -> 1856000 | F29: =SUMIFS(GASTOS!$F:$F,GASTOS!$I:$I,'INFORME GASTOS'!$A29,GASTOS!$B:$B,$B$25,GASTOS!$C:$C,F$2) -> 678000 | G29: =SUMIFS(GASTOS!$F:$F,GASTOS!$I:$I,'INFORME GASTOS'!$A29,GASTOS!$B:$B,$B$25,GASTOS!$C:$C,G$2) -> 728000 | H29: =SUMIFS(GASTOS!$F:$F,GASTOS!$I:$I,'INFORME GASTOS'!$A29,GASTOS!$B:$B,$B$25,GASTOS!$C:$C,H$2) -> 0 | I29: =SUMIFS(GASTOS!$F:$F,GASTOS!$I:$I,'INFORME GASTOS'!$A29,GASTOS!$B:$B,$B$25,GASTOS!$C:$C,I$2) -> 0 | ... M29: =SUMIFS(GASTOS!$F:$F,GASTOS!$I:$I,'INFORME GASTOS'!$A29,GASTOS!$B:$B,$B$25,GASTOS!$C:$C,M$2) -> 680000
A30: OTROS | B30: =SUMIFS(GASTOS!$F:$F,GASTOS!$I:$I,'INFORME GASTOS'!$A30,GASTOS!$B:$B,$B$25,GASTOS!$C:$C,B$2) -> 1158000 | C30: =SUMIFS(GASTOS!$F:$F,GASTOS!$I:$I,'INFORME GASTOS'!$A30,GASTOS!$B:$B,$B$25,GASTOS!$C:$C,C$2) -> 6830000 | D30: =SUMIFS(GASTOS!$F:$F,GASTOS!$I:$I,'INFORME GASTOS'!$A30,GASTOS!$B:$B,$B$25,GASTOS!$C:$C,D$2) -> 7198000 | E30: =SUMIFS(GASTOS!$F:$F,GASTOS!$I:$I,'INFORME GASTOS'!$A30,GASTOS!$B:$B,$B$25,GASTOS!$C:$C,E$2) -> 3603000 | F30: =SUMIFS(GASTOS!$F:$F,GASTOS!$I:$I,'INFORME GASTOS'!$A30,GASTOS!$B:$B,$B$25,GASTOS!$C:$C,F$2) -> 1753000 | G30: =SUMIFS(GASTOS!$F:$F,GASTOS!$I:$I,'INFORME GASTOS'!$A30,GASTOS!$B:$B,$B$25,GASTOS!$C:$C,G$2) -> 1389000 | H30: =SUMIFS(GASTOS!$F:$F,GASTOS!$I:$I,'INFORME GASTOS'!$A30,GASTOS!$B:$B,$B$25,GASTOS!$C:$C,H$2) -> 0 | I30: =SUMIFS(GASTOS!$F:$F,GASTOS!$I:$I,'INFORME GASTOS'!$A30,GASTOS!$B:$B,$B$25,GASTOS!$C:$C,I$2) -> 0 | ... M30: =SUMIFS(GASTOS!$F:$F,GASTOS!$I:$I,'INFORME GASTOS'!$A30,GASTOS!$B:$B,$B$25,GASTOS!$C:$C,M$2) -> 6073000
A31: NIÑOS | B31: =SUMIFS(GASTOS!$F:$F,GASTOS!$I:$I,'INFORME GASTOS'!$A31,GASTOS!$B:$B,$B$25,GASTOS!$C:$C,B$2) -> 1198000 | C31: =SUMIFS(GASTOS!$F:$F,GASTOS!$I:$I,'INFORME GASTOS'!$A31,GASTOS!$B:$B,$B$25,GASTOS!$C:$C,C$2) -> 480000 | D31: =SUMIFS(GASTOS!$F:$F,GASTOS!$I:$I,'INFORME GASTOS'!$A31,GASTOS!$B:$B,$B$25,GASTOS!$C:$C,D$2) -> 0 | E31: =SUMIFS(GASTOS!$F:$F,GASTOS!$I:$I,'INFORME GASTOS'!$A31,GASTOS!$B:$B,$B$25,GASTOS!$C:$C,E$2) -> 1050000 | F31: =SUMIFS(GASTOS!$F:$F,GASTOS!$I:$I,'INFORME GASTOS'!$A31,GASTOS!$B:$B,$B$25,GASTOS!$C:$C,F$2) -> 697000 | G31: =SUMIFS(GASTOS!$F:$F,GASTOS!$I:$I,'INFORME GASTOS'!$A31,GASTOS!$B:$B,$B$25,GASTOS!$C:$C,G$2) -> 1070000 | H31: =SUMIFS(GASTOS!$F:$F,GASTOS!$I:$I,'INFORME GASTOS'!$A31,GASTOS!$B:$B,$B$25,GASTOS!$C:$C,H$2) -> 0 | I31: =SUMIFS(GASTOS!$F:$F,GASTOS!$I:$I,'INFORME GASTOS'!$A31,GASTOS!$B:$B,$B$25,GASTOS!$C:$C,I$2) -> 0 | ... M31: =SUMIFS(GASTOS!$F:$F,GASTOS!$I:$I,'INFORME GASTOS'!$A31,GASTOS!$B:$B,$B$25,GASTOS!$C:$C,M$2) -> 2114000
A32: salidas | B32: =SUMIFS(GASTOS!$F:$F,GASTOS!$I:$I,'INFORME GASTOS'!$A32,GASTOS!$B:$B,$B$25,GASTOS!$C:$C,B$2) -> 457000 | C32: =SUMIFS(GASTOS!$F:$F,GASTOS!$I:$I,'INFORME GASTOS'!$A32,GASTOS!$B:$B,$B$25,GASTOS!$C:$C,C$2) -> 205000 | D32: =SUMIFS(GASTOS!$F:$F,GASTOS!$I:$I,'INFORME GASTOS'!$A32,GASTOS!$B:$B,$B$25,GASTOS!$C:$C,D$2) -> 109000 | E32: =SUMIFS(GASTOS!$F:$F,GASTOS!$I:$I,'INFORME GASTOS'!$A32,GASTOS!$B:$B,$B$25,GASTOS!$C:$C,E$2) -> 550000 | F32: =SUMIFS(GASTOS!$F:$F,GASTOS!$I:$I,'INFORME GASTOS'!$A32,GASTOS!$B:$B,$B$25,GASTOS!$C:$C,F$2) -> 679000 | G32: =SUMIFS(GASTOS!$F:$F,GASTOS!$I:$I,'INFORME GASTOS'!$A32,GASTOS!$B:$B,$B$25,GASTOS!$C:$C,G$2) -> 340000 | H32: =SUMIFS(GASTOS!$F:$F,GASTOS!$I:$I,'INFORME GASTOS'!$A32,GASTOS!$B:$B,$B$25,GASTOS!$C:$C,H$2) -> 0 | I32: =SUMIFS(GASTOS!$F:$F,GASTOS!$I:$I,'INFORME GASTOS'!$A32,GASTOS!$B:$B,$B$25,GASTOS!$C:$C,I$2) -> 0 | ... M32: =SUMIFS(GASTOS!$F:$F,GASTOS!$I:$I,'INFORME GASTOS'!$A32,GASTOS!$B:$B,$B$25,GASTOS!$C:$C,M$2) -> 1684000
A33: parqueadero | B33: =SUMIFS(GASTOS!$F:$F,GASTOS!$I:$I,'INFORME GASTOS'!$A33,GASTOS!$B:$B,$B$25,GASTOS!$C:$C,B$2) -> 24000 | C33: =SUMIFS(GASTOS!$F:$F,GASTOS!$I:$I,'INFORME GASTOS'!$A33,GASTOS!$B:$B,$B$25,GASTOS!$C:$C,C$2) -> 173000 | D33: =SUMIFS(GASTOS!$F:$F,GASTOS!$I:$I,'INFORME GASTOS'!$A33,GASTOS!$B:$B,$B$25,GASTOS!$C:$C,D$2) -> 0 | E33: =SUMIFS(GASTOS!$F:$F,GASTOS!$I:$I,'INFORME GASTOS'!$A33,GASTOS!$B:$B,$B$25,GASTOS!$C:$C,E$2) -> 0 | F33: =SUMIFS(GASTOS!$F:$F,GASTOS!$I:$I,'INFORME GASTOS'!$A33,GASTOS!$B:$B,$B$25,GASTOS!$C:$C,F$2) -> 0 | G33: =SUMIFS(GASTOS!$F:$F,GASTOS!$I:$I,'INFORME GASTOS'!$A33,GASTOS!$B:$B,$B$25,GASTOS!$C:$C,G$2) -> 0 | H33: =SUMIFS(GASTOS!$F:$F,GASTOS!$I:$I,'INFORME GASTOS'!$A33,GASTOS!$B:$B,$B$25,GASTOS!$C:$C,H$2) -> 0 | I33: =SUMIFS(GASTOS!$F:$F,GASTOS!$I:$I,'INFORME GASTOS'!$A33,GASTOS!$B:$B,$B$25,GASTOS!$C:$C,I$2) -> 0 | ... M33: =SUMIFS(GASTOS!$F:$F,GASTOS!$I:$I,'INFORME GASTOS'!$A33,GASTOS!$B:$B,$B$25,GASTOS!$C:$C,M$2) -> 96000
A34: empresa | B34: =SUMIFS(GASTOS!$F:$F,GASTOS!$I:$I,'INFORME GASTOS'!$A34,GASTOS!$B:$B,$B$25,GASTOS!$C:$C,B$2) -> 1833000 | C34: =SUMIFS(GASTOS!$F:$F,GASTOS!$I:$I,'INFORME GASTOS'!$A34,GASTOS!$B:$B,$B$25,GASTOS!$C:$C,C$2) -> 1044000 | D34: =SUMIFS(GASTOS!$F:$F,GASTOS!$I:$I,'INFORME GASTOS'!$A34,GASTOS!$B:$B,$B$25,GASTOS!$C:$C,D$2) -> 0 | E34: =SUMIFS(GASTOS!$F:$F,GASTOS!$I:$I,'INFORME GASTOS'!$A34,GASTOS!$B:$B,$B$25,GASTOS!$C:$C,E$2) -> 800000 | F34: =SUMIFS(GASTOS!$F:$F,GASTOS!$I:$I,'INFORME GASTOS'!$A34,GASTOS!$B:$B,$B$25,GASTOS!$C:$C,F$2) -> 2390000 | G34: =SUMIFS(GASTOS!$F:$F,GASTOS!$I:$I,'INFORME GASTOS'!$A34,GASTOS!$B:$B,$B$25,GASTOS!$C:$C,G$2) -> 353000 | H34: =SUMIFS(GASTOS!$F:$F,GASTOS!$I:$I,'INFORME GASTOS'!$A34,GASTOS!$B:$B,$B$25,GASTOS!$C:$C,H$2) -> 0 | I34: =SUMIFS(GASTOS!$F:$F,GASTOS!$I:$I,'INFORME GASTOS'!$A34,GASTOS!$B:$B,$B$25,GASTOS!$C:$C,I$2) -> 0 | ... M34: =SUMIFS(GASTOS!$F:$F,GASTOS!$I:$I,'INFORME GASTOS'!$A34,GASTOS!$B:$B,$B$25,GASTOS!$C:$C,M$2) -> 5915000
A35: gasolina | B35: =SUMIFS(GASTOS!$F:$F,GASTOS!$I:$I,'INFORME GASTOS'!$A35,GASTOS!$B:$B,$B$25,GASTOS!$C:$C,B$2) -> 420000 | C35: =SUMIFS(GASTOS!$F:$F,GASTOS!$I:$I,'INFORME GASTOS'!$A35,GASTOS!$B:$B,$B$25,GASTOS!$C:$C,C$2) -> 206000 | D35: =SUMIFS(GASTOS!$F:$F,GASTOS!$I:$I,'INFORME GASTOS'!$A35,GASTOS!$B:$B,$B$25,GASTOS!$C:$C,D$2) -> 426000 | E35: =SUMIFS(GASTOS!$F:$F,GASTOS!$I:$I,'INFORME GASTOS'!$A35,GASTOS!$B:$B,$B$25,GASTOS!$C:$C,E$2) -> 200000 | F35: =SUMIFS(GASTOS!$F:$F,GASTOS!$I:$I,'INFORME GASTOS'!$A35,GASTOS!$B:$B,$B$25,GASTOS!$C:$C,F$2) -> 435000 | G35: =SUMIFS(GASTOS!$F:$F,GASTOS!$I:$I,'INFORME GASTOS'!$A35,GASTOS!$B:$B,$B$25,GASTOS!$C:$C,G$2) -> 230000 | H35: =SUMIFS(GASTOS!$F:$F,GASTOS!$I:$I,'INFORME GASTOS'!$A35,GASTOS!$B:$B,$B$25,GASTOS!$C:$C,H$2) -> 0 | I35: =SUMIFS(GASTOS!$F:$F,GASTOS!$I:$I,'INFORME GASTOS'!$A35,GASTOS!$B:$B,$B$25,GASTOS!$C:$C,I$2) -> 0 | ... M35: =SUMIFS(GASTOS!$F:$F,GASTOS!$I:$I,'INFORME GASTOS'!$A35,GASTOS!$B:$B,$B$25,GASTOS!$C:$C,M$2) -> 470000
A36: isabella | B36: =SUMIFS(GASTOS!$F:$F,GASTOS!$I:$I,'INFORME GASTOS'!$A36,GASTOS!$B:$B,$B$25,GASTOS!$C:$C,B$2) -> 420000 | C36: =SUMIFS(GASTOS!$F:$F,GASTOS!$I:$I,'INFORME GASTOS'!$A36,GASTOS!$B:$B,$B$25,GASTOS!$C:$C,C$2) -> 0 | D36: =SUMIFS(GASTOS!$F:$F,GASTOS!$I:$I,'INFORME GASTOS'!$A36,GASTOS!$B:$B,$B$25,GASTOS!$C:$C,D$2) -> 0 | E36: =SUMIFS(GASTOS!$F:$F,GASTOS!$I:$I,'INFORME GASTOS'!$A36,GASTOS!$B:$B,$B$25,GASTOS!$C:$C,E$2) -> 100000 | F36: =SUMIFS(GASTOS!$F:$F,GASTOS!$I:$I,'INFORME GASTOS'!$A36,GASTOS!$B:$B,$B$25,GASTOS!$C:$C,F$2) -> 0 | G36: =SUMIFS(GASTOS!$F:$F,GASTOS!$I:$I,'INFORME GASTOS'!$A36,GASTOS!$B:$B,$B$25,GASTOS!$C:$C,G$2) -> 0 | H36: =SUMIFS(GASTOS!$F:$F,GASTOS!$I:$I,'INFORME GASTOS'!$A36,GASTOS!$B:$B,$B$25,GASTOS!$C:$C,H$2) -> 0 | I36: =SUMIFS(GASTOS!$F:$F,GASTOS!$I:$I,'INFORME GASTOS'!$A36,GASTOS!$B:$B,$B$25,GASTOS!$C:$C,I$2) -> 0 | ... M36: =SUMIFS(GASTOS!$F:$F,GASTOS!$I:$I,'INFORME GASTOS'!$A36,GASTOS!$B:$B,$B$25,GASTOS!$C:$C,M$2) -> 0
A37: IGLESIA | B37: =SUMIFS(GASTOS!$F:$F,GASTOS!$I:$I,'INFORME GASTOS'!$A37,GASTOS!$B:$B,$B$25,GASTOS!$C:$C,B$2) -> 0 | C37: =SUMIFS(GASTOS!$F:$F,GASTOS!$I:$I,'INFORME GASTOS'!$A37,GASTOS!$B:$B,$B$25,GASTOS!$C:$C,C$2) -> 500000 | D37: =SUMIFS(GASTOS!$F:$F,GASTOS!$I:$I,'INFORME GASTOS'!$A37,GASTOS!$B:$B,$B$25,GASTOS!$C:$C,D$2) -> 0 | E37: =SUMIFS(GASTOS!$F:$F,GASTOS!$I:$I,'INFORME GASTOS'!$A37,GASTOS!$B:$B,$B$25,GASTOS!$C:$C,E$2) -> 0 | F37: =SUMIFS(GASTOS!$F:$F,GASTOS!$I:$I,'INFORME GASTOS'!$A37,GASTOS!$B:$B,$B$25,GASTOS!$C:$C,F$2) -> 0 | G37: =SUMIFS(GASTOS!$F:$F,GASTOS!$I:$I,'INFORME GASTOS'!$A37,GASTOS!$B:$B,$B$25,GASTOS!$C:$C,G$2) -> 0 | H37: =SUMIFS(GASTOS!$F:$F,GASTOS!$I:$I,'INFORME GASTOS'!$A37,GASTOS!$B:$B,$B$25,GASTOS!$C:$C,H$2) -> 0 | I37: =SUMIFS(GASTOS!$F:$F,GASTOS!$I:$I,'INFORME GASTOS'!$A37,GASTOS!$B:$B,$B$25,GASTOS!$C:$C,I$2) -> 0 | ... M37: =SUMIFS(GASTOS!$F:$F,GASTOS!$I:$I,'INFORME GASTOS'!$A37,GASTOS!$B:$B,$B$25,GASTOS!$C:$C,M$2) -> 100000
A38: cadena | B38: =SUMIFS(GASTOS!$F:$F,GASTOS!$I:$I,'INFORME GASTOS'!$A38,GASTOS!$B:$B,$B$25,GASTOS!$C:$C,B$2) -> 0 | C38: =SUMIFS(GASTOS!$F:$F,GASTOS!$I:$I,'INFORME GASTOS'!$A38,GASTOS!$B:$B,$B$25,GASTOS!$C:$C,C$2) -> 0 | D38: =SUMIFS(GASTOS!$F:$F,GASTOS!$I:$I,'INFORME GASTOS'!$A38,GASTOS!$B:$B,$B$25,GASTOS!$C:$C,D$2) -> 0 | E38: =SUMIFS(GASTOS!$F:$F,GASTOS!$I:$I,'INFORME GASTOS'!$A38,GASTOS!$B:$B,$B$25,GASTOS!$C:$C,E$2) -> 0 | F38: =SUMIFS(GASTOS!$F:$F,GASTOS!$I:$I,'INFORME GASTOS'!$A38,GASTOS!$B:$B,$B$25,GASTOS!$C:$C,F$2) -> 0 | G38: =SUMIFS(GASTOS!$F:$F,GASTOS!$I:$I,'INFORME GASTOS'!$A38,GASTOS!$B:$B,$B$25,GASTOS!$C:$C,G$2) -> 0 | H38: =SUMIFS(GASTOS!$F:$F,GASTOS!$I:$I,'INFORME GASTOS'!$A38,GASTOS!$B:$B,$B$25,GASTOS!$C:$C,H$2) -> 0 | I38: =SUMIFS(GASTOS!$F:$F,GASTOS!$I:$I,'INFORME GASTOS'!$A38,GASTOS!$B:$B,$B$25,GASTOS!$C:$C,I$2) -> 0 | ... M38: =SUMIFS(GASTOS!$F:$F,GASTOS!$I:$I,'INFORME GASTOS'!$A38,GASTOS!$B:$B,$B$25,GASTOS!$C:$C,M$2) -> 0
A39: ASEO | B39: =SUMIFS(GASTOS!$F:$F,GASTOS!$I:$I,'INFORME GASTOS'!$A39,GASTOS!$B:$B,$B$25,GASTOS!$C:$C,B$2) -> 0 | C39: =SUMIFS(GASTOS!$F:$F,GASTOS!$I:$I,'INFORME GASTOS'!$A39,GASTOS!$B:$B,$B$25,GASTOS!$C:$C,C$2) -> 0 | D39: =SUMIFS(GASTOS!$F:$F,GASTOS!$I:$I,'INFORME GASTOS'!$A39,GASTOS!$B:$B,$B$25,GASTOS!$C:$C,D$2) -> 0 | E39: =SUMIFS(GASTOS!$F:$F,GASTOS!$I:$I,'INFORME GASTOS'!$A39,GASTOS!$B:$B,$B$25,GASTOS!$C:$C,E$2) -> 0 | F39: =SUMIFS(GASTOS!$F:$F,GASTOS!$I:$I,'INFORME GASTOS'!$A39,GASTOS!$B:$B,$B$25,GASTOS!$C:$C,F$2) -> 0 | G39: =SUMIFS(GASTOS!$F:$F,GASTOS!$I:$I,'INFORME GASTOS'!$A39,GASTOS!$B:$B,$B$25,GASTOS!$C:$C,G$2) -> 0 | H39: =SUMIFS(GASTOS!$F:$F,GASTOS!$I:$I,'INFORME GASTOS'!$A39,GASTOS!$B:$B,$B$25,GASTOS!$C:$C,H$2) -> 0 | I39: =SUMIFS(GASTOS!$F:$F,GASTOS!$I:$I,'INFORME GASTOS'!$A39,GASTOS!$B:$B,$B$25,GASTOS!$C:$C,I$2) -> 0 | ... M39: =SUMIFS(GASTOS!$F:$F,GASTOS!$I:$I,'INFORME GASTOS'!$A39,GASTOS!$B:$B,$B$25,GASTOS!$C:$C,M$2) -> 0
... A44: IMPUESTOS | B44: =SUMIFS(GASTOS!$F:$F,GASTOS!$I:$I,'INFORME GASTOS'!$A44,GASTOS!$B:$B,$B$25,GASTOS!$C:$C,B$2) -> 0 | C44: =SUMIFS(GASTOS!$F:$F,GASTOS!$I:$I,'INFORME GASTOS'!$A44,GASTOS!$B:$B,$B$25,GASTOS!$C:$C,C$2) -> 0 | D44: =SUMIFS(GASTOS!$F:$F,GASTOS!$I:$I,'INFORME GASTOS'!$A44,GASTOS!$B:$B,$B$25,GASTOS!$C:$C,D$2) -> 0 | E44: =SUMIFS(GASTOS!$F:$F,GASTOS!$I:$I,'INFORME GASTOS'!$A44,GASTOS!$B:$B,$B$25,GASTOS!$C:$C,E$2) -> 0 | F44: =SUMIFS(GASTOS!$F:$F,GASTOS!$I:$I,'INFORME GASTOS'!$A44,GASTOS!$B:$B,$B$25,GASTOS!$C:$C,F$2) -> 2660000 | G44: =SUMIFS(GASTOS!$F:$F,GASTOS!$I:$I,'INFORME GASTOS'!$A44,GASTOS!$B:$B,$B$25,GASTOS!$C:$C,G$2) -> 0 | H44: =SUMIFS(GASTOS!$F:$F,GASTOS!$I:$I,'INFORME GASTOS'!$A44,GASTOS!$B:$B,$B$25,GASTOS!$C:$C,H$2) -> 0 | I44: =SUMIFS(GASTOS!$F:$F,GASTOS!$I:$I,'INFORME GASTOS'!$A44,GASTOS!$B:$B,$B$25,GASTOS!$C:$C,I$2) -> 0 | ... M44: =SUMIFS(GASTOS!$F:$F,GASTOS!$I:$I,'INFORME GASTOS'!$A44,GASTOS!$B:$B,$B$25,GASTOS!$C:$C,M$2) -> 0
B45: =SUM(B29:B44) -> 7455000 | C45: =SUM(C29:C44) -> 10643000 | D45: =SUM(D29:D44) -> 8836000 | E45: =SUM(E29:E44) -> 9597000 | F45: =SUM(F29:F44) -> 9794000 | G45: =SUM(G29:G44) -> 5564300 | H45: =SUM(H29:H44) -> 0 | I45: =SUM(I29:I44) -> 0 | ... M45: =SUM(M29:M44) -> 18329000
A48: AÑO | B48: 2026
B49: 1 | C49: 2 | D49: 3 | E49: 4 | F49: 5 | G49: 6 | H49: 7 | I49: 8 | J49: 9 | K49: 10 | L49: 11 | M49: 12
A50: TIPO GASTO | B50: ENERO | C50: FEBRERO | D50: MARZO | E50: ABRIL | F50: MAYO | G50: JUNIO | H50: JULIO | I50: AGOSTO | J50: SEPTIEMBRE | K50: OCTUBRE | L50: NOVIEMBRE | M50: DICIEMBRE
A51: almuerzo | B51: =SUMIFS(GASTOS!$F:$F,GASTOS!$I:$I,'INFORME GASTOS'!$A51,GASTOS!$B:$B,$B$25,GASTOS!$C:$C,B$2) -> 638000 | C51: =SUMIFS(GASTOS!$F:$F,GASTOS!$I:$I,'INFORME GASTOS'!$A51,GASTOS!$B:$B,$B$25,GASTOS!$C:$C,C$2) -> 584000 | D51: =SUMIFS(GASTOS!$F:$F,GASTOS!$I:$I,'INFORME GASTOS'!$A51,GASTOS!$B:$B,$B$25,GASTOS!$C:$C,D$2) -> 309000 | E51: =SUMIFS(GASTOS!$F:$F,GASTOS!$I:$I,'INFORME GASTOS'!$A51,GASTOS!$B:$B,$B$25,GASTOS!$C:$C,E$2) -> 210000 | F51: =SUMIFS(GASTOS!$F:$F,GASTOS!$I:$I,'INFORME GASTOS'!$A51,GASTOS!$B:$B,$B$25,GASTOS!$C:$C,F$2) -> 1249000 | G51: =SUMIFS(GASTOS!$F:$F,GASTOS!$I:$I,'INFORME GASTOS'!$A51,GASTOS!$B:$B,$B$25,GASTOS!$C:$C,G$2) -> 116000 | H51: =SUMIFS(GASTOS!$F:$F,GASTOS!$I:$I,'INFORME GASTOS'!$A51,GASTOS!$B:$B,$B$25,GASTOS!$C:$C,H$2) -> 0 | I51: =SUMIFS(GASTOS!$F:$F,GASTOS!$I:$I,'INFORME GASTOS'!$A51,GASTOS!$B:$B,$B$25,GASTOS!$C:$C,I$2) -> 0 | ... M51: =SUMIFS(GASTOS!$F:$F,GASTOS!$I:$I,'INFORME GASTOS'!$A51,GASTOS!$B:$B,$B$25,GASTOS!$C:$C,M$2) -> 725000
A52: MERCADO | B52: =SUMIFS(GASTOS!$F:$F,GASTOS!$I:$I,'INFORME GASTOS'!$A52,GASTOS!$B:$B,$B$25,GASTOS!$C:$C,B$2) -> 1430000 | C52: =SUMIFS(GASTOS!$F:$F,GASTOS!$I:$I,'INFORME GASTOS'!$A52,GASTOS!$B:$B,$B$25,GASTOS!$C:$C,C$2) -> 0 | D52: =SUMIFS(GASTOS!$F:$F,GASTOS!$I:$I,'INFORME GASTOS'!$A52,GASTOS!$B:$B,$B$25,GASTOS!$C:$C,D$2) -> 972000 | E52: =SUMIFS(GASTOS!$F:$F,GASTOS!$I:$I,'INFORME GASTOS'!$A52,GASTOS!$B:$B,$B$25,GASTOS!$C:$C,E$2) -> 1856000 | F52: =SUMIFS(GASTOS!$F:$F,GASTOS!$I:$I,'INFORME GASTOS'!$A52,GASTOS!$B:$B,$B$25,GASTOS!$C:$C,F$2) -> 678000 | G52: =SUMIFS(GASTOS!$F:$F,GASTOS!$I:$I,'INFORME GASTOS'!$A52,GASTOS!$B:$B,$B$25,GASTOS!$C:$C,G$2) -> 728000 | H52: =SUMIFS(GASTOS!$F:$F,GASTOS!$I:$I,'INFORME GASTOS'!$A52,GASTOS!$B:$B,$B$25,GASTOS!$C:$C,H$2) -> 0 | I52: =SUMIFS(GASTOS!$F:$F,GASTOS!$I:$I,'INFORME GASTOS'!$A52,GASTOS!$B:$B,$B$25,GASTOS!$C:$C,I$2) -> 0 | ... M52: =SUMIFS(GASTOS!$F:$F,GASTOS!$I:$I,'INFORME GASTOS'!$A52,GASTOS!$B:$B,$B$25,GASTOS!$C:$C,M$2) -> 680000
A53: OTROS | B53: =SUMIFS(GASTOS!$F:$F,GASTOS!$I:$I,'INFORME GASTOS'!$A53,GASTOS!$B:$B,$B$25,GASTOS!$C:$C,B$2) -> 1158000 | C53: =SUMIFS(GASTOS!$F:$F,GASTOS!$I:$I,'INFORME GASTOS'!$A53,GASTOS!$B:$B,$B$25,GASTOS!$C:$C,C$2) -> 6830000 | D53: =SUMIFS(GASTOS!$F:$F,GASTOS!$I:$I,'INFORME GASTOS'!$A53,GASTOS!$B:$B,$B$25,GASTOS!$C:$C,D$2) -> 7198000 | E53: =SUMIFS(GASTOS!$F:$F,GASTOS!$I:$I,'INFORME GASTOS'!$A53,GASTOS!$B:$B,$B$25,GASTOS!$C:$C,E$2) -> 3603000 | F53: =SUMIFS(GASTOS!$F:$F,GASTOS!$I:$I,'INFORME GASTOS'!$A53,GASTOS!$B:$B,$B$25,GASTOS!$C:$C,F$2) -> 1753000 | G53: =SUMIFS(GASTOS!$F:$F,GASTOS!$I:$I,'INFORME GASTOS'!$A53,GASTOS!$B:$B,$B$25,GASTOS!$C:$C,G$2) -> 1389000 | H53: =SUMIFS(GASTOS!$F:$F,GASTOS!$I:$I,'INFORME GASTOS'!$A53,GASTOS!$B:$B,$B$25,GASTOS!$C:$C,H$2) -> 0 | I53: =SUMIFS(GASTOS!$F:$F,GASTOS!$I:$I,'INFORME GASTOS'!$A53,GASTOS!$B:$B,$B$25,GASTOS!$C:$C,I$2) -> 0 | ... M53: =SUMIFS(GASTOS!$F:$F,GASTOS!$I:$I,'INFORME GASTOS'!$A53,GASTOS!$B:$B,$B$25,GASTOS!$C:$C,M$2) -> 6073000
A54: NIÑOS | B54: =SUMIFS(GASTOS!$F:$F,GASTOS!$I:$I,'INFORME GASTOS'!$A54,GASTOS!$B:$B,$B$25,GASTOS!$C:$C,B$2) -> 1198000 | C54: =SUMIFS(GASTOS!$F:$F,GASTOS!$I:$I,'INFORME GASTOS'!$A54,GASTOS!$B:$B,$B$25,GASTOS!$C:$C,C$2) -> 480000 | D54: =SUMIFS(GASTOS!$F:$F,GASTOS!$I:$I,'INFORME GASTOS'!$A54,GASTOS!$B:$B,$B$25,GASTOS!$C:$C,D$2) -> 0 | E54: =SUMIFS(GASTOS!$F:$F,GASTOS!$I:$I,'INFORME GASTOS'!$A54,GASTOS!$B:$B,$B$25,GASTOS!$C:$C,E$2) -> 1050000 | F54: =SUMIFS(GASTOS!$F:$F,GASTOS!$I:$I,'INFORME GASTOS'!$A54,GASTOS!$B:$B,$B$25,GASTOS!$C:$C,F$2) -> 697000 | G54: =SUMIFS(GASTOS!$F:$F,GASTOS!$I:$I,'INFORME GASTOS'!$A54,GASTOS!$B:$B,$B$25,GASTOS!$C:$C,G$2) -> 1070000 | H54: =SUMIFS(GASTOS!$F:$F,GASTOS!$I:$I,'INFORME GASTOS'!$A54,GASTOS!$B:$B,$B$25,GASTOS!$C:$C,H$2) -> 0 | I54: =SUMIFS(GASTOS!$F:$F,GASTOS!$I:$I,'INFORME GASTOS'!$A54,GASTOS!$B:$B,$B$25,GASTOS!$C:$C,I$2) -> 0 | ... M54: =SUMIFS(GASTOS!$F:$F,GASTOS!$I:$I,'INFORME GASTOS'!$A54,GASTOS!$B:$B,$B$25,GASTOS!$C:$C,M$2) -> 2114000
A55: salidas | B55: =SUMIFS(GASTOS!$F:$F,GASTOS!$I:$I,'INFORME GASTOS'!$A55,GASTOS!$B:$B,$B$25,GASTOS!$C:$C,B$2) -> 457000 | C55: =SUMIFS(GASTOS!$F:$F,GASTOS!$I:$I,'INFORME GASTOS'!$A55,GASTOS!$B:$B,$B$25,GASTOS!$C:$C,C$2) -> 205000 | D55: =SUMIFS(GASTOS!$F:$F,GASTOS!$I:$I,'INFORME GASTOS'!$A55,GASTOS!$B:$B,$B$25,GASTOS!$C:$C,D$2) -> 109000 | E55: =SUMIFS(GASTOS!$F:$F,GASTOS!$I:$I,'INFORME GASTOS'!$A55,GASTOS!$B:$B,$B$25,GASTOS!$C:$C,E$2) -> 550000 | F55: =SUMIFS(GASTOS!$F:$F,GASTOS!$I:$I,'INFORME GASTOS'!$A55,GASTOS!$B:$B,$B$25,GASTOS!$C:$C,F$2) -> 679000 | G55: =SUMIFS(GASTOS!$F:$F,GASTOS!$I:$I,'INFORME GASTOS'!$A55,GASTOS!$B:$B,$B$25,GASTOS!$C:$C,G$2) -> 340000 | H55: =SUMIFS(GASTOS!$F:$F,GASTOS!$I:$I,'INFORME GASTOS'!$A55,GASTOS!$B:$B,$B$25,GASTOS!$C:$C,H$2) -> 0 | I55: =SUMIFS(GASTOS!$F:$F,GASTOS!$I:$I,'INFORME GASTOS'!$A55,GASTOS!$B:$B,$B$25,GASTOS!$C:$C,I$2) -> 0 | ... M55: =SUMIFS(GASTOS!$F:$F,GASTOS!$I:$I,'INFORME GASTOS'!$A55,GASTOS!$B:$B,$B$25,GASTOS!$C:$C,M$2) -> 1684000
A56: parqueadero | B56: =SUMIFS(GASTOS!$F:$F,GASTOS!$I:$I,'INFORME GASTOS'!$A56,GASTOS!$B:$B,$B$25,GASTOS!$C:$C,B$2) -> 24000 | C56: =SUMIFS(GASTOS!$F:$F,GASTOS!$I:$I,'INFORME GASTOS'!$A56,GASTOS!$B:$B,$B$25,GASTOS!$C:$C,C$2) -> 173000 | D56: =SUMIFS(GASTOS!$F:$F,GASTOS!$I:$I,'INFORME GASTOS'!$A56,GASTOS!$B:$B,$B$25,GASTOS!$C:$C,D$2) -> 0 | E56: =SUMIFS(GASTOS!$F:$F,GASTOS!$I:$I,'INFORME GASTOS'!$A56,GASTOS!$B:$B,$B$25,GASTOS!$C:$C,E$2) -> 0 | F56: =SUMIFS(GASTOS!$F:$F,GASTOS!$I:$I,'INFORME GASTOS'!$A56,GASTOS!$B:$B,$B$25,GASTOS!$C:$C,F$2) -> 0 | G56: =SUMIFS(GASTOS!$F:$F,GASTOS!$I:$I,'INFORME GASTOS'!$A56,GASTOS!$B:$B,$B$25,GASTOS!$C:$C,G$2) -> 0 | H56: =SUMIFS(GASTOS!$F:$F,GASTOS!$I:$I,'INFORME GASTOS'!$A56,GASTOS!$B:$B,$B$25,GASTOS!$C:$C,H$2) -> 0 | I56: =SUMIFS(GASTOS!$F:$F,GASTOS!$I:$I,'INFORME GASTOS'!$A56,GASTOS!$B:$B,$B$25,GASTOS!$C:$C,I$2) -> 0 | ... M56: =SUMIFS(GASTOS!$F:$F,GASTOS!$I:$I,'INFORME GASTOS'!$A56,GASTOS!$B:$B,$B$25,GASTOS!$C:$C,M$2) -> 96000
A57: empresa | B57: =SUMIFS(GASTOS!$F:$F,GASTOS!$I:$I,'INFORME GASTOS'!$A57,GASTOS!$B:$B,$B$25,GASTOS!$C:$C,B$2) -> 1833000 | C57: =SUMIFS(GASTOS!$F:$F,GASTOS!$I:$I,'INFORME GASTOS'!$A57,GASTOS!$B:$B,$B$25,GASTOS!$C:$C,C$2) -> 1044000 | D57: =SUMIFS(GASTOS!$F:$F,GASTOS!$I:$I,'INFORME GASTOS'!$A57,GASTOS!$B:$B,$B$25,GASTOS!$C:$C,D$2) -> 0 | E57: =SUMIFS(GASTOS!$F:$F,GASTOS!$I:$I,'INFORME GASTOS'!$A57,GASTOS!$B:$B,$B$25,GASTOS!$C:$C,E$2) -> 800000 | F57: =SUMIFS(GASTOS!$F:$F,GASTOS!$I:$I,'INFORME GASTOS'!$A57,GASTOS!$B:$B,$B$25,GASTOS!$C:$C,F$2) -> 2390000 | G57: =SUMIFS(GASTOS!$F:$F,GASTOS!$I:$I,'INFORME GASTOS'!$A57,GASTOS!$B:$B,$B$25,GASTOS!$C:$C,G$2) -> 353000 | H57: =SUMIFS(GASTOS!$F:$F,GASTOS!$I:$I,'INFORME GASTOS'!$A57,GASTOS!$B:$B,$B$25,GASTOS!$C:$C,H$2) -> 0 | I57: =SUMIFS(GASTOS!$F:$F,GASTOS!$I:$I,'INFORME GASTOS'!$A57,GASTOS!$B:$B,$B$25,GASTOS!$C:$C,I$2) -> 0 | ... M57: =SUMIFS(GASTOS!$F:$F,GASTOS!$I:$I,'INFORME GASTOS'!$A57,GASTOS!$B:$B,$B$25,GASTOS!$C:$C,M$2) -> 5915000
A58: gasolina | B58: =SUMIFS(GASTOS!$F:$F,GASTOS!$I:$I,'INFORME GASTOS'!$A58,GASTOS!$B:$B,$B$25,GASTOS!$C:$C,B$2) -> 420000 | C58: =SUMIFS(GASTOS!$F:$F,GASTOS!$I:$I,'INFORME GASTOS'!$A58,GASTOS!$B:$B,$B$25,GASTOS!$C:$C,C$2) -> 206000 | D58: =SUMIFS(GASTOS!$F:$F,GASTOS!$I:$I,'INFORME GASTOS'!$A58,GASTOS!$B:$B,$B$25,GASTOS!$C:$C,D$2) -> 426000 | E58: =SUMIFS(GASTOS!$F:$F,GASTOS!$I:$I,'INFORME GASTOS'!$A58,GASTOS!$B:$B,$B$25,GASTOS!$C:$C,E$2) -> 200000 | F58: =SUMIFS(GASTOS!$F:$F,GASTOS!$I:$I,'INFORME GASTOS'!$A58,GASTOS!$B:$B,$B$25,GASTOS!$C:$C,F$2) -> 435000 | G58: =SUMIFS(GASTOS!$F:$F,GASTOS!$I:$I,'INFORME GASTOS'!$A58,GASTOS!$B:$B,$B$25,GASTOS!$C:$C,G$2) -> 230000 | H58: =SUMIFS(GASTOS!$F:$F,GASTOS!$I:$I,'INFORME GASTOS'!$A58,GASTOS!$B:$B,$B$25,GASTOS!$C:$C,H$2) -> 0 | I58: =SUMIFS(GASTOS!$F:$F,GASTOS!$I:$I,'INFORME GASTOS'!$A58,GASTOS!$B:$B,$B$25,GASTOS!$C:$C,I$2) -> 0 | ... M58: =SUMIFS(GASTOS!$F:$F,GASTOS!$I:$I,'INFORME GASTOS'!$A58,GASTOS!$B:$B,$B$25,GASTOS!$C:$C,M$2) -> 470000
A59: isabella | B59: =SUMIFS(GASTOS!$F:$F,GASTOS!$I:$I,'INFORME GASTOS'!$A59,GASTOS!$B:$B,$B$25,GASTOS!$C:$C,B$2) -> 420000 | C59: =SUMIFS(GASTOS!$F:$F,GASTOS!$I:$I,'INFORME GASTOS'!$A59,GASTOS!$B:$B,$B$25,GASTOS!$C:$C,C$2) -> 0 | D59: =SUMIFS(GASTOS!$F:$F,GASTOS!$I:$I,'INFORME GASTOS'!$A59,GASTOS!$B:$B,$B$25,GASTOS!$C:$C,D$2) -> 0 | E59: =SUMIFS(GASTOS!$F:$F,GASTOS!$I:$I,'INFORME GASTOS'!$A59,GASTOS!$B:$B,$B$25,GASTOS!$C:$C,E$2) -> 100000 | F59: =SUMIFS(GASTOS!$F:$F,GASTOS!$I:$I,'INFORME GASTOS'!$A59,GASTOS!$B:$B,$B$25,GASTOS!$C:$C,F$2) -> 0 | G59: =SUMIFS(GASTOS!$F:$F,GASTOS!$I:$I,'INFORME GASTOS'!$A59,GASTOS!$B:$B,$B$25,GASTOS!$C:$C,G$2) -> 0 | H59: =SUMIFS(GASTOS!$F:$F,GASTOS!$I:$I,'INFORME GASTOS'!$A59,GASTOS!$B:$B,$B$25,GASTOS!$C:$C,H$2) -> 0 | I59: =SUMIFS(GASTOS!$F:$F,GASTOS!$I:$I,'INFORME GASTOS'!$A59,GASTOS!$B:$B,$B$25,GASTOS!$C:$C,I$2) -> 0 | ... M59: =SUMIFS(GASTOS!$F:$F,GASTOS!$I:$I,'INFORME GASTOS'!$A59,GASTOS!$B:$B,$B$25,GASTOS!$C:$C,M$2) -> 0
A60: IGLESIA | B60: =SUMIFS(GASTOS!$F:$F,GASTOS!$I:$I,'INFORME GASTOS'!$A60,GASTOS!$B:$B,$B$25,GASTOS!$C:$C,B$2) -> 0 | C60: =SUMIFS(GASTOS!$F:$F,GASTOS!$I:$I,'INFORME GASTOS'!$A60,GASTOS!$B:$B,$B$25,GASTOS!$C:$C,C$2) -> 500000 | D60: =SUMIFS(GASTOS!$F:$F,GASTOS!$I:$I,'INFORME GASTOS'!$A60,GASTOS!$B:$B,$B$25,GASTOS!$C:$C,D$2) -> 0 | E60: =SUMIFS(GASTOS!$F:$F,GASTOS!$I:$I,'INFORME GASTOS'!$A60,GASTOS!$B:$B,$B$25,GASTOS!$C:$C,E$2) -> 0 | F60: =SUMIFS(GASTOS!$F:$F,GASTOS!$I:$I,'INFORME GASTOS'!$A60,GASTOS!$B:$B,$B$25,GASTOS!$C:$C,F$2) -> 0 | G60: =SUMIFS(GASTOS!$F:$F,GASTOS!$I:$I,'INFORME GASTOS'!$A60,GASTOS!$B:$B,$B$25,GASTOS!$C:$C,G$2) -> 0 | H60: =SUMIFS(GASTOS!$F:$F,GASTOS!$I:$I,'INFORME GASTOS'!$A60,GASTOS!$B:$B,$B$25,GASTOS!$C:$C,H$2) -> 0 | I60: =SUMIFS(GASTOS!$F:$F,GASTOS!$I:$I,'INFORME GASTOS'!$A60,GASTOS!$B:$B,$B$25,GASTOS!$C:$C,I$2) -> 0 | ... M60: =SUMIFS(GASTOS!$F:$F,GASTOS!$I:$I,'INFORME GASTOS'!$A60,GASTOS!$B:$B,$B$25,GASTOS!$C:$C,M$2) -> 100000
A61: cadena | B61: =SUMIFS(GASTOS!$F:$F,GASTOS!$I:$I,'INFORME GASTOS'!$A61,GASTOS!$B:$B,$B$25,GASTOS!$C:$C,B$2) -> 0 | C61: =SUMIFS(GASTOS!$F:$F,GASTOS!$I:$I,'INFORME GASTOS'!$A61,GASTOS!$B:$B,$B$25,GASTOS!$C:$C,C$2) -> 0 | D61: =SUMIFS(GASTOS!$F:$F,GASTOS!$I:$I,'INFORME GASTOS'!$A61,GASTOS!$B:$B,$B$25,GASTOS!$C:$C,D$2) -> 0 | E61: =SUMIFS(GASTOS!$F:$F,GASTOS!$I:$I,'INFORME GASTOS'!$A61,GASTOS!$B:$B,$B$25,GASTOS!$C:$C,E$2) -> 0 | F61: =SUMIFS(GASTOS!$F:$F,GASTOS!$I:$I,'INFORME GASTOS'!$A61,GASTOS!$B:$B,$B$25,GASTOS!$C:$C,F$2) -> 0 | G61: =SUMIFS(GASTOS!$F:$F,GASTOS!$I:$I,'INFORME GASTOS'!$A61,GASTOS!$B:$B,$B$25,GASTOS!$C:$C,G$2) -> 0 | H61: =SUMIFS(GASTOS!$F:$F,GASTOS!$I:$I,'INFORME GASTOS'!$A61,GASTOS!$B:$B,$B$25,GASTOS!$C:$C,H$2) -> 0 | I61: =SUMIFS(GASTOS!$F:$F,GASTOS!$I:$I,'INFORME GASTOS'!$A61,GASTOS!$B:$B,$B$25,GASTOS!$C:$C,I$2) -> 0 | ... M61: =SUMIFS(GASTOS!$F:$F,GASTOS!$I:$I,'INFORME GASTOS'!$A61,GASTOS!$B:$B,$B$25,GASTOS!$C:$C,M$2) -> 0
A62: ASEO | B62: =SUMIFS(GASTOS!$F:$F,GASTOS!$I:$I,'INFORME GASTOS'!$A62,GASTOS!$B:$B,$B$25,GASTOS!$C:$C,B$2) -> 0 | C62: =SUMIFS(GASTOS!$F:$F,GASTOS!$I:$I,'INFORME GASTOS'!$A62,GASTOS!$B:$B,$B$25,GASTOS!$C:$C,C$2) -> 0 | D62: =SUMIFS(GASTOS!$F:$F,GASTOS!$I:$I,'INFORME GASTOS'!$A62,GASTOS!$B:$B,$B$25,GASTOS!$C:$C,D$2) -> 0 | E62: =SUMIFS(GASTOS!$F:$F,GASTOS!$I:$I,'INFORME GASTOS'!$A62,GASTOS!$B:$B,$B$25,GASTOS!$C:$C,E$2) -> 0 | F62: =SUMIFS(GASTOS!$F:$F,GASTOS!$I:$I,'INFORME GASTOS'!$A62,GASTOS!$B:$B,$B$25,GASTOS!$C:$C,F$2) -> 0 | G62: =SUMIFS(GASTOS!$F:$F,GASTOS!$I:$I,'INFORME GASTOS'!$A62,GASTOS!$B:$B,$B$25,GASTOS!$C:$C,G$2) -> 0 | H62: =SUMIFS(GASTOS!$F:$F,GASTOS!$I:$I,'INFORME GASTOS'!$A62,GASTOS!$B:$B,$B$25,GASTOS!$C:$C,H$2) -> 0 | I62: =SUMIFS(GASTOS!$F:$F,GASTOS!$I:$I,'INFORME GASTOS'!$A62,GASTOS!$B:$B,$B$25,GASTOS!$C:$C,I$2) -> 0 | ... M62: =SUMIFS(GASTOS!$F:$F,GASTOS!$I:$I,'INFORME GASTOS'!$A62,GASTOS!$B:$B,$B$25,GASTOS!$C:$C,M$2) -> 0
... A67: IMPUESTOS | B67: =SUMIFS(GASTOS!$F:$F,GASTOS!$I:$I,'INFORME GASTOS'!$A67,GASTOS!$B:$B,$B$25,GASTOS!$C:$C,B$2) -> 0 | C67: =SUMIFS(GASTOS!$F:$F,GASTOS!$I:$I,'INFORME GASTOS'!$A67,GASTOS!$B:$B,$B$25,GASTOS!$C:$C,C$2) -> 0 | D67: =SUMIFS(GASTOS!$F:$F,GASTOS!$I:$I,'INFORME GASTOS'!$A67,GASTOS!$B:$B,$B$25,GASTOS!$C:$C,D$2) -> 0 | E67: =SUMIFS(GASTOS!$F:$F,GASTOS!$I:$I,'INFORME GASTOS'!$A67,GASTOS!$B:$B,$B$25,GASTOS!$C:$C,E$2) -> 0 | F67: =SUMIFS(GASTOS!$F:$F,GASTOS!$I:$I,'INFORME GASTOS'!$A67,GASTOS!$B:$B,$B$25,GASTOS!$C:$C,F$2) -> 2660000 | G67: =SUMIFS(GASTOS!$F:$F,GASTOS!$I:$I,'INFORME GASTOS'!$A67,GASTOS!$B:$B,$B$25,GASTOS!$C:$C,G$2) -> 0 | H67: =SUMIFS(GASTOS!$F:$F,GASTOS!$I:$I,'INFORME GASTOS'!$A67,GASTOS!$B:$B,$B$25,GASTOS!$C:$C,H$2) -> 0 | I67: =SUMIFS(GASTOS!$F:$F,GASTOS!$I:$I,'INFORME GASTOS'!$A67,GASTOS!$B:$B,$B$25,GASTOS!$C:$C,I$2) -> 0 | ... M67: =SUMIFS(GASTOS!$F:$F,GASTOS!$I:$I,'INFORME GASTOS'!$A67,GASTOS!$B:$B,$B$25,GASTOS!$C:$C,M$2) -> 0
B68: =SUM(B52:B67) -> 7455000 | C68: =SUM(C52:C67) -> 10643000 | D68: =SUM(D52:D67) -> 8836000 | E68: =SUM(E52:E67) -> 9597000 | F68: =SUM(F52:F67) -> 9794000 | G68: =SUM(G52:G67) -> 5564300 | H68: =SUM(H52:H67) -> 0 | I68: =SUM(I52:I67) -> 0 | ... M68: =SUM(M52:M67) -> 18329000

Sheet PRESTAMOS
A1: ACTUALIZACION FEBRERO 2024
A2: No. | B2: año | C2: mes | D2: FECHA | E2: DESCRIPCION | F2: PRESTAMOS | G2: % | H2: FEBERO | I2: INTERESES | J2: MARZO | K2: INTERESES | L2: ABRIL | M2: INTERESES | N2: MAYO | O2: INTERESES | P2: JUNIO | Q2: INTERESES | R2: JULIO | S2: INTERESES | T2: AGOSTO | U2: INTERESES | V2: SEPTIEMBRE | W2: INTERESES | X2: dic | Y2: INTERESES | Z2: ENE | AA2: INTERESES | AB2: FEB | AC2: INTERESES | AD2: MARZO | AE2: INTERESES | AF2: ABRIL | AG2: INTERESES | AH2: MAYO | AI2: INTERESES | AJ2: JUNIO | AK2: INTERESES | AL2: JULIO | AM2: INTERESES | AN2: AGOSTO | AO2: INTERESES
A3: 1 | B3: =YEAR(D3) -> 2020 | C3: =MONTH(D3) -> 2 | D3: 43862 | E3: ESTEFANIA BARREIRO | F3: 3060000 | G3: 0.035 | H3: 3060000 | I3: =H3*G3 -> 107100 | J3: 3060000 | K3: 0 | L3: 5000000 | M3: =L3*G3 -> 175000 | N3: 3657500 | O3: =N3*G3 -> 128012.5 | P3: 2785512.5 | Q3: =P3*G3 -> 97492.938 | R3: 2785512.5 | S3: =R3*G3 -> 97492.938 | T3: 2785512.5 | U3: =T3*G3 -> 97492.938 | V3: 0 | W3: =V3*G3 -> 0 | X3: 0 | Y3: 0 | Z3: 0 | AA3: =Z3*$G3 -> 0 | AB3: 0 | AC3: =AB3*$G3 -> 0 | AD3: 0 | AE3: =AD3*$G3 -> 0 | AF3: 0 | AG3: =AF3*$G3 -> 0 | AH3: 0 | AI3: =AH3*$G3 -> 0 | AJ3: 0 | AK3: =AJ3*$G3 -> 0 | AL3: 0 | AM3: =AL3*$G3 -> 0 | AN3: 0 | AO3: =AN3*$G3 -> 0
A4: 3 | B4: =YEAR(D4) -> 2020 | C4: =MONTH(D4) -> 9 | D4: 44075 | E4: DOÑA LUCY | F4: 6200000 | G4: 0.035 | H4: 1681220.2 | I4: =H4*G4 -> 58842.708 | J4: 1497465.1 | K4: =J4*G4 -> 52411.28 | L4: 1349876.4 | M4: =L4*G4 -> 47245.675 | N4: 1397122.1 | O4: =N4*G4 -> 48899.273 | P4: 1763521.4 | Q4: =P4*G4 -> 61723.248 | R4: 1763521.4 | S4: =R4*G4 -> 61723.248 | T4: 1763521.4 | U4: =T4*G4 -> 61723.248 | V4: 3223142.8 | W4: =V4*G4 -> 112810 | X4: 3152000 | Y4: =X4*G4 -> 110320 | Z4: 3152000 | AA4: =Z4*$G4 -> 110320 | AB4: 3152000 | AC4: =AB4*$G4 -> 110320 | AD4: 5172775.6 | AE4: =AD4*$G4 -> 181047.15 | AF4: 5172775.6 | AG4: =AF4*$G4 -> 181047.15 | AH4: 5172775.6 | AI4: =AH4*$G4 -> 181047.15 | AJ4: 5172775.6 | AK4: =AJ4*$G4 -> 181047.15 | AL4: 5172775.6 | AM4: =AL4*$G4 -> 181047.15 | AN4: 5172775.6 | AO4: =AN4*$G4 -> 181047.15
A5: 4 | B5: =YEAR(D5) -> 2021 | C5: =MONTH(D5) -> 2 | D5: 44228 | E5: HECTOR MEDINA | F5: 21000000 | G5: 0.035 | H5: 14984550 | I5: =H5*G5 -> 524459.26 | J5: 15509009 | K5: =J5*G5 -> 542815.33 | L5: 16051825 | M5: =L5*G5 -> 561813.87 | N5: 16613639 | O5: 0 | P5: 16613639 | Q5: 0 | R5: 16613639 | S5: 0 | T5: 16613639 | U5: 0 | V5: 16613639 | W5: 0 | X5: 16613639 | Y5: 0 | Z5: 16613639 | AA5: 0 | AB5: 16613639 | AC5: 0 | AD5: 16613639 | AE5: 0 | AF5: 16613639 | AG5: 0 | AH5: 16613639 | AI5: 0 | AJ5: 16613639 | AK5: 0 | AL5: 16613639 | AM5: 0 | AN5: 16613639 | AO5: 0
A6: 5 | B6: =YEAR(D6) -> 2021 | C6: =MONTH(D6) -> 12 | D6: 44531 | E6: LUIS MIRA | F6: 4000000 | G6: 0.035 | H6: 3291685.5 | I6: =H6*G6 -> 115208.99 | J6: 3406894.5 | K6: =J6*G6 -> 119241.31 | L6: 3526135.8 | M6: =L6*G6 -> 123414.75 | N6: 3649550.5 | O6: 0 | P6: 3649550.5 | Q6: 0 | R6: 3649550.5 | S6: 0 | T6: 3649550.5 | U6: 0 | V6: 3649550.5 | W6: 0 | X6: 3649550.5 | Y6: 0 | Z6: 3649550.5 | AA6: 0 | AB6: 3649550.5 | AC6: 0 | AD6: 3649550.5 | AE6: 0 | AF6: 3649550.5 | AG6: 0 | AH6: 3649550.5 | AI6: 0 | AJ6: 3649550.5 | AK6: 0 | AL6: 3649550.5 | AM6: 0 | AN6: 1000000 | AO6: 0
A7: 6 | B7: =YEAR(D7) -> 2023 | C7: =MONTH(D7) -> 1 | D7: 44927 | E7: FABIONELSON | F7: 1500000 | G7: 0.035 | H7: 910029.56 | I7: =H7*G7 -> 31851.035 | J7: 941880.6 | K7: =J7*G7 -> 32965.821 | L7: 974846.42 | M7: =L7*G7 -> 34119.625 | N7: 1008965 | O7: =N7*G7 -> 35313.776 | P7: 1044279.9 | Q7: =P7*G7 -> 36549.795 | R7: 1044279.9 | S7: =R7*G7 -> 36549.795 | T7: 1044279.9 | U7: =T7*G7 -> 36549.795 | V7: 1044279.9 | W7: 0 | X7: 1044279.9 | Y7: 0 | Z7: 1044279.9 | AA7: 0 | AB7: 1044279.9 | AC7: 0 | AD7: 1044279.9 | AE7: 0 | AF7: 1044279.9 | AG7: 0 | AH7: 1044279.9 | AI7: 0 | AJ7: 1044279.9 | AK7: 0 | AL7: 1044279.9 | AM7: 0 | AN7: 1044279.9 | AO7: 0
A8: 7 | B8: =YEAR(D8) -> 2023 | C8: =MONTH(D8) -> 1 | D8: 44944 | E8: JUAN PABLO ROSERO | F8: 14700000 | G8: 0.035 | H8: 14700502 | I8: =H8*G8 -> 514517.57 | J8: 14415019 | K8: =J8*G8 -> 504525.68 | L8: 14919545 | M8: =L8*G8 -> 522184.08 | N8: 14224229 | O8: =N8*G8 -> 497848.02 | P8: 14022077 | Q8: =P8*G8 -> 490772.7 | R8: 14022077 | S8: =R8*G8 -> 490772.7 | T8: 14022077 | U8: =T8*G8 -> 490772.7 | V8: 13890054 | W8: =V8*G8 -> 486151.88 | X8: 13890054 | Y8: 0 | Z8: 13890054 | AA8: 0 | AB8: 13890054 | AC8: 0 | AD8: 13890054 | AE8: 0 | AF8: 13890054 | AG8: 0 | AH8: 13890054 | AI8: 0 | AJ8: 13890054 | AK8: 0 | AL8: 13890054 | AM8: 0 | AN8: 13890054 | AO8: 0
A9: 8 | B9: =YEAR(D9) -> 2023 | C9: =MONTH(D9) -> 2 | D9: 44958 | E9: AMPARO CARRO - CARLOS | F9: 40000000 | G9: 0 | H9: 21000000 | I9: =H9*G9 -> 0 | J9: 19000000 | K9: =J9*G9 -> 0 | L9: 17000000 | M9: =L9*G9 -> 0 | N9: 15000000 | O9: =N9*G9 -> 0 | P9: 14000000 | Q9: =P9*G9 -> 0 | R9: 14000000 | S9: =R9*G9 -> 0 | T9: 14000000 | U9: =T9*G9 -> 0 | V9: 12000000 | W9: =V9*G9 -> 0 | X9: 12000000 | Y9: =X9*I9 -> 0 | Z9: 12000000 | AA9: =Z9*K9 -> 0 | AB9: 12000000 | AC9: =AB9*M9 -> 0 | AD9: 12000000 | AE9: =AD9*O9 -> 0 | AF9: 12000000 | AG9: =AF9*Q9 -> 0 | AH9: 12000000 | AI9: =AH9*S9 -> 0 | AJ9: 12000000 | AK9: =AJ9*U9 -> 0 | AL9: 12000000 | AM9: =AL9*W9 -> 0 | AN9: 12000000 | AO9: =AN9*Y9 -> 0
A10: 9 | B10: =YEAR(D10) -> 2023 | C10: =MONTH(D10) -> 8 | D10: 45139 | E10: SANDRA LATORRE Y MARTIN | F10: 4000000 | G10: 0.05 | H10: 4264126.2 | I10: =H10*G10 -> 213206.31 | J10: 4477332.6 | K10: =J10*G10 -> 223866.63 | L10: 4401199.2 | M10: =L10*G10 -> 220059.96 | N10: 4621259.2 | O10: =N10*G10 -> 231062.96 | P10: 4852322.1 | Q10: =P10*G10 -> 242616.11 | R10: 4852322.1 | S10: =R10*G10 -> 242616.11 | T10: 4852322.1 | U10: =T10*G10 -> 242616.11 | V10: 5898027.8 | W10: =V10*G10 -> 294901.39 | X10: 6827704.5 | Y10: 0 | Z10: 6827704.5 | AA10: 0 | AB10: 6827704.5 | AC10: 0 | AD10: 6827704.5 | AE10: 0 | AF10: 6827704.5 | AG10: 0 | AH10: 6827704.5 | AI10: 0 | AJ10: 6827704.5 | AK10: 0 | AL10: 6827704.5 | AM10: 0 | AN10: 6827704.5 | AO10: 0
A11: 10 | B11: =YEAR(D11) -> 2023 | C11: =MONTH(D11) -> 12 | D11: 45261 | E11: TOÑO | F11: 5236000 | G11: 0.035 | H11: 5319152.5 | I11: =H11*G11 -> 186170.34 | J11: 5318322.8 | K11: =J11*G11 -> 186141.3 | L11: 5317464.1 | M11: =L11*G11 -> 186111.24 | N11: 5313575.4 | O11: =N11*G11 -> 185975.14 | P11: 5309550.5 | Q11: =P11*G11 -> 185834.27 | R11: 5309550.5 | S11: =R11*G11 -> 185834.27 | T11: 5309550.5 | U11: =T11*G11 -> 185834.27 | V11: 5291992.2 | W11: =V11*G11 -> 185219.73 | X11: 6775588.8 | Y11: =X11*G11 -> 237145.61 | Z11: 6775588.8 | AA11: =Z11*$G11 -> 237145.61 | AB11: 6775588.8 | AC11: =AB11*$G11 -> 237145.61 | AD11: 7020180.1 | AE11: =AD11*$G11 -> 245706.3 | AF11: 7020180.1 | AG11: =AF11*$G11 -> 245706.3 | AH11: 7020180.1 | AI11: =AH11*$G11 -> 245706.3 | AJ11: 7020180.1 | AK11: =AJ11*$G11 -> 245706.3 | AL11: 7020180.1 | AM11: =AL11*$G11 -> 245706.3 | AN11: 7020180.1 | AO11: =AN11*$G11 -> 245706.3
A12: 11 | B12: =YEAR(D12) -> 2023 | C12: =MONTH(D12) -> 12 | D12: 45261 | E12: EDUARDO MOLINA Y DIANA MOLINA | F12: 9000000 | G12: 0.015 | H12: 9000000 | I12: =H12*G12 -> 135000 | J12: 9000000 | K12: =J12*G12 -> 135000 | L12: 9000000 | M12: =L12*G12 -> 135000 | N12: 9000000 | O12: =N12*G12 -> 135000 | P12: 9000000 | Q12: =P12*G12 -> 135000 | R12: 9000000 | S12: =R12*G12 -> 135000 | T12: 9000000 | U12: =T12*G12 -> 135000 | V12: 9000000 | W12: =V12*G12 -> 135000 | X12: 9000000 | Y12: =X12*G12 -> 135000 | Z12: 9000000 | AA12: =Z12*$G12 -> 135000 | AB12: 9000000 | AC12: =AB12*$G12 -> 135000 | AD12: 9000000 | AE12: =AD12*$G12 -> 135000 | AF12: 9000000 | AG12: =AF12*$G12 -> 135000 | AH12: 9000000 | AI12: =AH12*$G12 -> 135000 | AJ12: 9000000 | AK12: =AJ12*$G12 -> 135000 | AL12: 9000000 | AM12: =AL12*$G12 -> 135000 | AN12: 4000000 | AO12: =AN12*$G12 -> 60000
A13: 13 | B13: =YEAR(D13) -> 2024 | C13: =MONTH(D13) -> 2 | D13: 45329 | E13: JESSICA RAMIREZ | F13: 7000000 | G13: 0.035 | H13: 7000000 | I13: =H13*G13 -> 245000 | J13: 7245000 | K13: =J13*G13 -> 253575 | L13: 6768575 | M13: =L13*G13 -> 236900.13 | N13: 5765116.8 | O13: =N13*G13 -> 201779.09 | P13: 5236895.8 | Q13: =P13*G13 -> 183291.35 | R13: 5236895.8 | S13: =R13*G13 -> 183291.35 | T13: 5236895.8 | U13: =T13*G13 -> 183291.35 | V13: 3538695.8 | W13: =V13*G13 -> 123854.35 | X13: 2411421 | Y13: =X13*G13 -> 84399.735 | Z13: 2411421 | AA13: =Z13*$G13 -> 84399.735 | AB13: 1765820.7 | AC13: =AB13*$G13 -> 61803.726 | AD13: 1097624.5 | AE13: =AD13*$G13 -> 38416.857 | AF13: 1097624.5 | AG13: =AF13*$G13 -> 38416.857 | AH13: 1097624.5 | AI13: =AH13*$G13 -> 38416.857 | AJ13: 0 | AK13: =AJ13*$G13 -> 0 | AL13: 0 | AM13: =AL13*$G13 -> 0 | AN13: 0 | AO13: =AN13*$G13 -> 0
A14: 14 | B14: =YEAR(D14) -> 2024 | C14: =MONTH(D14) -> 2 | D14: 45323 | E14: FABIO ARROYAVE | F14: 35000000 | G14: 0.02 | H14: 25000000 | I14: =H14*G14 -> 500000 | J14: 35000000 | K14: =J14*G14 -> 700000 | L14: 0 | M14: =L14*G14 -> 0 | N14: =M14*H14 -> 0 | O14: =N14*G14 -> 0 | P14: =O14*H14 -> 0 | Q14: =P14*G14 -> 0 | R14: =Q14*J14 -> 0 | S14: =R14*G14 -> 0 | T14: =S14*L14 -> 0 | U14: =T14*G14 -> 0 | V14: =U14*N14 -> 0 | W14: =V14*G14 -> 0 | X14: =W14*H14 -> 0 | Y14: =X14*I14 -> 0 | Z14: =Y14*J14 -> 0 | AA14: =Z14*$G14 -> 0 | AB14: =AA14*L14 -> 0 | AC14: =AB14*$G14 -> 0 | AD14: =AC14*N14 -> 0 | AE14: =AD14*$G14 -> 0 | AF14: =AE14*P14 -> 0 | AG14: =AF14*$G14 -> 0 | AH14: =AG14*R14 -> 0 | AI14: =AH14*$G14 -> 0 | AJ14: =AI14*T14 -> 0 | AK14: =AJ14*$G14 -> 0 | AL14: =AK14*V14 -> 0 | AM14: =AL14*$G14 -> 0 | AN14: =AM14*X14 -> 0 | AO14: =AN14*$G14 -> 0
A15: 17 | B15: =YEAR(D15) -> 2024 | C15: =MONTH(D15) -> 2 | D15: 45323 | E15: VALENTINA LOPEZ | F15: 210000 | G15: 0.035 | H15: 210000 | I15: =H15*G15 -> 7350 | J15: 210000 | K15: =J15*G15 -> 7350 | L15: 210000 | M15: =L15*G15 -> 7350 | N15: 210000 | O15: =N15*G15 -> 7350 | P15: 210000 | Q15: =P15*G15 -> 7350 | R15: 210000 | S15: =R15*G15 -> 7350 | T15: 210000 | U15: =T15*G15 -> 7350 | V15: 210000 | W15: =V15*G15 -> 7350 | X15: 210000 | Y15: =X15*G15 -> 7350 | Z15: 0 | AA15: =Z15*$G15 -> 0 | AB15: 0 | AC15: =AB15*$G15 -> 0 | AD15: 0 | AE15: =AD15*$G15 -> 0 | AF15: 0 | AG15: =AF15*$G15 -> 0 | AH15: 0 | AI15: =AH15*$G15 -> 0 | AJ15: 0 | AK15: =AJ15*$G15 -> 0 | AL15: 0 | AM15: =AL15*$G15 -> 0 | AN15: 0 | AO15: =AN15*$G15 -> 0
A16: 18 | B16: =YEAR(D16) -> 2024 | C16: =MONTH(D16) -> 3 | D16: 45354 | E16: JHON ROSERO | F16: 2600000 | G16: 0.05 | H16: 2600000 | I16: =H16*G16 -> 130000 | J16: 2600000 | K16: =J16*G16 -> 130000 | L16: 2600000 | M16: =L16*G16 -> 130000 | N16: 5000000 | O16: =N16*G16 -> 250000 | P16: 6890000 | Q16: =P16*G16 -> 344500 | R16: 6890000 | S16: =R16*G16 -> 344500 | T16: 6890000 | U16: =T16*G16 -> 344500 | V16: 9803098.5 | W16: =V16*G16 -> 490154.92 | X16: 12552399 | Y16: =X16*G16 -> 627619.97 | Z16: 12552399 | AA16: 0 | AB16: 12552399 | AC16: 0 | AD16: 12552399 | AE16: 0 | AF16: 12552399 | AG16: 0 | AH16: 12552399 | AI16: 0 | AJ16: 12552399 | AK16: 0 | AL16: 12552399 | AM16: 0 | AN16: 12552399 | AO16: 0
A17: 19 | B17: =YEAR(D17) -> 2024 | C17: =MONTH(D17) -> 3 | D17: 45357 | E17: LEIDY LOPEZ | F17: =2900000+500000 -> 3400000 | G17: 0.05 | H17: 3400000 | I17: 0 | J17: 3400000 | K17: =J17*G17 -> 170000 | L17: 3547500 | M17: =L17*G17 -> 177375 | N17: 3584875 | O17: =N17*G17 -> 179243.75 | P17: 3152118.8 | Q17: =P17*G17 -> 157605.94 | R17: 3152118.8 | S17: =R17*G17 -> 157605.94 | T17: 3152118.8 | U17: =T17*G17 -> 157605.94 | V17: 1456169.8 | W17: =V17*G17 -> 72808.489 | X17: 566729.25 | Y17: =X17*G17 -> 28336.462 | Z17: 566729.25 | AA17: =Z17*$G17 -> 28336.462 | AB17: 0 | AC17: =AB17*$G17 -> 0 | AD17: 0 | AE17: =AD17*$G17 -> 0 | AF17: 0 | AG17: =AF17*$G17 -> 0 | AH17: 0 | AI17: =AH17*$G17 -> 0 | AJ17: 0 | AK17: =AJ17*$G17 -> 0 | AL17: 0 | AM17: =AL17*$G17 -> 0 | AN17: 0 | AO17: =AN17*$G17 -> 0
A18: 20 | B18: =YEAR(D18) -> 2024 | C18: =MONTH(D18) -> 3 | D18: 45359 | E18: JHON JAIRO MUÑOZ | F18: 5000000 | G18: 0.02 | H18: 0 | I18: 0 | J18: 5000000 | K18: =J18*G18 -> 100000 | L18: 0 | M18: =L18*G18 -> 0 | N18: 0 | O18: =N18*G18 -> 0 | P18: 0 | Q18: =P18*G18 -> 0 | R18: 0 | S18: =R18*G18 -> 0 | T18: 0 | U18: =T18*G18 -> 0 | V18: 0 | W18: 0 | X18: 0 | Y18: 0 | Z18: 0 | AA18: =Z18*$G18 -> 0 | AB18: 0 | AC18: =AB18*$G18 -> 0 | AD18: 0 | AE18: =AD18*$G18 -> 0 | AF18: 0 | AG18: =AF18*$G18 -> 0 | AH18: 0 | AI18: =AH18*$G18 -> 0 | AJ18: 0 | AK18: =AJ18*$G18 -> 0 | AL18: 0 | AM18: =AL18*$G18 -> 0 | AN18: 0 | AO18: =AN18*$G18 -> 0
A19: 21 | B19: =YEAR(D19) -> 2024 | C19: =MONTH(D19) -> 4 | D19: 45384 | E19: ARROYAVE | F19: 2000000 | G19: 0 | L19: 2000000 | M19: =L19*G19 -> 0 | N19: 0 | O19: =N19*G19 -> 0 | P19: 0 | Q19: =P19*G19 -> 0 | R19: 0 | S19: =R19*G19 -> 0 | T19: 0 | U19: =T19*G19 -> 0 | V19: 0 | W19: =V19*G19 -> 0 | X19: 0 | Y19: 0 | Z19: 0 | AA19: =Z19*$G19 -> 0 | AB19: 0 | AC19: =AB19*$G19 -> 0 | AD19: 0 | AE19: =AD19*$G19 -> 0 | AF19: 0 | AG19: =AF19*$G19 -> 0 | AH19: 0 | AI19: =AH19*$G19 -> 0 | AJ19: 0 | AK19: =AJ19*$G19 -> 0 | AL19: 0 | AM19: =AL19*$G19 -> 0 | AN19: 0 | AO19: =AN19*$G19 -> 0
A20: 22 | B20: =YEAR(D20) -> 2024 | C20: =MONTH(D20) -> 5 | D20: 45433 | E20: ERMERSON ESPOSO MARITZA | F20: 350000 | P20: 350000 | Q20: =P20*G20 -> 0 | R20: 350000 | S20: =R20*G20 -> 0 | T20: 350000 | U20: =T20*G20 -> 0 | V20: 350000 | W20: =V20*G20 -> 0 | X20: 350000 | Y20: =X20*G20 -> 0 | Z20: 350000 | AA20: =Z20*$G20 -> 0 | AB20: 350000 | AC20: =AB20*$G20 -> 0 | AD20: 350000 | AE20: =AD20*$G20 -> 0 | AF20: 350000 | AG20: =AF20*$G20 -> 0 | AH20: 350000 | AI20: =AH20*$G20 -> 0 | AJ20: 350000 | AK20: =AJ20*$G20 -> 0 | AL20: 350000 | AM20: =AL20*$G20 -> 0 | AN20: 350000 | AO20: =AN20*$G20 -> 0
A21: 24 | B21: =YEAR(D21) -> 2024 | C21: =MONTH(D21) -> 5 | D21: 45427 | E21: TIA LORENA - DIANA | F21: 1500000 | G21: 0.035 | P21: 1552500 | Q21: =P21*G21 -> 54337.5 | R21: 1552500 | S21: =R21*G21 -> 54337.5 | T21: 1552500 | U21: =T21*G21 -> 54337.5 | V21: 552000 | W21: =V21*G21 -> 19320 | X21: 552000 | Y21: =X21*G21 -> 19320 | Z21: 552000 | AA21: =Z21*$G21 -> 19320 | AB21: 0 | AC21: =AB21*$G21 -> 0 | AD21: 0 | AE21: =AD21*$G21 -> 0 | AF21: 0 | AG21: =AF21*$G21 -> 0 | AH21: 0 | AI21: =AH21*$G21 -> 0 | AJ21: 0 | AK21: =AJ21*$G21 -> 0 | AL21: 0 | AM21: =AL21*$G21 -> 0 | AN21: 0 | AO21: =AN21*$G21 -> 0
A22: 26 | B22: =YEAR(D22) -> 2024 | C22: =MONTH(D22) -> 6 | D22: 45458 | E22: JHON JAIRO MUÑOZ | F22: 2000000 | G22: 0.025 | P22: 2000000 | Q22: =P22*G22 -> 50000 | R22: 2000000 | S22: =R22*G22 -> 50000 | T22: 2000000 | U22: =T22*G22 -> 50000 | V22: 2129453.5 | W22: =V22*G22 -> 53236.338 | X22: 2293188.5 | Y22: =X22*G22 -> 57329.713 | Z22: 2293188.5 | AA22: =Z22*$G22 -> 57329.713 | AB22: 2293188.5 | AC22: =AB22*$G22 -> 57329.713 | AD22: 2409281.2 | AE22: =AD22*$G22 -> 60232.03 | AF22: 2409281.2 | AG22: =AF22*$G22 -> 60232.03 | AH22: 2409281.2 | AI22: =AH22*$G22 -> 60232.03 | AJ22: 2409281.2 | AK22: =AJ22*$G22 -> 60232.03 | AL22: 2409281.2 | AM22: =AL22*$G22 -> 60232.03 | AN22: 2409281.2 | AO22: =AN22*$G22 -> 60232.03
A23: 28 | B23: =YEAR(D23) -> 2024 | C23: =MONTH(D23) -> 9 | D23: 45558 | E23: JUAN DAVID RODRIGUEZ | F23: 500000 | V23: 500000 | W23: =V23*G23 -> 0 | X23: =W23*H23 -> 0 | Y23: =X23*I23 -> 0 | Z23: =Y23*J23 -> 0 | AA23: =Z23*$G23 -> 0 | AB23: =AA23*L23 -> 0 | AC23: =AB23*$G23 -> 0 | AD23: =AC23*N23 -> 0 | AE23: =AD23*$G23 -> 0 | AF23: =AE23*P23 -> 0 | AG23: =AF23*$G23 -> 0 | AH23: =AG23*R23 -> 0 | AI23: =AH23*$G23 -> 0 | AJ23: =AI23*T23 -> 0 | AK23: =AJ23*$G23 -> 0 | AL23: =AK23*V23 -> 0 | AM23: =AL23*$G23 -> 0 | AN23: =AM23*X23 -> 0 | AO23: =AN23*$G23 -> 0
A24: 30 | B24: =YEAR(D24) -> 2024 | C24: =MONTH(D24) -> 9 | D24: 45551 | E24: FABIO ARROYAVE | F24: 50000000 | G24: 0.0185 | H24: 0.0185 | I24: 0.0185 | V24: 30677220 | W24: =V24*G24 -> 567528.57 | X24: 50308378 | Y24: =X24*G24 -> 930704.99 | Z24: 50308378 | AA24: =Z24*$G24 -> 930704.99 | AB24: 50308378 | AC24: =AB24*$G24 -> 930704.99 | AD24: 51262006 | AE24: =AD24*$G24 -> 948347.11 | AF24: 51262006 | AG24: =AF24*$G24 -> 948347.11 | AH24: 51262006 | AI24: =AH24*$G24 -> 948347.11 | AJ24: 51262006 | AK24: =AJ24*$G24 -> 948347.11 | AL24: 51262006 | AM24: =AL24*$G24 -> 948347.11 | AN24: 51262006 | AO24: =AN24*$G24 -> 948347.11
A25: 32 | B25: =YEAR(D25) -> 2025 | C25: =MONTH(D25) -> 1 | D25: 45672 | E25: FF ARROYAVE | F25: 30000000 | G25: 0.0185 | Z25: 20000000 | AA25: =Z25*$G25 -> 370000 | AB25: 20000000 | AC25: =AB25*$G25 -> 370000 | AD25: 20565268 | AE25: =AD25*$G25 -> 380457.45 | AF25: 20565268 | AG25: =AF25*$G25 -> 380457.45 | AH25: 20565268 | AI25: =AH25*$G25 -> 380457.45 | AJ25: 20565268 | AK25: =AJ25*$G25 -> 380457.45 | AL25: 20565268 | AM25: =AL25*$G25 -> 380457.45 | AN25: 20565268 | AO25: =AN25*$G25 -> 380457.45
A26: 34 | B26: =YEAR(D26) -> 2024 | C26: =MONTH(D26) -> 10 | D26: 45581 | E26: ANTONIO CARDENAS | F26: 3000000 | G26: 0.05 | W26: =V26*G26 -> 0 | X26: 3315375 | Y26: =X26*G26 -> 165768.75 | Z26: 3315375 | AA26: =Z26*$G26 -> 165768.75 | AB26: 3315375 | AC26: =AB26*$G26 -> 165768.75 | AD26: 3655200.9 | AE26: =AD26*$G26 -> 182760.05 | AF26: 3655200.9 | AG26: =AF26*$G26 -> 182760.05 | AH26: 3655200.9 | AI26: =AH26*$G26 -> 182760.05 | AJ26: 3655200.9 | AK26: =AJ26*$G26 -> 182760.05 | AL26: 3655200.9 | AM26: =AL26*$G26 -> 182760.05 | AN26: 3655200.9 | AO26: =AN26*$G26 -> 182760.05
A27: 36 | B27: =YEAR(D27) -> 2024 | C27: =MONTH(D27) -> 10 | D27: 45591 | E27: COMPRA DE CARRO JUANPA | F27: 8100000 | X27: 8100000 | Z27: 8100000 | AA27: =Z27*$G27 -> 0 | AB27: 8100000 | AC27: =AB27*$G27 -> 0 | AD27: 8100000 | AE27: =AD27*$G27 -> 0 | AF27: 8100000 | AG27: =AF27*$G27 -> 0 | AH27: 8100000 | AI27: =AH27*$G27 -> 0 | AJ27: 8100000 | AK27: =AJ27*$G27 -> 0 | AL27: 8100000 | AM27: =AL27*$G27 -> 0 | AN27: 8100000 | AO27: =AN27*$G27 -> 0
A28: 38 | B28: =YEAR(D28) -> 2024 | C28: =MONTH(D28) -> 12 | D28: 45640 | E28: EINER PELUQUERIA | F28: 4000000 | G28: 0.045 | X28: 4000000 | Y28: =X28*G28 -> 180000 | Z28: 4000000 | AA28: =Z28*$G28 -> 180000 | AB28: 4000000 | AC28: =AB28*$G28 -> 180000 | AD28: 3920500 | AE28: =AD28*$G28 -> 176422.5 | AF28: 3920500 | AG28: =AF28*$G28 -> 176422.5 | AH28: 3920500 | AI28: =AH28*$G28 -> 176422.5 | AJ28: 3920500 | AK28: =AJ28*$G28 -> 176422.5 | AL28: 3920500 | AM28: =AL28*$G28 -> 176422.5 | AN28: 24000000 | AO28: =AN28*$G28 -> 1080000
A29: 40 | B29: =YEAR(D29) -> 2024 | C29: =MONTH(D29) -> 11 | D29: 45623 | E29: DIANA MANZANO | F29: 2000000 | G29: 0.05 | X29: 2000000 | Y29: =X29*G29 -> 100000 | Z29: 2000000 | AA29: =Z29*$G29 -> 100000 | AB29: 2000000 | AC29: =AB29*$G29 -> 100000 | AD29: 2000000 | AE29: =AD29*$G29 -> 100000 | AF29: 2000000 | AG29: =AF29*$G29 -> 100000 | AH29: 2000000 | AI29: =AH29*$G29 -> 100000 | AJ29: 2000000 | AK29: =AJ29*$G29 -> 100000 | AL29: 2000000 | AM29: =AL29*$G29 -> 100000 | AN29: 2000000 | AO29: =AN29*$G29 -> 100000
A30: 42 | B30: =YEAR(D30) -> 2024 | C30: =MONTH(D30) -> 12 | D30: 45637 | E30: CESAR MANZANO | F30: =1400000-800000 -> 600000 | X30: 600000 | Y30: =X30*G30 -> 0 | Z30: 600000 | AA30: =Z30*$G30 -> 0 | AB30: 600000 | AC30: =AB30*$G30 -> 0 | AD30: 600000 | AE30: =AD30*$G30 -> 0 | AF30: 600000 | AG30: =AF30*$G30 -> 0 | AH30: 600000 | AI30: =AH30*$G30 -> 0 | AJ30: 600000 | AK30: =AJ30*$G30 -> 0 | AL30: 600000 | AM30: =AL30*$G30 -> 0 | AN30: 600000 | AO30: =AN30*$G30 -> 0
A31: 44 | B31: =YEAR(D31) -> 2025 | C31: =MONTH(D31) -> 2 | D31: 45703 | E31: VIVIANA AGUDELO | F31: 1500000 | G31: 0.0185 | AD31: 1500000 | AE31: =AD31*$G31 -> 27750 | AF31: 1500000 | AG31: =AF31*$G31 -> 27750 | AH31: 1500000 | AI31: =AH31*$G31 -> 27750 | AJ31: 1500000 | AK31: =AJ31*$G31 -> 27750 | AL31: 1500000 | AM31: =AL31*$G31 -> 27750 | AN31: 1500000 | AO31: =AN31*$G31 -> 27750
A32: 46 | B32: =YEAR(D32) -> 2025 | C32: =MONTH(D32) -> 3 | D32: 45717 | E32: ANGELA ORTIZ | F32: 1100000 | G32: 0 | AD32: 1100000 | AE32: =AD32*$G32 -> 0 | AF32: 1100000 | AG32: =AF32*$G32 -> 0 | AH32: 1100000 | AI32: =AH32*$G32 -> 0 | AJ32: 1100000 | AK32: =AJ32*$G32 -> 0 | AL32: 1100000 | AM32: =AL32*$G32 -> 0 | AN32: 1100000 | AO32: =AN32*$G32 -> 0
A33: 48 | B33: =YEAR(D33) -> 1900 | C33: =MONTH(D33) -> 1 | E33: OFICINA ARROYAVE | F33: 54000000 | G33: 0.0185 | AJ33: 54000000 | AK33: =AJ33*$G33 -> 999000 | AL33: 54000000 | AM33: =AL33*$G33 -> 999000 | AN33: 54000000 | AO33: =AN33*$G33 -> 999000
A34: 50 | B34: =YEAR(D34) -> 2025 | C34: =MONTH(D34) -> 7 | D34: 45848 | E34: LUIS VALENCIA - PRESTAMO | F34: 10000000 | G34: 0.03 | AL34: 10000000 | AM34: =AL34*$G34 -> 300000 | AN34: 10000000 | AO34: =AN34*$G34 -> 300000
A35: 52 | B35: =YEAR(D35) -> 2025 | C35: =MONTH(D35) -> 7 | D35: 45848 | E35: LUIS VALENCIA CAMIONETA | F35: 20000000 | G35: 0.03 | AL35: 20000000 | AM35: =AL35*$G35 -> 600000 | AN35: 20000000 | AO35: =AN35*$G35 -> 600000
A36: 54 | B36: =YEAR(D36) -> 2026 | C36: =MONTH(D36) -> 6 | D36: 46185 | E36: MARITZA QUIÑONES | F36: 5000000 | G36: 0.03
A37: 56 | B37: =YEAR(D37) -> 2026 | C37: =MONTH(D37) -> 5 | D37: 46149 | E37: JEIMY OCAMPO | F37: 1000000 | G37: 0
A38: 58 | B38: =YEAR(D38) -> 2026 | C38: =MONTH(D38) -> 4 | D38: 46113 | E38: OSCAR TORO (PAPA SARA) | F38: 4000000 | G38: 0.035
A39: 60 | B39: =YEAR(D39) -> 2026 | C39: =MONTH(D39) -> 1 | D39: 46037 | E39: LUIS FERNANDO DELGADO | F39: 2000000 | G39: 0.03
A40: 62 | B40: =YEAR(D40) -> 1900 | C40: =MONTH(D40) -> 1
A41: 64 | B41: =YEAR(D41) -> 1900 | C41: =MONTH(D41) -> 1 | W41: =V41*G41 -> 0
F42: =SUM(F3:F41) -> 364556000 | H42: =SUM(H3:H41) -> 1.1642127e+08 | I42: =SUM(I3:I41) -> 2768706.2 | J42: =SUM(J3:J41) -> 1.3008092e+08 | K42: =SUM(K3:K41) -> 3157892.3 | L42: =SUM(L3:L41) -> 92666967 | M42: =SUM(M3:M41) -> 2556574.3 | N42: =SUM(N3:N41) -> 89045832 | O42: =SUM(O3:O41) -> 1900484.5 | ... AO42: =SUM(AO3:AO41) -> 5165300.1

Sheet cuenta
B1: MES | C1: SALDO | D1: ADMIN BBVA | F1: 4XMIL BBVA
P2: 2000000 | Q2: de caja
B3: JUNIO | C3: 566100 | D3: -60000 | F3: 0 | P3: 2000000 | Q3: de caja | R3: 43507
B4: JULIO | C4: 1663600 | D4: -60000 | F4: 0
B5: AGOSTO | C5: -243200 | D5: -60000 | F5: -3202.8
B6: SEPTIEMBRE | C6: 1457000 | D6: -60000 | F6: -28482.4
B7: OCTUBRE | C7: 916700 | D7: -60000 | F7: -34442 | Q7: 43867 | R7: 510400 | S7: se le pago planillas el niche
B8: NOVIEMBRE | C8: 2574700 | D8: -60000 | F8: -34396.4 | Q8: 43867 | R8: 2084000 | S8: SALDO INCAPACIDAD NICHE
B9: DICIEMBRE | C9: 1148860 | D9: -60000 | F9: -48377.92 | Q9: 43784 | R9: 449600 | S9: se le pago planillas el niche
B10: ENERO | C10: 1316700 | D10: -62000 | F10: -41412.4 | Q10: 43817 | R10: 449600 | S10: se le pago planillas el niche
B11: FEBRERO | C11: 1166700 | D11: -62000 | F11: -45946.8 | Q11: 43839 | R11: 358800 | S11: incapacidad lego - jose carlos
B12: MARZO | C12: 1824950 | D12: -62000 | F12: -53939.2 | Q12: 43839 | R12: 138000 | S12: incapacidad lego - jose carlos
B13: ABRIL | C13: 2148203.3 | D13: -62000 | F13: -64140.067 | Q13: 43840 | R13: 383000 | S13: se le pago planillas el niche
B14: MAYO | C14: 1441093.3 | D14: -62000 | F14: -54698.867 | Q14: 43853 | R14: 500000 | S14: prestamo a Edgar Garcia
B15: JUNIO | C15: 2524350 | D15: -62000 | F15: -67276.4 | H15: DESCRIPCION | I15: VALOR | J15: FECHA | Q15: 43853 | R15: 53000 | S15: prestamo a viviana gil
B16: JULIO | C16: 2200613.3 | D16: -62000 | F16: -57859.36 | H16: APARTO | I16: 250000000 | J16: 44868 | Y16: 1000000
B17: AGOSTO | C17: 8250289 | D17: -62000 | F17: -77143.98 | H17: ESCRITURAS | I17: 5700000 | J17: 44868 | Y17: 5400000
B18: SEPTIEMBRE | C18: 7749331.1 | D18: -62000 | F18: -59757.596 | H18: CAMION 2 | I18: 40000000 | J18: 44105 | V18: 1215000 | Y18: =42*20000 -> 840000
B19: OCTUBRE | C19: 4492654.5 | D19: -62000 | F19: -71255.955 | H19: CAMION 3 | I19: 26500000 | J19: 44950 | V19: 1197000 | Y19: 270000
B20: NOVIEMBRE | C20: 3663290 | D20: -62000 | F20: -57639.04 | H20: Iphone 14 Pro | I20: 5900000 | J20: 44972 | V20: =V18-V19 -> 18000 | Y20: 55000
B21: DICIEMBRE | C21: 3767543.3 | D21: -62000 | F21: -62812 | H21: compra portatil dell | I21: 2300000 | J21: 45140 | Y21: =24*2000 -> 48000
A22: =BRAYAN!C2 -> 1113000 | B22: ENERO | C22: 2888350 | D22: -62000 | F22: -54825.2 | H22: compra camioneta | I22: 129000000 | J22: 45168 | Y22: 2000
A23: =BRAYAN!D2 -> 1588000 | B23: FEBRERO | C23: 3014900 | D23: -62000 | F23: -56958.8 | H23: Iphone 16 Pro | I23: 4600000 | J23: 45610
A24: =BRAYAN!E2 -> 1732000 | B24: MARZO | C24: 3297656.7 | D24: -62000 | F24: -56958.8 | H24: PORTATIL DELL | I24: 0 | J24: 45651
A25: =BRAYAN!F2 -> 1422000 | B25: ABRIL | C25: 1374956.7 | D25: -62000 | F25: -56958.8 | H25: Portatil Macbook Pro | I25: 6800000 | J25: 45736
A26: =BRAYAN!G2 -> 1000000 | B26: MAYO | C26: 1921000 | D26: 0 | F26: -56958.8 | H26: tv 65 | I26: 2800000 | J26: 45928
A27: =BRAYAN!H2 -> 1000000 | B27: JUNIO | C27: 1790800 | D27: 0 | F27: -56958.8
A28: =BRAYAN!I2 -> 1500000 | B28: JULIO | C28: 2573550 | D28: 0 | F28: -56958.8
A29: =BRAYAN!J2 -> 1800000 | B29: AGOSTO | C29: 3379243.3 | D29: 0 | F29: -56958.8 | I29: =-(SUM(I16:I28)) -> -473600000
A30: =BRAYAN!K2 -> 3100000 | B30: SEPTIEMBRE | C30: 2922223.3 | D30: 0 | F30: -56958.8
A31: =BRAYAN!L2 -> 2708500 | B31: OCTUBRE | C31: 2500000 | D31: 0 | F31: -56958.8 | L31: 43646
A32: =BRAYAN!M2 -> 2800000 | B32: NOVIEMBRE | C32: 3480000 | D32: 0 | F32: -56958.8 | H32: CUENTAS | L32: DEDUCCIONES
A33: 2553300 | B33: DICIEMBRE | C33: 2553300 | D33: 0 | F33: -56958.8 | H33: BBVA NET | I33: 0 | J33: 45548 | L33: 43713 | M33: 1048000 | N33: se le pago a Lego por incapacidad Anderson
A34: 3033000 | B34: ENERO | C34: 3480000 | D34: 0 | F34: -56958.8 | H34: BBVA | I34: 0 | J34: 45548 | L34: 43978 | M34: 1103990 | N34: NEVECON
A35: 3500000 | B35: FEBRERO | C35: 3600000 | D35: -69000 | F35: -56958.8 | H35: BBVA AHORRAR | I35: 10000000 | J35: 45548 | L35: 44180 | M35: 271000 | N35: planilla alejandra gonzalez
A36: 2500000 | B36: MARZO | C36: 2600000 | D36: -69000 | F36: -56958.8 | H36: BANCOLOMBIA B | I36: 1279000 | J36: 45548
A37: 3740000 | B37: ABRIL | C37: 4000000 | D37: -69000 | F37: -56958.8 | H37: NEQUI | I37: 865000 | J37: 45548
A38: 2500000 | B38: MAYO | C38: 2500000 | D38: -69000 | F38: -56958.8 | H38: DAVIPLATA | I38: 86000 | J38: 45548 | L38: 44140 | M38: 380000 | N38: cruce incapacidad lego - juan david trejos x cobrar
A39: 3050000 | B39: JUNIO | C39: 3050000 | D39: -69000 | F39: -22000 | H39: LULO BANK | I39: 83000 | L39: 44230 | M39: 120000 | N39: PERDIDA PLANILLAS
A40: 4890000 | B40: JULIO | C40: 4890000 | D40: -69000 | F40: -22000 | H40: LULO BOLSILLO | I40: 1012000 | L40: 44051 | M40: 200000 | N40: PAGO CLINICA CLARA
A41: 4200000 | B41: AGOSTO | C41: 4200000 | D41: -69000 | F41: -22000 | H41: NU - AHORRO | I41: 11500 | J41: 45548 | L41: 44058 | M41: 88500 | N41: pago eps clara
A42: 3800000 | B42: SEPTIEMBRE | C42: 3800000 | D42: -69000 | F42: -22000 | H42: CAJITA NU | I42: 4245500 | J42: 45548 | L42: 44089 | M42: 88500 | N42: pago eps clara
A43: 4000000 | B43: OCTUBRE | C43: 4000000 | D43: -69000 | F43: -22000 | H43: mega AMPARO | I43: 5000000 | J43: 45548 | L43: 44440 | M43: 1000000 | N43: regalo a madre viaje a españa
A44: 3750000 | B44: NOVIEMBRE | C44: 3750000 | D44: -69000 | F44: -22000 | H44: ALM | I44: 400000000 | J44: 45812 | L44: 44495 | M44: 2100000 | N44: Compra portatil Dell
A45: 4500000 | B45: DICIEMBRE | C45: 4500000 | D45: -69000 | F45: -22000 | H45: CENTER CIT | I45: 0 | L45: 44504 | M45: =145500*4 -> 582000 | N45: pago de pension lego 4 meses
A46: 6000000 | B46: ENERO | C46: 6000000 | D46: -69000 | F46: -22000 | H46: CONSTRUTECH | I46: 0 | L46: 44718 | M46: 1000000 | N46: k
A47: 4700000 | B47: FEBRERO | C47: 4700000 | D47: -69000 | F47: -22000 | H47: LOGISTIC HOUSE | I47: 0 | L47: 44805 | M47: 1000000 | N47: benitez
A48: 5000000 | B48: MARZO | C48: 5000000 | D48: -69000 | F48: -22000 | H48: arroyave | I48: 0 | L48: 44783 | M48: 250000 | N48: arreglo del carro - bobina
A49: 5000000 | B49: ABRIL | C49: 4500000 | D49: -69000 | F49: -22000 | H49: EFECTIVO | I49: 0 | J49: 45569 | L49: 44785 | M49: 1430000 | N49: compra de llantas
A50: 4000000 | B50: MAYO | C50: 4000000 | D50: -69000 | F50: -22000 | H50: DANIELA BRYGAR | I50: 0 | J50: 45334 | L50: 44792 | M50: 1074000 | N50: ultimo pago efecty
A51: 5500000 | B51: JUNIO | C51: 5400000 | D51: -69000 | F51: -22000 | H51: DIANA | I51: 0 | J51: 45435 | L51: 44593 | M51: 1000000 | N51: pago efecty
A52: 3800000 | B52: JULIO | C52: 3785000 | D52: -69000 | F52: -22000 | I52: =SUM(I33:I51) -> 422582000 | L52: 44640 | M52: 1000000 | N52: pago efecty
A53: 4750000 | B53: AGOSTO | C53: 4750000 | D53: -69000 | F53: -22000 | L53: 44713 | M53: 1000000 | N53: abono efecty
A54: 5000000 | B54: SEPTIEMBRE | C54: 4700000 | D54: -69000 | F54: -22000 | H54: ENTRADAS | I54: =BRAYAN!CD60 -> #REF! | L54: 45073 | M54: 13500000 | N54: robo de plataforma de recargas
A55: 4500000 | B55: OCTUBRE | C55: 4500000 | D55: -69000 | F55: -22000 | H55: SEGURIDAD SOCIAL | I55: =C110 -> 3.8225077e+08 | L55: 45045 | M55: 2530000 | N55: operación de los ojos
A56: 7000000 | B56: NOVIEMBRE | C56: 7695000 | D56: -69000 | F56: -22000 | H56: BRYGAR_ACTUAL | I56: 1500000 | L56: 45279 | M56: 502000 | N56: Luis Enrique salas (ADRIANA SALAS)
A57: 10000000 | B57: DICIEMBRE | C57: 12000000 | D57: -69000 | F57: -22000 | H57: PROYECTOS | I57: =PROYECTOS!D98 -> 53488000 | J57: 45568 | L57: 45279 | M57: 502000 | N57: JHON FABIO MORALES SERNA
A58: 6000000 | B58: ENERO | C58: 5800000 | D58: -69000 | F58: -22000 | H58: PRESTAMOS | I58: -279000000 | L58: 45383 | M58: 2500000 | N58: IMPUESTOS KUY 188
A59: 6800000 | B59: FEBRERO | C59: 6800000 | D59: -69000 | F59: -22000 | H59: PATRIMONIO | I59: =I29 -> -473600000 | L59: 45383 | M59: 3446750 | N59: PREDIAL APTO 2024
A60: 7000000 | B60: MARZO | C60: 7800000 | D60: -69000 | F60: -22000 | I60: =SUM(I54:I59) -> #REF! | L60: 45379 | M60: 800000 | N60: 800 cámara comercio
A61: 7000000 | B61: ABRIL | C61: 8000000 | D61: -69000 | F61: -22000 | L61: 45421 | M61: 300000 | N61: 300 contadora IVA cit
A62: 7000000 | B62: MAYO | C62: 5500000 | D62: -69000 | F62: -22000 | L62: 45427 | M62: 471000 | N62: 471 MULTA homenurse
A63: 7000000 | B63: JUNIO | C63: 7000000 | D63: -69000 | F63: -22000 | I63: =I52-I60 -> #REF! | L63: 45428 | M63: 471000 | N63: 471 impuestos
A64: 7000000 | B64: JULIO | C64: 7000000 | D64: -69000 | F64: -22000 | L64: 45428 | M64: 471000 | N64: 471 impuestos
A65: 7000000 | B65: AGOSTO | C65: 7000000 | D65: -69000 | F65: -22000 | L65: 45428 | M65: 471000 | N65: 471 impuestos
A66: 7000000 | B66: SEPTIEMBRE | C66: 7000000 | D66: -69000 | F66: -22000 | L66: 45435 | M66: 471000 | N66: 471 renta 2022 house
A67: 10000000 | B67: OCTUBRE | C67: 7000000 | D67: -69000 | F67: -22000 | L67: 45435 | M67: 471000 | N67: 471 renta 2023 center
A68: 8000000 | B68: NOVIEMBRE | C68: 8000000 | D68: -69000 | F68: -22000 | L68: 45435 | M68: 4871000 | N68: 4871 IVA construtech
A69: 10000000 | B69: DICIEMBRE | C69: 10000000 | D69: -69000 | F69: -22000 | L69: 45435 | M69: 500000 | N69: tutela mave -
A70: 5000000 | B70: ENERO | C70: 4000000 | D70: -69000 | F70: -22000 | L70: 45436 | M70: 1000000 | N70: 1000 Jeimy declaraciones
A71: 7000000 | B71: FEBRERO | C71: 7000000 | D71: -69000 | F71: -22000 | L71: 45470 | M71: 2350000 | N71: lina - contador
A72: 6000000 | B72: MARZO | C72: 6000000 | D72: -69000 | F72: -22000 | L72: 45537 | M72: 2000000 | N72: COMPRA DE SERVIDOR
A73: 6000000 | B73: ABRIL | C73: 6000000 | D73: -69000 | F73: -22000 | L73: 45537 | M73: 600000 | N73: DISCOS SOLIDOS SERVIDOR
A74: 5500000 | B74: MAYO | C74: 5000000 | D74: -69000 | F74: -22000 | L74: 45540 | M74: 3000000 | N74: IPHONE DIANA
A75: 4700000 | B75: JUNIO | C75: 4500000 | D75: -69000 | F75: -22000 | L75: 45561 | M75: 2500000 | N75: fuente de poder y tarjeta grafica servidor
A76: 8000000 | B76: JULIO | C76: 7500000 | D76: -69000 | F76: -22000 | L76: 45930 | M76: 2915000 | N76: 2915 liquidación Daniela
A77: 6200000 | B77: AGOSTO | C77: 6000000 | D77: -69000 | F77: -22000
A78: 6000000 | B78: SEPTIEMBRE | C78: 6000000 | D78: -69000 | F78: -22000
A79: 7000000 | B79: OCTUBRE | C79: 6500000 | D79: -69000 | F79: -22000
A80: 5000000 | B80: NOVIEMBRE | C80: 4700000 | D80: -69000 | F80: -22000
A81: 7000000 | B81: DICIEMBRE | C81: 6000000 | D81: -69000 | F81: -22000
A82: 5000000 | B82: ENERO | C82: 5000000 | D82: -69000 | F82: -22000
A83: 7000000 | B83: FEBRERO | C83: 7000000 | D83: -69000 | F83: -22000
A84: 6000000 | B84: MARZO | C84: 5000000 | D84: -69000 | F84: -22000
A85: 5700000 | B85: ABRIL | C85: 5000000 | D85: -69000 | F85: -22000
A86: 6500000 | B86: MAYO | C86: 6500000 | D86: -69000 | F86: -22000
A87: 5000000 | B87: JUNIO | C87: 5000000 | D87: -69000 | F87: -22000
A88: 7500000 | B88: JULIO | C88: 7500000 | D88: -69000 | F88: -22000
... A98: 7000000 | B98: MAYO | C98: 6000000 | D98: -69000 | F98: -22000
B99: JUNIO
B100: JULIO
B103: 43830 | C103: 2500000 | D103: Prima dic | L103: 44454 | M103: 0 | N103: JORGE EDWIN TELLEZ TAVERA (219,200) 16777157 FACTURA No. 2204
C104: 5000000 | D104: Carro | L104: 44484 | M104: 0 | N104: JORGE EDWIN TELLEZ TAVERA (219,200) 16777157 FACTURA No. 2298
B105: NOVIEMBRE | C105: 2905000 | D105: PAGO 1 NOV | L105: 44515 | M105: 0 | N105: JORGE EDWIN TELLEZ TAVERA (219,200) 16777157 FACTURA No. 2441
L106: 44558 | M106: 0 | N106: JORGE EDWIN TELLEZ TAVERA (219,200) 16777157 FACTURA No.
L107: 44477 | M107: 0 | N107: pago incapacidad de jose ever
C108: =SUM(C3:C106) -> 4.5473046e+08 | D108: =SUM(D3:D106) -> -5828000 | E108: =SUM(E3:E106) -> 0 | F108: =SUM(F3:F106) -> -3148949.2 | L108: 44666 | M108: 0 | N108: INCAPACIDAD DE SINDY - JOHANA NUÑEZ $545
L109: 44737 | M109: 0 | N109: incapacidad HAMILTON MARTINEZ 156
C110: =C108+D108+F108+E108-M129 -> 3.8225077e+08 | L110: 44750 | M110: 0 | N110: incapacidad edwin tellez 844,000
L111: 44757 | M111: 0 | N111: Incapacidad nestor giraldo 430
...

Sheet mensual
C1: DESCRIPCION | D1: CANT | E1: VALOR | F1: POR PAGAR | G1: PAGO NOV | H1: PRIMA | I1: PAGO DIC
C2: ACUERDO BRAYAN | D2: 1 | E2: 1000000 | F2: =D2*E2 -> 1000000 | G2: 1000000
C3: CONTRATO LLAMADAS Y DIGITACION | D3: 1 | E3: 1500000 | F3: =D3*E3 -> 1500000 | G3: 1500000
C4: INTERESES PRESTAMO AMPARO | D4: 1 | E4: 558000 | F4: =D4*E4 -> 558000 | G4: 558000
C5: TARJETA CREDITO BRAYAN | D5: 1 | E5: 500000 | F5: 371500 | H5: 371500 | R5: 277400
C6: IPHONE CARMEN ELENA | D6: 1 | E6: 250000 | F6: =D6*E6 -> 250000 | H6: 250000 | R6: 32100
C7: LLAMADAS y SMS VINCULADOS 1 | D7: 210 | E7: 500 | F7: =D7*E7 -> 105000 | G7: 105000 | R7: 62000
C8: LLAMADAS y SMS VINCULADOS 2 | D8: 400 | E8: 500 | F8: =D8*E8 -> 200000 | G8: 200000
C9: LLAMADAS y SMS VINCULADOS 3 | D9: 226 | E9: 500 | F9: =D9*E9 -> 113000 | G9: 113000
C10: AFILIACION MERK XPRESS - USMA | D10: 1 | E10: 95000 | F10: =D10*E10 -> 95000 | G10: 95000
C11: AFILIACION FABIO ALONSO | D11: 1 | E11: 150000 | F11: =D11*E11 -> 150000 | G11: 150000
C12: EPS DICIEMBRE RUTH SARAZA | D12: 1 | E12: 69500 | F12: =D12*E12 -> 69500 | G12: 69500
C13: EPS DICIEMBRE ALEX ZUÑIGA | D13: 1 | E13: 240000 | F13: =D13*E13 -> 240000 | G13: 240000
C14: EPS DICIEMBRE ROSA YATACUE | D14: 1 | E14: 97500 | F14: =D14*E14 -> 97500 | G14: 97500
C15: EPS DICIEMBRE MERK SPRESS | D15: 1 | E15: 95000 | F15: =D15*E15 -> 95000 | G15: 95000
C16: LLAMADA LIDERES - ENCUESTA | D16: 2250 | E16: 500 | H16: =D16*E16 -> 1125000 | O16: 71594013
C17: cable HDMI Y 1 CABLE DE AUDIO | D17: 2 | E17: 10000 | F17: =D17*E17 -> 20000 | H17: 20000
C18: prima | D18: 1 | H18: 500000
C19: EPS Y ARL FABIO ARROYAVE | D19: 1 | E19: 310000 | F19: 310000 | H19: 310000
C20: AFILIACION HIJO BENEFICIARIO | D20: 1 | E20: 30000 | F20: =D20*E20 -> 30000 | H20: 30000
C22: AFILIACION MERK XPRESS - HOLGUIN | D22: 1 | E22: 95000 | F22: =D22*E22 -> 95000
C23: Admin programa whatsapp DIC | D23: 1 | E23: 250000 | F23: =D23*E23 -> 250000
C24: envio 1700 whatsapp lideres | D24: 1700 | E24: 50 | F24: =D24*E24 -> 85000
C25: envio 500 whatsapp | D25: 500 | E25: 50 | F25: =D25*E25 -> 25000
C26: envio 1450 whatsapp | D26: 1450 | E26: 50 | F26: =D26*E26 -> 72500
C27: DIGITACION 2800 REGISTROS | D27: 2800 | E27: 150 | F27: =D27*E27 -> 420000
C28: LLAMADAS CUMPLE DICIEMBRE | D28: 1 | E28: 1500000 | F28: 1200000
C29: ACUERDO BRAYAN | D29: 1 | E29: 1000000 | F29: =D29*E29 -> 1000000
C30: INTERESES PRESTAMO AMPARO | D30: 1 | E30: 558000 | F30: =D30*E30 -> 558000
C31: TARJETA CREDITO BRAYAN | D31: 1 | E31: 350000 | F31: =D31*E31 -> 350000
C32: IPHONE CARMEN ELENA | D32: 1 | E32: 250000 | F32: =D32*E32 -> 250000
C33: EPS DICIEMBRE RUTH SARAZA | D33: 1 | E33: 69500 | F33: 0
C34: EPS DICIEMBRE ALEX ZUÑIGA | D34: 1 | E34: 240000 | F34: =D34*E34 -> 240000
C35: EPS DICIEMBRE ROSA YATACUE | D35: 1 | E35: 97500 | F35: =D35*E35 -> 97500
C36: EPS DICIEMBRE MERK SPRESS | D36: 1 | E36: 95000 | F36: =D36*E36 -> 95000
C37: EPS DICIEMBRE FABIO ALONSO | D37: 1 | E37: 850000 | F37: =D37*E37 -> 850000
C38: AFILIACION ROBERTO SALUD TOTAL | D38: 1 | E38: 90000 | F38: =D38*E38 -> 90000
C39: memoria ram y sotfware sede | D39: 2 | E39: 50000 | F39: =D39*E39 -> 100000
C40: cargador y juegos sede | D40: 2 | E40: 40000 | F40: =D40*E40 -> 80000
C41: envio 82mil whatsapp | D41: 82000 | E41: 20 | F41: =D41*E41 -> 1640000
F43: =SUM(F2:F41) -> 12702500 | G43: =SUM(G2:G26) -> 4223000 | H43: =SUM(H2:H41) -> 2606500 | I43: =SUM(I2:I41) -> 0
G44: =4229000-G43 -> 6000 | H44: =2044250-H43 -> -562250
H45: =H44+G44 -> -556250
C49: cant | D49: cant | E49: pago | F49: dias | G49: total
C50: personal | D50: 2 | E50: 30000 | F50: 30 | G50: =D50*E50*F50 -> 1800000
C51: personal | D51: 2 | E51: 30000 | F51: 15 | G51: =D51*E51*F51 -> 900000
C52: minutos | D52: 7850 | E52: 45 | G52: =D52*E52 -> 353250
C53: mensajes de texto | D53: 7850 | E53: 45 | G53: =D53*E53 -> 353250
C54: gastos equipos y energia | G54: 300000
G56: =SUM(G50:G55) -> 3706500
F58: ganancia | G58: =4400000-G56 -> 693500
C61: ENERO
C62: DESCRIPCION | D62: CANT | E62: VALOR | F62: VALOR EXTRA
C63: llamadas lideres | D63: 1 | E63: 200000
C64: LLAMADAS CUMPLE DICIEMBRE | D64: 1 | E64: 1500000
C65: ACUERDO BRAYAN | D65: 1 | E65: 1000000
C66: INTERESES PRESTAMO AMPARO | D66: 1 | E66: 558000
C67: TARJETA CREDITO BRAYAN | D67: 1 | E67: 350000
C68: IPHONE CARMEN ELENA | D68: 1 | E68: 250000
C69: EPS DICIEMBRE SARAZA | D69: 1 | E69: 200000
C70: EPS DICIEMBRE ALEX ZUÑIGA | D70: 1 | E70: 240000
C71: EPS DICIEMBRE ROSA YATACUE | D71: 1 | E71: 100000
C72: EPS DICIEMBRE FABIO ALONSO | D72: 1 | F72: 1120000
C73: AFILIACION ROBERTO SALUD TOTAL | D73: 1 | F73: 140000
C74: RECARGAS A CELULAR | D74: 1
E77: =SUM(E63:E75) -> 4398000 | F77: =SUM(F63:F75) -> 1260000
C82: FEBRERO
C83: DESCRIPCION | D83: CANT | E83: VALOR | F83: VALOR EXTRA
C84: LLAMADAS CUMPLE DICIEMBRE | D84: 1 | E84: 2000000
C85: ACUERDO BRAYAN | D85: 1 | E85: 1000000
C86: INTERESES PRESTAMO AMPARO | D86: 1 | E86: 360000
C87: IPHONE CARMEN ELENA | D87: 1 | E87: 250000
C88: EPS DICIEMBRE LUCIA SARAZA | D88: 1 | E88: 205000
C89: EPS DICIEMBRE ALEX ZUÑIGA | D89: 1 | E89: 240000
C90: EPS DICIEMBRE ROSA YATACUE | D90: 1 | E90: 105000
C91: EPS DICIEMBRE FABIO ALONSO | D91: 1 | F91: 1120000
C92: EPS ROBERTO SALUD TOTAL FEBRERO | D92: 1 | E92: 134000
C93: FORMATEO, INSTALACION PORTATILES | D93: 5 | F93: =D93*45000 -> 225000
C94: RECARGAS A CELULAR | D94: 1 | E94: 0
C95: envio extras sms | D95: 2800 | E95: =D95*38 -> 106400
C96: monica castiblanco EPS | D96: 1
E99: =SUM(E84:E98) -> 4400400 | F99: =SUM(F84:F98) -> 1345000
C103: MARZO
C104: DESCRIPCION | D104: CANT | E104: VALOR | F104: VALOR EXTRA
C105: LLAMADAS CUMPLE DICIEMBRE | D105: 1 | E105: 2000000
C106: ACUERDO BRAYAN | D106: 1 | E106: 500000
C107: INTERESES PRESTAMO AMPARO | D107: 1 | E107: 360000
C108: IPHONE CARMEN ELENA | D108: 1 | E108: 250000
C109: ALQUILER SERVIDOR | D109: 1 | E109: 200000
C110: ALQUILER PROGRAMA | D110: 1 | E110: 300000
C111: abono prestamo | E111: ??
C112: EPS DICIEMBRE LUCIA SARAZA | D112: 1 | E112: 205000
C113: EPS DICIEMBRE ALEX ZUÑIGA | D113: 1 | E113: 240000
C114: EPS DICIEMBRE ROSA YATACUE | D114: 1 | E114: 105000
C115: FABITO - EPS+ARL+PENSION AFILIACION | D115: 1 | E115: 150000
C116: EPS DICIEMBRE FABIO ALONSO | D116: 1 | F116: 1120000
C117: FABITO - EPS+ARL+PENSION | D117: 1 | F117: 275000
C118: llamadas lideres | D118: 1 | F118: 500000
C119: tiquetes | D119: 50 | E119: 100000
C120: SMS RECONOCIMIENTO | D120: 2100 | F120: 100000
...

Sheet INTERESES
B2: ESTEFANIA BARREIRO | J2: ESTEFANIA BARREIRO | R2: DOÑA LUCY
B4: MES | C4: PRESTAMO | D4: INTERES | E4: DEUDA | G4: ABONO | H4: SALDO | J4: MES | K4: PRESTAMO | L4: INTERES | M4: DEUDA | O4: ABONO | P4: SALDO | R4: MES | S4: PRESTAMO | T4: INTERES | U4: DEUDA | W4: ABONO | X4: SALDO
A5: 2020 | B5: MARZO | C5: 1000000 | D5: =C5*3.5% -> 35000 | E5: =C5+D5 -> 1035000 | G5: 0 | H5: =E5-G5 -> 1035000 | I5: 2020 | J5: FEBRERO | K5: 2060000 | L5: =K5*3.5% -> 72100 | M5: =K5+L5 -> 2132100 | O5: 60000 | P5: =M5-O5 -> 2072100 | Q5: 2020 | R5: SEPTIEMBRE | S5: 2200000 | T5: =S5*3.5% -> 77000 | U5: =S5+T5 -> 2277000 | W5: 300000 | X5: =U5-W5 -> 1977000
A6: 2020 | B6: ABRIL | C6: =H5 -> 1035000 | D6: =C6*3.5% -> 36225 | E6: =C6+D6 -> 1071225 | G6: 0 | H6: =E6-G6 -> 1071225 | I6: 2020 | J6: MARZO | K6: =P5 -> 2072100 | L6: =K6*3.5% -> 72523.5 | M6: =K6+L6 -> 2144623.5 | O6: 120000 | P6: =M6-O6 -> 2024623.5 | Q6: 2020 | R6: OCTUBRE | S6: =X5 -> 1977000 | T6: =S6*3.5% -> 69195 | U6: =S6+T6 -> 2046195 | W6: 300000 | X6: =U6-W6 -> 1746195
A7: 2020 | B7: MAYO | C7: =H6 -> 1071225 | D7: =C7*3.5% -> 37492.875 | E7: =C7+D7 -> 1108717.9 | G7: 0 | H7: =E7-G7 -> 1108717.9 | I7: 2020 | J7: ABRIL | K7: =P6 -> 2024623.5 | L7: =K7*3.5% -> 70861.823 | M7: =K7+L7 -> 2095485.3 | O7: 0 | P7: =M7-O7 -> 2095485.3 | Q7: 2020 | R7: NOVIEMBRE | S7: =X6+200000 -> 1946195 | T7: =S7*3.5% -> 68116.825 | U7: =S7+T7 -> 2014311.8 | W7: 300000 | X7: =U7-W7 -> 1714311.8
A8: 2020 | B8: JUNIO | C8: =H7 -> 1108717.9 | D8: =C8*3.5% -> 38805.126 | E8: =C8+D8 -> 1147523 | G8: 0 | H8: =E8-G8 -> 1147523 | I8: 2020 | J8: MAYO | K8: =P7 -> 2095485.3 | L8: =K8*3.5% -> 73341.986 | M8: =K8+L8 -> 2168827.3 | O8: 0 | P8: =M8-O8 -> 2168827.3 | Q8: 2020 | R8: DICIEMBRE | S8: =X7+1000000 -> 2714311.8 | T8: =S8*3.5% -> 95000.914 | U8: =S8+T8 -> 2809312.7 | W8: 300000 | X8: =U8-W8 -> 2509312.7
A9: 2020 | B9: JULIO | C9: =H8 -> 1147523 | D9: =C9*3.5% -> 40163.305 | E9: =C9+D9 -> 1187686.3 | G9: 0 | H9: =E9-G9 -> 1187686.3 | I9: 2020 | J9: JUNIO | K9: =P8 -> 2168827.3 | L9: =K9*3.5% -> 75908.956 | M9: =K9+L9 -> 2244736.3 | O9: 240000 | P9: =M9-O9 -> 2004736.3 | Q9: 2021 | R9: ENERO | S9: =X8 -> 2509312.7 | T9: =S9*3.5% -> 87825.946 | U9: =S9+T9 -> 2597138.7 | W9: 300000 | X9: =U9-W9 -> 2297138.7
A10: 2020 | B10: AGOSTO | C10: =H9 -> 1187686.3 | D10: =C10*3.5% -> 41569.021 | E10: =C10+D10 -> 1229255.3 | G10: 0 | H10: =E10-G10 -> 1229255.3 | I10: 2020 | J10: JULIO | K10: =P9 -> 2004736.3 | L10: =K10*3.5% -> 70165.769 | M10: =K10+L10 -> 2074902 | O10: 120000 | P10: =M10-O10 -> 1954902 | Q10: 2021 | R10: FEBRERO | S10: =X9 -> 2297138.7 | T10: =S10*3.5% -> 80399.854 | U10: =S10+T10 -> 2377538.5 | W10: 300000 | X10: =U10-W10 -> 2077538.5
A11: 2020 | B11: SEPTIEMBRE | C11: =H10 -> 1229255.3 | D11: =C11*3.5% -> 43023.936 | E11: =C11+D11 -> 1272279.3 | G11: 400000 | H11: =E11-G11 -> 872279.26 | I11: 2020 | J11: AGOSTO | K11: =P10 -> 1954902 | L11: =K11*3.5% -> 68421.571 | M11: =K11+L11 -> 2023323.6 | O11: 120000 | P11: =M11-O11 -> 1903323.6 | Q11: 2021 | R11: MARZO | S11: =X10 -> 2077538.5 | T11: =S11*3.5% -> 72713.849 | U11: =S11+T11 -> 2150252.4 | W11: 300000 | X11: =U11-W11 -> 1850252.4
A12: 2020 | B12: OCTUBRE | C12: =H11 -> 872279.26 | D12: =C12*3.5% -> 30529.774 | E12: =C12+D12 -> 902809.04 | H12: =E12-G12 -> 902809.04 | I12: 2020 | J12: SEPTIEMBRE | K12: =P11 -> 1903323.6 | L12: =K12*3.5% -> 66616.326 | M12: =K12+L12 -> 1969939.9 | O12: 600000 | P12: =M12-O12 -> 1369939.9 | Q12: 2021 | R12: ABRIL | S12: 3150252 | T12: =S12*3.5% -> 110258.82 | U12: =S12+T12 -> 3260510.8 | W12: 300000 | X12: =U12-W12 -> 2960510.8
A13: 2020 | B13: NOVIEMBRE | C13: =H12 -> 902809.04 | D13: =C13*3.5% -> 31598.316 | E13: =C13+D13 -> 934407.35 | H13: =E13-G13 -> 934407.35 | I13: 2020 | J13: OCTUBRE | K13: =P12 -> 1369939.9 | L13: =K13*3.5% -> 47947.898 | M13: =K13+L13 -> 1417887.8 | P13: =M13-O13 -> 1417887.8 | Q13: 2021 | R13: MAYO | S13: =X12 -> 2960510.8 | T13: =S13*3.5% -> 103617.88 | U13: =S13+T13 -> 3064128.7 | W13: 300000 | X13: =U13-W13 -> 2764128.7
A14: 2020 | B14: DICIEMBRE | C14: =H13 -> 934407.35 | D14: =C14*3.5% -> 32704.257 | E14: =C14+D14 -> 967111.61 | H14: =E14-G14 -> 967111.61 | I14: 2020 | J14: NOVIEMBRE | K14: =P13 -> 1417887.8 | L14: =K14*3.5% -> 49626.074 | M14: =K14+L14 -> 1467513.9 | P14: =M14-O14 -> 1467513.9 | Q14: 2021 | R14: JUNIO | S14: =X13 -> 2764128.7 | T14: =S14*3.5% -> 96744.504 | U14: =S14+T14 -> 2860873.2 | W14: 300000 | X14: =U14-W14 -> 2560873.2
A15: 2021 | B15: ENERO | C15: =H14 -> 967111.61 | D15: =C15*3.5% -> 33848.906 | E15: =C15+D15 -> 1000960.5 | H15: =E15-G15 -> 1000960.5 | I15: 2020 | J15: DICIEMBRE | K15: =P14 -> 1467513.9 | L15: =K15*3.5% -> 51362.987 | M15: =K15+L15 -> 1518876.9 | P15: =M15-O15 -> 1518876.9 | Q15: 2021 | R15: JULIO | S15: =X14 -> 2560873.2 | T15: =S15*3.5% -> 89630.562 | U15: =S15+T15 -> 2650503.8 | W15: 300000 | X15: =U15-W15 -> 2350503.8
A16: 2021 | B16: FEBRERO | C16: =H15 -> 1000960.5 | D16: =C16*3.5% -> 35033.618 | E16: =C16+D16 -> 1035994.1 | H16: =E16-G16 -> 1035994.1 | I16: 2021 | J16: ENERO | K16: =P15 -> 1518876.9 | L16: =K16*3.5% -> 53160.691 | M16: =K16+L16 -> 1572037.6 | P16: =M16-O16 -> 1572037.6 | Q16: 2021 | R16: AGOSTO | S16: =X15 -> 2350503.8 | T16: =S16*3.5% -> 82267.632 | U16: =S16+T16 -> 2432771.4 | W16: 300000 | X16: =U16-W16 -> 2132771.4
A17: 2021 | B17: MARZO | C17: =H16 -> 1035994.1 | D17: =C17*3.5% -> 36259.795 | E17: =C17+D17 -> 1072253.9 | H17: =E17-G17 -> 1072253.9 | I17: 2021 | J17: FEBRERO | K17: =P16 -> 1572037.6 | L17: =K17*3.5% -> 55021.315 | M17: =K17+L17 -> 1627058.9 | P17: =M17-O17 -> 1627058.9 | Q17: 2021 | R17: SEPTIEMBRE | S17: 3632771 | T17: =S17*3.5% -> 127146.99 | U17: =S17+T17 -> 3759918 | W17: 300000 | X17: =U17-W17 -> 3459918
A18: 2021 | B18: ABRIL | C18: =H17 -> 1072253.9 | D18: =C18*3.5% -> 37528.888 | E18: =C18+D18 -> 1109782.8 | H18: =E18-G18 -> 1109782.8 | I18: 2021 | J18: MARZO | K18: =P17 -> 1627058.9 | L18: =K18*3.5% -> 56947.061 | M18: =K18+L18 -> 1684006 | P18: =M18-O18 -> 1684006 | Q18: 2021 | R18: OCTUBRE | S18: =X17 -> 3459918 | T18: =S18*3.5% -> 121097.13 | U18: =S18+T18 -> 3581015.1 | W18: 250000 | X18: =U18-W18 -> 3331015.1
A19: 2021 | B19: MAYO | C19: =H18 -> 1109782.8 | D19: =C19*3.5% -> 38842.399 | E19: =C19+D19 -> 1148625.2 | H19: =E19-G19 -> 1148625.2 | I19: 2021 | J19: ABRIL | K19: =P18 -> 1684006 | L19: =K19*3.5% -> 58940.209 | M19: =K19+L19 -> 1742946.2 | P19: =M19-O19 -> 1742946.2 | Q19: 2021 | R19: NOVIEMBRE | S19: =X18 -> 3331015.1 | T19: =S19*3.5% -> 116585.53 | U19: =S19+T19 -> 3447600.6 | W19: 250000 | X19: =U19-W19 -> 3197600.6
A20: 2021 | B20: JUNIO | C20: =H19 -> 1148625.2 | D20: =C20*3.5% -> 40201.883 | E20: =C20+D20 -> 1188827.1 | H20: =E20-G20 -> 1188827.1 | I20: 2021 | J20: MAYO | K20: =P19 -> 1742946.2 | L20: =K20*3.5% -> 61003.116 | M20: =K20+L20 -> 1803949.3 | P20: =M20-O20 -> 1803949.3 | Q20: 2021 | R20: DICIEMBRE | S20: =X19 -> 3197600.6 | T20: =S20*3.5% -> 111916.02 | U20: =S20+T20 -> 3309516.7 | W20: 250000 | X20: =U20-W20 -> 3059516.7
A21: 2021 | B21: JULIO | C21: =H20 -> 1188827.1 | D21: =C21*3.5% -> 41608.948 | E21: =C21+D21 -> 1230436 | H21: =E21-G21 -> 1230436 | I21: 2021 | J21: JUNIO | K21: =P20 -> 1803949.3 | L21: =K21*3.5% -> 63138.225 | M21: =K21+L21 -> 1867087.5 | P21: =M21-O21 -> 1867087.5 | Q21: 2022 | R21: ENERO | S21: =X20 -> 3059516.7 | T21: =S21*3.5% -> 107083.08 | U21: =S21+T21 -> 3166599.7 | W21: 250000 | X21: =U21-W21 -> 2916599.7
A22: 2021 | B22: AGOSTO | C22: =H21 -> 1230436 | D22: =C22*3.5% -> 43065.262 | E22: =C22+D22 -> 1273501.3 | H22: =E22-G22 -> 1273501.3 | I22: 2021 | J22: JULIO | K22: =P21 -> 1867087.5 | L22: =K22*3.5% -> 65348.063 | M22: =K22+L22 -> 1932435.6 | P22: =M22-O22 -> 1932435.6 | Q22: 2022 | R22: FEBRERO | S22: =X21 -> 2916599.7 | T22: =S22*3.5% -> 102080.99 | U22: =S22+T22 -> 3018680.7 | W22: 210000 | X22: =U22-W22 -> 2808680.7
A23: 2021 | B23: SEPTIEMBRE | C23: =H22 -> 1273501.3 | D23: =C23*3.5% -> 44572.546 | E23: =C23+D23 -> 1318073.9 | H23: =E23-G23 -> 1318073.9 | I23: 2021 | J23: AGOSTO | K23: =P22 -> 1932435.6 | L23: =K23*3.5% -> 67635.245 | M23: =K23+L23 -> 2000070.8 | P23: =M23-O23 -> 2000070.8 | Q23: 2022 | R23: MARZO | S23: =X22 -> 2808680.7 | T23: =S23*3.5% -> 98303.826 | U23: =S23+T23 -> 2906984.6 | W23: 200000 | X23: =U23-W23 -> 2706984.6
A24: 2021 | B24: OCTUBRE | C24: =H23 -> 1318073.9 | D24: =C24*3.5% -> 46132.585 | E24: =C24+D24 -> 1364206.4 | H24: =E24-G24 -> 1364206.4 | I24: 2021 | J24: SEPTIEMBRE | K24: =P23 -> 2000070.8 | L24: =K24*3.5% -> 70002.478 | M24: =K24+L24 -> 2070073.3 | P24: =M24-O24 -> 2070073.3 | Q24: 2022 | R24: ABRIL | S24: =X23 -> 2706984.6 | T24: =S24*3.5% -> 94744.46 | U24: =S24+T24 -> 2801729 | X24: =U24-W24 -> 2801729
A25: 2021 | B25: NOVIEMBRE | C25: =H24 -> 1364206.4 | D25: =C25*3.5% -> 47747.225 | E25: =C25+D25 -> 1411953.7 | H25: =E25-G25 -> 1411953.7 | I25: 2021 | J25: OCTUBRE | K25: =P24 -> 2070073.3 | L25: =K25*3.5% -> 72452.565 | M25: =K25+L25 -> 2142525.9 | P25: =M25-O25 -> 2142525.9 | Q25: 2022 | R25: MAYO | S25: =X24 -> 2801729 | T25: =S25*3.5% -> 98060.516 | U25: =S25+T25 -> 2899789.5 | X25: =U25-W25 -> 2899789.5
A26: 2021 | B26: DICIEMBRE | C26: =H25 -> 1411953.7 | D26: =C26*3.5% -> 49418.378 | E26: =C26+D26 -> 1461372 | H26: =E26-G26 -> 1461372 | I26: 2021 | J26: NOVIEMBRE | K26: =P25 -> 2142525.9 | L26: =K26*3.5% -> 74988.405 | M26: =K26+L26 -> 2217514.3 | P26: =M26-O26 -> 2217514.3 | Q26: 2022 | R26: JUNIO | S26: =X25 -> 2899789.5 | T26: =S26*3.5% -> 101492.63 | U26: =S26+T26 -> 3001282.2 | X26: =U26-W26 -> 3001282.2
A27: 2022 | B27: ENERO | C27: =H26 -> 1461372 | D27: =C27*3.5% -> 51148.022 | E27: =C27+D27 -> 1512520.1 | H27: =E27-G27 -> 1512520.1 | I27: 2021 | J27: DICIEMBRE | K27: =P26 -> 2217514.3 | L27: =K27*3.5% -> 77612.999 | M27: =K27+L27 -> 2295127.3 | P27: =M27-O27 -> 2295127.3 | Q27: 2022 | R27: JULIO | S27: =X26 -> 3001282.2 | T27: =S27*3.5% -> 105044.88 | U27: =S27+T27 -> 3106327.1 | X27: =U27-W27 -> 3106327.1
A28: 2022 | B28: FEBRERO | C28: =H27 -> 1512520.1 | D28: =C28*3.5% -> 52938.202 | E28: =C28+D28 -> 1565458.3 | H28: =E28-G28 -> 1565458.3 | I28: 2022 | J28: ENERO | K28: =P27 -> 2295127.3 | L28: =K28*3.5% -> 80329.454 | M28: =K28+L28 -> 2375456.7 | P28: =M28-O28 -> 2375456.7 | Q28: 2022 | R28: AGOSTO | S28: =X27 -> 3106327.1 | T28: =S28*3.5% -> 108721.45 | U28: =S28+T28 -> 3215048.5 | X28: =U28-W28 -> 3215048.5
A29: 2022 | B29: MARZO | C29: =H28 -> 1565458.3 | D29: =C29*3.5% -> 54791.039 | E29: =C29+D29 -> 1620249.3 | H29: =E29-G29 -> 1620249.3 | I29: 2022 | J29: FEBRERO | K29: =P28 -> 2375456.7 | L29: =K29*3.5% -> 83140.985 | M29: =K29+L29 -> 2458597.7 | P29: =M29-O29 -> 2458597.7 | Q29: 2022 | R29: SEPTIEMBRE | S29: =X28 -> 3215048.5 | T29: =S29*3.5% -> 112526.7 | U29: =S29+T29 -> 3327575.2 | X29: =U29-W29 -> 3327575.2
A30: 2022 | B30: ABRIL | C30: =H29 -> 1620249.3 | D30: =C30*3.5% -> 56708.726 | E30: =C30+D30 -> 1676958 | H30: =E30-G30 -> 1676958 | I30: 2022 | J30: MARZO | K30: =P29 -> 2458597.7 | L30: =K30*3.5% -> 86050.92 | M30: =K30+L30 -> 2544648.6 | P30: =M30-O30 -> 2544648.6 | Q30: 2022 | R30: OCTUBRE | S30: =X29 -> 3327575.2 | T30: =S30*3.5% -> 116465.13 | U30: =S30+T30 -> 3444040.3 | X30: =U30-W30 -> 3444040.3
A31: 2022 | B31: MAYO | C31: =H30 -> 1676958 | D31: =C31*3.5% -> 58693.531 | E31: =C31+D31 -> 1735651.6 | H31: =E31-G31 -> 1735651.6 | I31: 2022 | J31: ABRIL | K31: =P30 -> 2544648.6 | L31: =K31*3.5% -> 89062.702 | M31: =K31+L31 -> 2633711.3 | P31: =M31-O31 -> 2633711.3 | Q31: 2022 | R31: NOVIEMBRE | S31: =X30 -> 3444040.3 | T31: =S31*3.5% -> 120541.41 | U31: =S31+T31 -> 3564581.7 | X31: =U31-W31 -> 3564581.7
A32: 2022 | B32: JUNIO | C32: =H31 -> 1735651.6 | D32: =C32*3.5% -> 60747.805 | E32: =C32+D32 -> 1796399.4 | H32: =E32-G32 -> 1796399.4 | I32: 2022 | J32: MAYO | K32: =P31 -> 2633711.3 | L32: =K32*3.5% -> 92179.896 | M32: =K32+L32 -> 2725891.2 | P32: =M32-O32 -> 2725891.2 | Q32: 2022 | R32: DICIEMBRE | S32: =X31 -> 3564581.7 | T32: =S32*3.5% -> 124760.36 | U32: =S32+T32 -> 3689342.1 | X32: =U32-W32 -> 3689342.1
A33: 2022 | B33: JULIO | C33: =H32 -> 1796399.4 | D33: =C33*3.5% -> 62873.978 | E33: =C33+D33 -> 1859273.3 | H33: =E33-G33 -> 1859273.3 | I33: 2022 | J33: JUNIO | K33: =P32 -> 2725891.2 | L33: =K33*3.5% -> 95406.193 | M33: =K33+L33 -> 2821297.4 | P33: =M33-O33 -> 2821297.4
A34: 2022 | B34: AGOSTO | C34: =H33 -> 1859273.3 | D34: =C34*3.5% -> 65074.567 | E34: =C34+D34 -> 1924347.9 | H34: =E34-G34 -> 1924347.9 | I34: 2022 | J34: JULIO | K34: =P33 -> 2821297.4 | L34: =K34*3.5% -> 98745.409 | M34: =K34+L34 -> 2920042.8 | P34: =M34-O34 -> 2920042.8
B42: HECTOR MEDINA | J42: EINER MEJIA | R42: HUMBERTO PINEDA 3,5%
B44: MES | C44: PRESTAMO | D44: INTERES | E44: DEUDA | G44: ABONO | H44: SALDO | J44: MES | K44: PRESTAMO | L44: INTERES | M44: DEUDA | O44: ABONO | P44: SALDO | R44: MES | S44: PRESTAMO | T44: INTERES | U44: DEUDA | W44: ABONO | X44: SALDO
B45: FEBRERO | C45: 8000000 | D45: =C45*3.5% -> 280000 | E45: =C45+D45 -> 8280000 | G45: 280000 | H45: =E45-G45 -> 8000000 | I45: 2020 | J45: NOVIEMBRE | K45: 1300000 | L45: =K45*3.5% -> 45500 | M45: =K45+L45 -> 1345500 | O45: 12000 | P45: =M45-O45 -> 1333500 | Q45: 2020 | R45: SEPTIEMBRE | S45: 2000000 | T45: =S45*3.5% -> 70000 | U45: =S45+T45 -> 2070000 | W45: 70000 | X45: =U45-W45 -> 2000000
B46: MARZO | C46: =H45 -> 8000000 | D46: =C46*3.5% -> 280000 | E46: =C46+D46 -> 8280000 | G46: 0 | H46: =E46-G46 -> 8280000 | I46: 2020 | J46: DICIEMBRE | K46: =P45 -> 1333500 | L46: =K46*3.5% -> 46672.5 | M46: =K46+L46 -> 1380172.5 | O46: 200000 | P46: =M46-O46 -> 1180172.5 | Q46: 2020 | R46: OCTUBRE | S46: =X45 -> 2000000 | T46: =S46*3.5% -> 70000 | U46: =S46+T46 -> 2070000 | W46: 70000 | X46: =U46-W46 -> 2000000
B47: ABRIL | C47: =H46 -> 8280000 | D47: =C47*3.5% -> 289800 | E47: =C47+D47 -> 8569800 | G47: 1000000 | H47: =E47-G47 -> 7569800 | I47: 2021 | J47: ENERO | K47: =P46 -> 1180172.5 | L47: =K47*3.5% -> 41306.038 | M47: =K47+L47 -> 1221478.5 | O47: 100000 | P47: =M47-O47 -> 1121478.5 | Q47: 2020 | R47: NOVIEMBRE | S47: =X46 -> 2000000 | T47: =S47*3.5% -> 70000 | U47: =S47+T47 -> 2070000 | W47: 0 | X47: =U47-W47 -> 2070000
B48: MAYO | C48: =H47 -> 7569800 | D48: =C48*3.5% -> 264943 | E48: =C48+D48 -> 7834743 | G48: 1000000 | H48: =E48-G48 -> 6834743 | I48: 2021 | J48: FEBRERO | K48: =P47 -> 1121478.5 | L48: =K48*3.5% -> 39251.749 | M48: =K48+L48 -> 1160730.3 | O48: 100000 | P48: =M48-O48 -> 1060730.3 | Q48: 2020 | R48: DICIEMBRE | S48: =X47 -> 2070000 | T48: =S48*3.5% -> 72450 | U48: =S48+T48 -> 2142450 | W48: 140000 | X48: =U48-W48 -> 2002450
B49: JUNIO | C49: =H48 -> 6834743 | D49: =C49*3.5% -> 239216.01 | E49: =C49+D49 -> 7073959 | G49: 1488000 | H49: =E49-G49 -> 5585959 | I49: 2021 | J49: MARZO | K49: =P48 -> 1060730.3 | L49: =K49*3.5% -> 37125.56 | M49: =K49+L49 -> 1097855.8 | O49: 0 | P49: =M49-O49 -> 1097855.8 | Q49: 2021 | R49: ENERO | S49: =X48 -> 2002450 | T49: =S49*3.5% -> 70085.75 | U49: =S49+T49 -> 2072535.8 | W49: 70000 | X49: =U49-W49 -> 2002535.8
B50: JULIO | C50: =H49 -> 5585959 | D50: =C50*3.5% -> 195508.57 | E50: =C50+D50 -> 5781467.6 | G50: 0 | H50: =E50-G50 -> 5781467.6 | I50: 2021 | J50: ABRIL | K50: =P49 -> 1097855.8 | L50: =K50*3.5% -> 38424.955 | M50: =K50+L50 -> 1136280.8 | O50: 25000 | P50: =M50-O50 -> 1111280.8 | Q50: 2021 | R50: FEBRERO | S50: =X49 -> 2002535.8 | T50: =S50*3.5% -> 70088.751 | U50: =S50+T50 -> 2072624.5 | W50: 70000 | X50: =U50-W50 -> 2002624.5
B51: AGOSTO | C51: =H50 -> 5781467.6 | D51: =C51*3.5% -> 202351.36 | E51: =C51+D51 -> 5983818.9 | G51: 500000 | H51: =E51-G51 -> 5483818.9 | I51: 2021 | J51: MAYO | K51: =P50 -> 1111280.8 | L51: =K51*3.5% -> 38894.828 | M51: =K51+L51 -> 1150175.6 | O51: 0 | P51: =M51-O51 -> 1150175.6 | Q51: 2021 | R51: MARZO | S51: =X50 -> 2002624.5 | T51: =S51*3.5% -> 70091.858 | U51: =S51+T51 -> 2072716.4 | W51: 0 | X51: =U51-W51 -> 2072716.4
B52: SEPTIEMBRE | C52: =H51 -> 5483818.9 | D52: =C52*3.5% -> 191933.66 | E52: =C52+D52 -> 5675752.6 | G52: 0 | H52: =E52-G52 -> 5675752.6 | I52: 2021 | J52: JUNIO | K52: =P51 -> 1150175.6 | L52: =K52*3.5% -> 40256.147 | M52: =K52+L52 -> 1190431.8 | O52: 117000 | P52: =M52-O52 -> 1073431.8 | Q52: 2021 | R52: ABRIL | S52: =X51 -> 2072716.4 | T52: =S52*3.5% -> 72545.073 | U52: =S52+T52 -> 2145261.4 | W52: 70000 | X52: =U52-W52 -> 2075261.4
B53: OCTUBRE | C53: =H52 -> 5675752.6 | D53: =C53*3.5% -> 198651.34 | E53: =C53+D53 -> 5874403.9 | G53: 1000000 | H53: =E53-G53 -> 4874403.9 | I53: 2021 | J53: JULIO | K53: =P52 -> 1073431.8 | L53: =K53*3.5% -> 37570.112 | M53: =K53+L53 -> 1111001.9 | O53: 0 | P53: =M53-O53 -> 1111001.9 | Q53: 2021 | R53: MAYO | S53: =X52 -> 2075261.4 | T53: =S53*3.5% -> 72634.15 | U53: =S53+T53 -> 2147895.6 | W53: 70000 | X53: =U53-W53 -> 2077895.6
B54: NOVIEMBRE | C54: =H53+2000000 -> 6874403.9 | D54: =C54*3.5% -> 240604.14 | E54: =C54+D54 -> 7115008.1 | G54: 2000000 | H54: =E54-G54 -> 5115008.1 | I54: 2021 | J54: AGOSTO | K54: =P53 -> 1111001.9 | L54: =K54*3.5% -> 38885.066 | M54: =K54+L54 -> 1149887 | O54: 0 | P54: =M54-O54 -> 1149887 | Q54: 2021 | R54: JUNIO | S54: =X53 -> 2077895.6 | T54: =S54*3.5% -> 72726.345 | U54: =S54+T54 -> 2150621.9 | W54: 70000 | X54: =U54-W54 -> 2080621.9
B55: DICIEMBRE | C55: =H54 -> 5115008.1 | D55: =C55*3.5% -> 179025.28 | E55: =C55+D55 -> 5294033.4 | G55: 0 | H55: =E55-G55 -> 5294033.4 | I55: 2021 | J55: SEPTIEMBRE | K55: =P54 -> 1149887 | L55: =K55*3.5% -> 40246.043 | M55: =K55+L55 -> 1190133 | O55: 0 | P55: =M55-O55 -> 1190133 | Q55: 2021 | R55: JULIO | S55: =X54 -> 2080621.9 | T55: =S55*3.5% -> 72821.767 | U55: =S55+T55 -> 2153443.7 | W55: 0 | X55: =U55-W55 -> 2153443.7
B56: ENERO | C56: =H55 -> 5294033.4 | D56: =C56*3.5% -> 185291.17 | E56: =C56+D56 -> 5479324.5 | G56: 0 | H56: =E56-G56 -> 5479324.5 | I56: 2021 | J56: OCTUBRE | K56: =P55 -> 1190133 | L56: =K56*3.5% -> 41654.655 | M56: =K56+L56 -> 1231787.7 | O56: 0 | P56: =M56-O56 -> 1231787.7 | Q56: 2021 | R56: AGOSTO | S56: =X55 -> 2153443.7 | T56: =S56*3.5% -> 75370.529 | U56: =S56+T56 -> 2228814.2 | W56: 0 | X56: =U56-W56 -> 2228814.2
B57: FEBRERO | C57: =H56 -> 5479324.5 | D57: =C57*3.5% -> 191776.36 | E57: =C57+D57 -> 5671100.9 | G57: 0 | H57: =E57-G57 -> 5671100.9 | I57: 2021 | J57: NOVIEMBRE | K57: =P56 -> 1231787.7 | L57: =K57*3.5% -> 43112.568 | M57: =K57+L57 -> 1274900.2 | O57: 0 | P57: =M57-O57 -> 1274900.2 | Q57: 2021 | R57: SEPTIEMBRE | S57: =X56 -> 2228814.2 | T57: =S57*3.5% -> 78008.498 | U57: =S57+T57 -> 2306822.7 | W57: 0 | X57: =U57-W57 -> 2306822.7
B58: MARZO | I58: 2021 | J58: DICIEMBRE | K58: =P57 -> 1274900.2 | L58: =K58*3.5% -> 44621.508 | M58: =K58+L58 -> 1319521.7 | O58: 0 | P58: =M58-O58 -> 1319521.7 | Q58: 2021 | R58: OCTUBRE | S58: =X57 -> 2306822.7 | T58: =S58*3.5% -> 80738.795 | U58: =S58+T58 -> 2387561.5 | W58: 0 | X58: =U58-W58 -> 2387561.5
B59: ABRIL | I59: 2022 | J59: ENERO | K59: =P58 -> 1319521.7 | L59: =K59*3.5% -> 46183.26 | M59: =K59+L59 -> 1365705 | O59: 282000 | P59: =M59-O59 -> 1083705 | Q59: 2021 | R59: NOVIEMBRE | S59: =X58 -> 2387561.5 | T59: =S59*3.5% -> 83564.653 | U59: =S59+T59 -> 2471126.2 | W59: 0 | X59: =U59-W59 -> 2471126.2
B60: MAYO | I60: 2022 | J60: FEBRERO | K60: =P59 -> 1083705 | L60: =K60*3.5% -> 37929.675 | M60: =K60+L60 -> 1121634.7 | O60: 0 | P60: =M60-O60 -> 1121634.7 | Q60: 2021 | R60: DICIEMBRE | S60: =X59 -> 2471126.2 | T60: =S60*3.5% -> 86489.416 | U60: =S60+T60 -> 2557615.6 | W60: 0 | X60: =U60-W60 -> 2557615.6
B61: JUNIO | I61: 2022 | J61: MARZO | K61: =P60 -> 1121634.7 | L61: =K61*3.5% -> 39257.213 | M61: =K61+L61 -> 1160891.9 | O61: 0 | P61: =M61-O61 -> 1160891.9 | Q61: 2022 | R61: ENERO | S61: =X60 -> 2557615.6 | T61: =S61*3.5% -> 89516.545 | U61: =S61+T61 -> 2647132.1 | W61: 0 | X61: =U61-W61 -> 2647132.1
I62: 2022 | J62: ABRIL | K62: =P61 -> 1160891.9 | L62: =K62*3.5% -> 40631.216 | M62: =K62+L62 -> 1201523.1 | O62: 0 | P62: =M62-O62 -> 1201523.1 | Q62: 2022 | R62: FEBRERO | S62: =X61 -> 2647132.1 | T62: =S62*3.5% -> 92649.625 | U62: =S62+T62 -> 2739781.8 | W62: 0 | X62: =U62-W62 -> 2739781.8
I63: 2022 | J63: MAYO | K63: =P62 -> 1201523.1 | L63: =K63*3.5% -> 42053.308 | M63: =K63+L63 -> 1243576.4 | O63: 0 | P63: =M63-O63 -> 1243576.4 | Q63: 2022 | R63: MARZO
I64: 2022 | J64: JUNIO | K64: =P63 -> 1243576.4 | L64: =K64*3.5% -> 43525.174 | M64: =K64+L64 -> 1287101.6 | O64: 0 | P64: =M64-O64 -> 1287101.6 | Q64: 2022 | R64: ABRIL
I65: 2022 | J65: JULIO | K65: =P64 -> 1287101.6 | L65: =K65*3.5% -> 45048.555 | M65: =K65+L65 -> 1332150.1 | O65: 0 | P65: =M65-O65 -> 1332150.1 | Q65: 2022 | R65: MAYO
I66: 2022 | J66: AGOSTO | K66: =P65 -> 1332150.1 | L66: =K66*3.5% -> 46625.255 | M66: =K66+L66 -> 1378775.4 | O66: 0 | P66: =M66-O66 -> 1378775.4 | Q66: 2022 | R66: JUNIO
I67: 2022 | J67: SEPTIEMBRE | K67: =P66 -> 1378775.4 | L67: =K67*3.5% -> 48257.138 | M67: =K67+L67 -> 1427032.5 | O67: 0 | P67: =M67-O67 -> 1427032.5 | Q67: 2022 | R67: JULIO
I68: 2022 | J68: OCTUBRE | K68: =P67 -> 1427032.5 | L68: =K68*3.5% -> 49946.138 | M68: =K68+L68 -> 1476978.7 | O68: 0 | P68: =M68-O68 -> 1476978.7 | Q68: 2022 | R68: AGOSTO
R74: 3.5
B75: LUIS EDUARDO MIRA | J75: EDGAR GARCIA | R75: TOÑO
B77: MES | C77: PRESTAMO | D77: INTERES | E77: DEUDA | G77: ABONO | H77: SALDO | J77: MES | K77: PRESTAMO | L77: INTERES | M77: DEUDA | O77: ABONO | P77: SALDO | R77: MES | S77: PRESTAMO | T77: INTERES | U77: DEUDA | W77: ABONO | X77: SALDO
A78: 2021 | B78: DICIEMBRE | C78: 4000000 | D78: =C78*3.5% -> 140000 | E78: =C78+D78 -> 4140000 | G78: 0 | H78: =E78-G78 -> 4140000 | J78: ABRIL | K78: 2000000 | L78: =K78*3.5% -> 70000 | M78: =K78+L78 -> 2070000 | P78: =M78-O78 -> 2070000 | Q78: 2021 | R78: ABRIL | S78: 2000000 | T78: =S78*3.5% -> 70000 | U78: =S78+T78 -> 2070000 | W78: 120000 | X78: =U78-W78 -> 1950000
A79: 2022 | B79: ENERO | C79: =H78 -> 4140000 | D79: =C79*3.5% -> 144900 | E79: =C79+D79 -> 4284900 | G79: 100000 | H79: =E79-G79 -> 4184900 | J79: MAYO | K79: =P78 -> 2070000 | L79: =K79*3.5% -> 72450 | M79: =K79+L79 -> 2142450 | P79: =M79-O79 -> 2142450 | Q79: 2021 | R79: MAYO | S79: =X78 -> 1950000 | T79: =S79*3.5% -> 68250 | U79: =S79+T79 -> 2018250 | W79: 120000 | X79: =U79-W79 -> 1898250
A80: 2022 | B80: FEBRERO | C80: =H79 -> 4184900 | D80: =C80*3.5% -> 146471.5 | E80: =C80+D80 -> 4331371.5 | G80: 0 | H80: =E80-G80 -> 4331371.5 | J80: JUNIO | K80: =P79 -> 2142450 | L80: =K80*3.5% -> 74985.75 | M80: =K80+L80 -> 2217435.8 | P80: =M80-O80 -> 2217435.8 | Q80: 2021 | R80: JUNIO | S80: =X79 -> 1898250 | T80: =S80*3.5% -> 66438.75 | U80: =S80+T80 -> 1964688.8 | W80: 100000 | X80: =U80-W80 -> 1864688.8
A81: 2022 | B81: MARZO | C81: =H80 -> 4331371.5 | D81: =C81*3.5% -> 151598 | E81: =C81+D81 -> 4482969.5 | G81: 0 | H81: =E81-G81 -> 4482969.5 | J81: JULIO | K81: =P80 -> 2217435.8 | L81: =K81*3.5% -> 77610.251 | M81: =K81+L81 -> 2295046 | P81: =M81-O81 -> 2295046 | Q81: 2021 | R81: JULIO | S81: =X80 -> 1864688.8 | T81: =S81*3.5% -> 65264.106 | U81: =S81+T81 -> 1929952.9 | W81: 50000 | X81: =U81-W81 -> 1879952.9
A82: 2022 | B82: ABRIL | C82: =H81 -> 4482969.5 | D82: =C82*3.5% -> 156903.93 | E82: =C82+D82 -> 4639873.4 | G82: 0 | H82: =E82-G82 -> 4639873.4 | J82: AGOSTO | K82: =P81 -> 2295046 | L82: =K82*3.5% -> 80326.61 | M82: =K82+L82 -> 2375372.6 | P82: =M82-O82 -> 2375372.6 | Q82: 2021 | R82: AGOSTO | S82: =X81 -> 1879952.9 | T82: =S82*3.5% -> 65798.35 | U82: =S82+T82 -> 1945751.2 | W82: 0 | X82: =U82-W82 -> 1945751.2
A83: 2022 | B83: MAYO | C83: =H82 -> 4639873.4 | D83: =C83*3.5% -> 162395.57 | E83: =C83+D83 -> 4802269 | G83: 0 | H83: =E83-G83 -> 4802269 | J83: SEPTIEMBRE | K83: =P82 -> 2375372.6 | L83: =K83*3.5% -> 83138.041 | M83: =K83+L83 -> 2458510.7 | P83: =M83-O83 -> 2458510.7 | Q83: 2021 | R83: SEPTIEMBRE | S83: =X82 -> 1945751.2 | T83: =S83*3.5% -> 68101.292 | U83: =S83+T83 -> 2013852.5 | W83: 300000 | X83: =U83-W83 -> 1713852.5
A84: 2022 | B84: JUNIO | C84: =H83 -> 4802269 | D84: =C84*3.5% -> 168079.42 | E84: =C84+D84 -> 4970348.4 | G84: 0 | H84: =E84-G84 -> 4970348.4 | J84: OCTUBRE | K84: =P83 -> 2458510.7 | L84: =K84*3.5% -> 86047.873 | M84: =K84+L84 -> 2544558.5 | P84: =M84-O84 -> 2544558.5 | Q84: 2021 | R84: OCTUBRE | S84: =X83 -> 1713852.5 | T84: =S84*3.5% -> 59984.837 | U84: =S84+T84 -> 1773837.3 | X84: =U84-W84 -> 1773837.3
A85: 2022 | B85: JULIO | C85: =H84 -> 4970348.4 | D85: =C85*3.5% -> 173962.19 | E85: =C85+D85 -> 5144310.6 | G85: 0 | H85: =E85-G85 -> 5144310.6 | J85: NOVIEMBRE | K85: =P84 -> 2544558.5 | M85: =K85+L85 -> 2544558.5 | P85: =M85-O85 -> 2544558.5 | Q85: 2021 | R85: NOVIEMBRE | S85: =X84 -> 1773837.3 | T85: =S85*3.5% -> 62084.307 | U85: =S85+T85 -> 1835921.6 | W85: 200000 | X85: =U85-W85 -> 1635921.6
A86: 2022 | B86: AGOSTO | C86: =H85 -> 5144310.6 | D86: =C86*3.5% -> 180050.87 | E86: =C86+D86 -> 5324361.5 | G86: 0 | H86: =E86-G86 -> 5324361.5 | J86: DICIEMBRE | K86: =P85 -> 2544558.5 | M86: =K86+L86 -> 2544558.5 | P86: =M86-O86 -> 2544558.5 | Q86: 2021 | R86: DICIEMBRE | S86: =X85 -> 1635921.6 | T86: =S86*3.5% -> 57257.257 | U86: =S86+T86 -> 1693178.9 | W86: 100000 | X86: =U86-W86 -> 1593178.9
J87: ENERO | Q87: 2022 | R87: ENERO | S87: =X86 -> 1593178.9 | T87: =S87*3.5% -> 55761.262 | U87: =S87+T87 -> 1648940.2 | W87: 200000 | X87: =U87-W87 -> 1448940.2
J88: FEBRERO | Q88: 2022 | R88: FEBRERO | S88: =X87 -> 1448940.2 | T88: =S88*3.5% -> 50712.906 | U88: =S88+T88 -> 1499653.1 | W88: 150000 | X88: =U88-W88 -> 1349653.1
J89: MARZO | Q89: 2022 | R89: MARZO | S89: =X88 -> 1349653.1 | T89: =S89*3.5% -> 47237.857 | U89: =S89+T89 -> 1396890.9 | X89: =U89-W89 -> 1396890.9
B98: JOHANA BARONA 1 | J98: JOHANA BARONA 2 | R98: MARTIN CHAVEZ
B100: MES | C100: PRESTAMO | D100: INTERES | E100: DEUDA | G100: ABONO | H100: SALDO | J100: MES | K100: PRESTAMO | L100: INTERES | M100: DEUDA | O100: ABONO | P100: SALDO | R100: MES | S100: PRESTAMO | T100: INTERES | U100: DEUDA | W100: ABONO | X100: SALDO
A101: 2020 | B101: ENERO | C101: 600000 | D101: =C101*3.5% -> 21000 | E101: =C101+D101 -> 621000 | G101: 0 | H101: =E101-G101 -> 621000 | I101: 2020 | J101: FEBRERO | K101: 2000000 | L101: =K101*3.5% -> 70000 | M101: =K101+L101 -> 2070000 | O101: 0 | P101: =M101-O101 -> 2070000 | Q101: 2020 | R101: ENERO | S101: 1000000 | T101: =S101*3.5% -> 35000 | U101: =S101+T101 -> 1035000 | X101: =U101-W101 -> 1035000
A102: 2020 | B102: FEBRERO | C102: =H101 -> 621000 | D102: =C102*3.5% -> 21735 | E102: =C102+D102 -> 642735 | G102: 21000 | H102: =E102-G102 -> 621735 | I102: 2020 | J102: MARZO | K102: =P101 -> 2070000 | L102: =K102*3.5% -> 72450 | M102: =K102+L102 -> 2142450 | O102: 53000 | P102: =M102-O102 -> 2089450 | Q102: 2020 | R102: FEBRERO | S102: =X101 -> 1035000 | T102: =S102*3.5% -> 36225 | U102: =S102+T102 -> 1071225 | X102: =U102-W102 -> 1071225
A103: 2020 | B103: MARZO | C103: =H102 -> 621735 | D103: =C103*3.5% -> 21760.725 | E103: =C103+D103 -> 643495.72 | G103: 21000 | H103: =E103-G103 -> 622495.72 | I103: 2020 | J103: ABRIL | K103: =P102 -> 2089450 | L103: =K103*3.5% -> 73130.75 | M103: =K103+L103 -> 2162580.8 | O103: 0 | P103: =M103-O103 -> 2162580.8 | Q103: 2020 | R103: MARZO | S103: =X102 -> 1071225 | T103: =S103*3.5% -> 37492.875 | U103: =S103+T103 -> 1108717.9 | X103: =U103-W103 -> 1108717.9
A104: 2020 | B104: ABRIL | C104: =H103 -> 622495.72 | D104: =C104*3.5% -> 21787.35 | E104: =C104+D104 -> 644283.08 | G104: 21000 | H104: =E104-G104 -> 623283.08 | I104: 2020 | J104: MAYO | K104: =P103 -> 2162580.8 | L104: =K104*3.5% -> 75690.326 | M104: =K104+L104 -> 2238271.1 | O104: 0 | P104: =M104-O104 -> 2238271.1 | Q104: 2020 | R104: ABRIL | S104: =X103 -> 1108717.9 | T104: =S104*3.5% -> 38805.126 | U104: =S104+T104 -> 1147523 | X104: =U104-W104 -> 1147523
A105: 2020 | B105: MAYO | C105: =H104 -> 623283.08 | D105: =C105*3.5% -> 21814.908 | E105: =C105+D105 -> 645097.98 | G105: 0 | H105: =E105-G105 -> 645097.98 | I105: 2020 | J105: JUNIO | K105: =P104 -> 2238271.1 | L105: =K105*3.5% -> 78339.488 | M105: =K105+L105 -> 2316610.6 | O105: 0 | P105: =M105-O105 -> 2316610.6 | Q105: 2020 | R105: MAYO | S105: =X104 -> 1147523 | T105: =S105*3.5% -> 40163.305 | U105: =S105+T105 -> 1187686.3 | X105: =U105-W105 -> 1187686.3
A106: 2020 | B106: JUNIO | C106: =H105 -> 645097.98 | D106: =C106*3.5% -> 22578.429 | E106: =C106+D106 -> 667676.41 | G106: 0 | H106: =E106-G106 -> 667676.41 | I106: 2020 | J106: JULIO | K106: =P105 -> 2316610.6 | L106: =K106*3.5% -> 81081.37 | M106: =K106+L106 -> 2397691.9 | O106: 0 | P106: =M106-O106 -> 2397691.9 | Q106: 2020 | R106: JUNIO | S106: =X105 -> 1187686.3 | T106: =S106*3.5% -> 41569.021 | U106: =S106+T106 -> 1229255.3 | X106: =U106-W106 -> 1229255.3
A107: 2020 | B107: JULIO | C107: =H106 -> 667676.41 | D107: =C107*3.5% -> 23368.674 | E107: =C107+D107 -> 691045.09 | G107: 0 | H107: =E107-G107 -> 691045.09 | I107: 2020 | J107: AGOSTO | K107: =P106 -> 2397691.9 | L107: =K107*3.5% -> 83919.218 | M107: =K107+L107 -> 2481611.2 | O107: 0 | P107: =M107-O107 -> 2481611.2 | Q107: 2020 | R107: JULIO | S107: =X106 -> 1229255.3 | T107: =S107*3.5% -> 43023.936 | U107: =S107+T107 -> 1272279.3 | X107: =U107-W107 -> 1272279.3
A108: 2020 | B108: AGOSTO | C108: =H107 -> 691045.09 | D108: =C108*3.5% -> 24186.578 | E108: =C108+D108 -> 715231.66 | G108: 0 | H108: =E108-G108 -> 715231.66 | I108: 2020 | J108: SEPTIEMBRE | K108: =P107 -> 2481611.2 | L108: =K108*3.5% -> 86856.39 | M108: =K108+L108 -> 2568467.5 | O108: 0 | P108: =M108-O108 -> 2568467.5 | Q108: 2020 | R108: AGOSTO | S108: =X107 -> 1272279.3 | T108: =S108*3.5% -> 44529.774 | U108: =S108+T108 -> 1316809 | X108: =U108-W108 -> 1316809
A109: 2020 | B109: SEPTIEMBRE | C109: =H108 -> 715231.66 | D109: =C109*3.5% -> 25033.108 | E109: =C109+D109 -> 740264.77 | G109: 600000 | H109: =E109-G109 -> 140264.77 | I109: 2020 | J109: OCTUBRE | K109: =P108 -> 2568467.5 | L109: =K109*3.5% -> 89896.364 | M109: =K109+L109 -> 2658363.9 | O109: 0 | P109: =M109-O109 -> 2658363.9 | Q109: 2020 | R109: SEPTIEMBRE | S109: =X108 -> 1316809 | T109: =S109*3.5% -> 46088.316 | U109: =S109+T109 -> 1362897.4 | X109: =U109-W109 -> 1362897.4
A110: 2020 | B110: OCTUBRE | C110: =H109 -> 140264.77 | D110: =C110*3.5% -> 4909.2671 | E110: =C110+D110 -> 145174.04 | G110: 0 | H110: =E110-G110 -> 145174.04 | I110: 2020 | J110: NOVIEMBRE | K110: =P109 -> 2658363.9 | L110: =K110*3.5% -> 93042.737 | M110: =K110+L110 -> 2751406.6 | O110: 0 | P110: =M110-O110 -> 2751406.6 | Q110: 2020 | R110: OCTUBRE | S110: =X109 -> 1362897.4 | T110: =S110*3.5% -> 47701.407 | U110: =S110+T110 -> 1410598.8 | X110: =U110-W110 -> 1410598.8
A111: 2020 | B111: NOVIEMBRE | C111: =H110 -> 145174.04 | D111: =C111*3.5% -> 5081.0914 | E111: =C111+D111 -> 150255.13 | G111: 0 | H111: =E111-G111 -> 150255.13 | I111: 2020 | J111: DICIEMBRE | K111: =P110 -> 2751406.6 | L111: =K111*3.5% -> 96299.232 | M111: =K111+L111 -> 2847705.9 | O111: 0 | P111: =M111-O111 -> 2847705.9 | Q111: 2020 | R111: NOVIEMBRE | S111: =X110 -> 1410598.8 | T111: =S111*3.5% -> 49370.957 | U111: =S111+T111 -> 1459969.7 | X111: =U111-W111 -> 1459969.7
A112: 2020 | B112: DICIEMBRE | C112: =H111 -> 150255.13 | D112: =C112*3.5% -> 5258.9296 | E112: =C112+D112 -> 155514.06 | G112: 0 | H112: =E112-G112 -> 155514.06 | I112: 2021 | J112: ENERO | K112: =P111 -> 2847705.9 | L112: =K112*3.5% -> 99669.706 | M112: =K112+L112 -> 2947375.6 | O112: 0 | P112: =M112-O112 -> 2947375.6 | Q112: 2020 | R112: DICIEMBRE | S112: =X111 -> 1459969.7 | T112: =S112*3.5% -> 51098.94 | U112: =S112+T112 -> 1511068.7 | X112: =U112-W112 -> 1511068.7
A113: 2021 | B113: ENERO | C113: =H112 -> 155514.06 | D113: =C113*3.5% -> 5442.9921 | E113: =C113+D113 -> 160957.05 | G113: 0 | H113: =E113-G113 -> 160957.05 | I113: 2021 | J113: FEBRERO | K113: =P112 -> 2947375.6 | L113: =K113*3.5% -> 103158.15 | M113: =K113+L113 -> 3050533.7 | O113: 0 | P113: =M113-O113 -> 3050533.7 | Q113: 2021 | R113: ENERO | S113: =X112 -> 1511068.7 | T113: =S113*3.5% -> 52887.403 | U113: =S113+T113 -> 1563956.1 | X113: =U113-W113 -> 1563956.1
... A126: 2022 | B126: FEBRERO | C126: =H125 -> 243217.16 | D126: =C126*3.5% -> 8512.6005 | E126: =C126+D126 -> 251729.76 | G126: 0 | H126: =E126-G126 -> 251729.76 | I126: 2022 | J126: MARZO | K126: =P125 -> 2609565.9 | L126: =K126*3.5% -> 91334.807 | M126: =K126+L126 -> 2700900.7 | O126: 0 | P126: =M126-O126 -> 2700900.7 | Q126: 2022 | R126: FEBRERO | S126: =X125 -> 2363245 | T126: =S126*3.5% -> 82713.574 | U126: =S126+T126 -> 2445958.6 | X126: =U126-W126 -> 2445958.6
A127: 2022 | B127: MARZO | C127: =H126 -> 251729.76 | D127: =C127*3.5% -> 8810.5416 | E127: =C127+D127 -> 260540.3 | G127: 0 | H127: =E127-G127 -> 260540.3 | I127: 2022 | J127: ABRIL | K127: =P126 -> 2700900.7 | L127: =K127*3.5% -> 94531.525 | M127: =K127+L127 -> 2795432.2 | O127: 0 | P127: =M127-O127 -> 2795432.2 | Q127: 2022 | R127: MARZO
A128: 2022 | B128: ABRIL | C128: =H127 -> 260540.3 | D128: =C128*3.5% -> 9118.9105 | E128: =C128+D128 -> 269659.21 | G128: 0 | H128: =E128-G128 -> 269659.21 | I128: 2022 | J128: MAYO | K128: =P127 -> 2795432.2 | L128: =K128*3.5% -> 97840.128 | M128: =K128+L128 -> 2893272.4 | O128: 0 | P128: =M128-O128 -> 2893272.4 | Q128: 2022 | R128: ABRIL
A129: 2022 | B129: MAYO | C129: =H128 -> 269659.21 | D129: =C129*3.5% -> 9438.0724 | E129: =C129+D129 -> 279097.28 | G129: 0 | H129: =E129-G129 -> 279097.28 | I129: 2022 | J129: JUNIO | K129: =P128 -> 2893272.4 | L129: =K129*3.5% -> 101264.53 | M129: =K129+L129 -> 2994536.9 | O129: 0 | P129: =M129-O129 -> 2994536.9 | Q129: 2022 | R129: MAYO
A130: 2022 | B130: JUNIO | C130: =H129 -> 279097.28 | D130: =C130*3.5% -> 9768.4049 | E130: =C130+D130 -> 288865.69 | G130: 0 | H130: =E130-G130 -> 288865.69 | I130: 2022 | J130: JULIO | K130: =P129 -> 2994536.9 | L130: =K130*3.5% -> 104808.79 | M130: =K130+L130 -> 3099345.7 | O130: 0 | P130: =M130-O130 -> 3099345.7 | Q130: 2022 | R130: JUNIO
A131: 2022 | B131: JULIO | C131: =H130 -> 288865.69 | D131: =C131*3.5% -> 10110.299 | E131: =C131+D131 -> 298975.99 | G131: 0 | H131: =E131-G131 -> 298975.99 | I131: 2022 | J131: AGOSTO | K131: =P130 -> 3099345.7 | L131: =K131*3.5% -> 108477.1 | M131: =K131+L131 -> 3207822.8 | O131: 0 | P131: =M131-O131 -> 3207822.8 | Q131: 2022 | R131: JULIO
A132: 2022 | B132: AGOSTO | C132: =H131 -> 298975.99 | D132: =C132*3.5% -> 10464.16 | E132: =C132+D132 -> 309440.15 | G132: 0 | H132: =E132-G132 -> 309440.15 | I132: 2022 | J132: SEPTIEMBRE | K132: =P131 -> 3207822.8 | L132: =K132*3.5% -> 112273.8 | M132: =K132+L132 -> 3320096.6 | O132: 0 | P132: =M132-O132 -> 3320096.6 | Q132: 2022 | R132: AGOSTO
A133: 2022 | B133: SEPTIEMBRE | C133: =H132 -> 309440.15 | D133: =C133*3.5% -> 10830.405 | E133: =C133+D133 -> 320270.55 | G133: 0 | H133: =E133-G133 -> 320270.55 | I133: 2022 | J133: OCTUBRE | K133: =P132 -> 3320096.6 | L133: =K133*3.5% -> 116203.38 | M133: =K133+L133 -> 3436300 | O133: 0 | P133: =M133-O133 -> 3436300 | Q133: 2022 | R133: SEPTIEMBRE
A134: 2022 | B134: OCTUBRE | C134: =H133 -> 320270.55 | D134: =C134*3.5% -> 11209.469 | E134: =C134+D134 -> 331480.02 | G134: 0 | H134: =E134-G134 -> 331480.02 | I134: 2022 | J134: NOVIEMBRE | K134: =P133 -> 3436300 | L134: =K134*3.5% -> 120270.5 | M134: =K134+L134 -> 3556570.5 | O134: 0 | P134: =M134-O134 -> 3556570.5 | Q134: 2022 | R134: OCTUBRE
A135: 2022 | B135: NOVIEMBRE | C135: =H134 -> 331480.02 | D135: =C135*3.5% -> 11601.801 | E135: =C135+D135 -> 343081.82 | G135: 0 | H135: =E135-G135 -> 343081.82 | I135: 2022 | J135: DICIEMBRE | K135: =P134 -> 3556570.5 | L135: =K135*3.5% -> 124479.97 | M135: =K135+L135 -> 3681050.4 | O135: 0 | P135: =M135-O135 -> 3681050.4 | Q135: 2022 | R135: NOVIEMBRE
A136: 2022 | B136: DICIEMBRE | C136: =H135 -> 343081.82 | D136: =C136*3.5% -> 12007.864 | E136: =C136+D136 -> 355089.69 | G136: 0 | H136: =E136-G136 -> 355089.69 | I136: 2022 | J136: ENERO | K136: =P135 -> 3681050.4 | L136: =K136*3.5% -> 128836.76 | M136: =K136+L136 -> 3809887.2 | O136: 0 | P136: =M136-O136 -> 3809887.2 | Q136: 2022 | R136: DICIEMBRE

Sheet Vantage
A1: No | B1: NOMBRE | C1: USUARIO | D1: CONTRASEÑA | E1: IUD | F1: MT5 | G1: CELULAR | H1: invertido | I1: ganado
A2: 1 | B2: Diana Molina | C2: dianaleja0509@hotmail.com | D2: Diana.3000 | E2: 10752590 | F2: Usuario de MT5 28885678 Contraseña de MT5 @Y4WG$Be Servidor de MT5 VantageInternational-Live 5 Acc Type Raw ECN | G2: 3207593673 | H2: 1300 | I2: 200
A3: 2 | B3: Amparo Vidal | C3: juamvi2@hotmail.com | D3: Amparo.3000 | E3: 10772130 | F3: MT5 Login 28885992 MT5 Password Kk7qB&kk MT5 Server VantageInternational-Live 5 Acc Type Raw ECN | G3: 3175225336 | H3: 1268 | J3: ok
A4: 3 | B4: Jessica Perdomo | C4: alperdomo@gmail.com | D4: Perdomo.3000 | E4: 10772318 | F4: MT5 Login 28886050 MT5 Password i$82JCsv MT5 Server VantageInternational-Live 5 Acc Type Raw ECN | G4: 3008511288
A5: 4
